Workbook

Sheet pagos febrero
A1: DETALLE DE PAGOS EN BANCO
C3: MES DE FEBERO DE 2025
A4: Cuenta:Alborada 04-11-00-000468-4
A8: Fecha | B8: Recibo | C8: Descripción | D8: No.Casa | E8: Pagos | F8: Saldo total | G8: Columna1 | J8: Fecha | K8: Casa | L8: Recibo | M8: NOMBRE | N8: Monto
A9: 45696.354 | B9: 16701 al 16726 | C9: BANCA MOVIL TRANSFERENCIA DE 0427120001653 DAYRA LUCILA CANALES de SWANSTON ENTRE CUENTAS | E9: 52 | F9: 52 | G9: a | J9: 45694 | K9: 205 | L9: 16701 | M9: JAIME PEREZ | N9: 2 | O9: a
A10: 45696.354 | B10: 16727 | C10: YAPPY DE YOLANDA ENEIDA LOPER ALABARCA POR mantenimiento enero 2025 casa 271 | D10: 271 | E10: 20 | F10: =+F9+Tabla25[[#This Row],[Pagos]] -> 72 | G10: a | J10: 45695 | K10: 193 | L10: 16702 | M10: NURIA ELENA JIMENEZ de ABREGO | N10: 2 | O10: a
A11: 45696.354 | B11: 16728 | C11: YAPPY DE MARIA DE LOS ANGELES MONTENEGRO DE LEON POR cuota mes de enero 2025 | D11: 14 | E11: 15 | F11: =+F10+Tabla25[[#This Row],[Pagos]] -> 87 | G11: a | J11: 45695 | K11: 177 | L11: 16703 | M11: JOEL ALBERTO BELFORD PETERS | N11: 2 | O11: a
A12: 45696.354 | B12: 16729 | C12: YAPPY DE VIELKA LUZMILA CUSATTI ANAYA POR Pago de Mantenimiento casa 20 calle primer este | D12: 20 | E12: 20 | F12: =+F11+Tabla25[[#This Row],[Pagos]] -> 107 | G12: a | J12: 45695 | K12: 58 | L12: 16704 | M12: ODALIS DE MENESES | N12: 2 | O12: a
A13: 45696.354 | B13: 16730 | C13: YAPPY DE JAIME ALBERTO PEREZ MERO | D13: 205 | E13: 20 | F13: =+F12+Tabla25[[#This Row],[Pagos]] -> 127 | G13: a | J13: 45695 | K13: 179 | L13: 16705 | M13: ALMA IFIL | N13: 2 | O13: a
A14: 45696.354 | B14: 16731 | C14: YAPPY DE SHARYN TAVANE DELGADO ROWE POR Casa 199 pago mes de enero Sharyn Delgado | D14: 199 | E14: 15 | F14: =+F13+Tabla25[[#This Row],[Pagos]] -> 142 | G14: a | J14: 45695 | K14: 166 | L14: 16706 | M14: NATALIA KATIUSKA WARDROPE SANCHEZ | N14: 2 | O14: a
A15: 45696.354 | B15: 16732 | C15: YAPPY DE DAIZA BRU TORRES | D15: 143 | E15: 15 | F15: =+F14+Tabla25[[#This Row],[Pagos]] -> 157 | G15: a | J15: 45695 | K15: 8 | L15: 16707 | M15: DARINKA DANISETT DE HOYOS LOPEZ | N15: 2 | O15: a
A16: 45696.354 | B16: 16733 | C16: YAPPY DE JERONIMO VALENTIN HERNANDEZ CHIN | D16: 54 | E16: 15 | F16: =+F15+Tabla25[[#This Row],[Pagos]] -> 172 | G16: a | J16: 45695 | K16: 54 | L16: 16708 | M16: JERONIMO VALENTIN HERNANDEZ CHIN | N16: 2 | O16: a
A17: 45697.354 | B17: 16734 | C17: YAPPY DE JOANNA VANESSA EVERSLEY DE VALDES POR casa71 mes enero 2025 | D17: 71 | E17: 15 | F17: =+F16+Tabla25[[#This Row],[Pagos]] -> 187 | G17: a | J17: 45695 | K17: 75 | L17: 16709 | M17: VANESSA VICTORIA PARNTHER LUZCANDO | N17: 2 | O17: a
A18: 45697.354 | B18: 16735 | C18: YAPPY DE QUERUBI LIZET NEREIDA de HILTON | D18: 19 | E18: 15 | F18: =+F17+Tabla25[[#This Row],[Pagos]] -> 202 | G18: a | J18: 45695 | K18: 6 | L18: 16710 | M18: MIGUEL ROGELIO SANCHEZ PALACIO | N18: 2 | O18: a
A19: 45698.354 | B19: 16736 | C19: transferencia Iluminada Bonilla - casa 167- enero 2025 | D19: 167 | E19: 15 | F19: =+F18+Tabla25[[#This Row],[Pagos]] -> 217 | G19: a | J19: 45695 | K19: 117 | L19: 16711 | M19: SARALIZ LORENA HUSBAND DE VELASQUEZ | N19: 2 | O19: a
A20: 45698 | B20: 16737 | C20: fla ibarguen casa 21 enero | D20: 21 | E20: 15 | F20: =+F19+Tabla25[[#This Row],[Pagos]] -> 232 | G20: a | J20: 45695 | K20: 49 | L20: 16712 | M20: TAIRIN TATIANA ROBINSON de LASSONDE | N20: 2 | O20: a
A21: 45698.354 | B21: 16738 | C21: YAPPY DE GREGORIA HEIDI BRYAN RAMOS POR pago enero febrero casa196 | D21: 196 | E21: 30 | F21: =+F20+Tabla25[[#This Row],[Pagos]] -> 262 | G21: a | J21: 45695 | K21: 119 | L21: 16713 | M21: IRASEMA ESTHER MURILLO DE SMALL | N21: 2 | O21: a
... A27: 45700.354 | B27: 16744 | C27: BANCA MOVIL TRANSFERENCIA DE YISEL BONET ALTAMIRANDA de YARD pago mes de enero y feb casa | D27: 156 | E27: 30 | F27: =+F26+Tabla25[[#This Row],[Pagos]] -> 442 | G27: a | J27: 45695 | K27: 278 | L27: 16719 | M27: YAMILKA TUÑON ALCAZAR | N27: 2 | O27: a
A28: 45701.354 | B28: 16745 | C28: YAPPY DE ILKA MELISA MARK HOY | D28: 59 | E28: 15 | F28: =+F27+Tabla25[[#This Row],[Pagos]] -> 457 | G28: a | J28: 45695 | K28: D-9 | L28: 16720 | M28: ADELSA AYARIS AGUILAR ALVARADO | N28: 2 | O28: a
A29: 45701.354 | B29: 16746 | C29: BANCA MOVIL TRANSFERENCIA DE JOSE ALEJANDRO BARROWS ROBINSON casa 154 | D29: 154 | E29: 30 | F29: =+F28+Tabla25[[#This Row],[Pagos]] -> 487 | G29: a | J29: 45695 | K29: 130 | L29: 16721 | M29: ENRIQUE JOSE MARCANO GOMEZ | N29: 2 | O29: a
A30: 45702.354 | B30: 16747 | C30: BANCA MOVIL TRANSFERENCIA DE 0427120001653 DAYRA LUCILA CANALES de SWANSTON casa 50 Pablo Mejia | D30: 50 | E30: 15 | F30: =+F29+Tabla25[[#This Row],[Pagos]] -> 502 | G30: a | J30: 45695 | K30: 254 | L30: 16722 | M30: TATEANA JAEN | N30: 2 | O30: a
A31: 45702.354 | B31: 16748 | C31: BANCA EN LINEA TRANSFERENCIA DE LINDA YAJAIRA LAJON ANDERSON Pago seguridad Casa 219 enero | D31: 219 | E31: 30 | F31: =+F30+Tabla25[[#This Row],[Pagos]] -> 532 | G31: a | J31: 45695 | K31: 199 | L31: 16723 | M31: SHARYN TAVANE DELGADO ROWE | N31: 2 | O31: a
A32: 45702.354 | B32: 16749 | C32: YAPPY DE MARTIN LUIS MENESES TESIS POR FLIA Meneses 58 | D32: 58 | E32: 15 | F32: =+F31+Tabla25[[#This Row],[Pagos]] -> 547 | G32: a | J32: 45695 | K32: 140 | L32: 16724 | M32: FERNANDO NOAH ROSALES | N32: 2 | O32: a
A33: 45702.354 | B33: 16750 | C33: YAPPY DE PORFIRIO JUSTAVINO CEDEÑO | D33: 289 | E33: 30 | F33: =+F32+Tabla25[[#This Row],[Pagos]] -> 577 | G33: a | J33: 45695 | K33: 167 | L33: 16725 | M33: ILUMINADA BONILLA VIDAL | N33: 2 | O33: a
A34: 45703.354 | B34: 16751 | C34: BANCA MOVIL TRANSFERENCIA DE ROLANDO RODRIGO SIMS PEREZ Casa 314 enero y febrero 2025 | D34: 314 | E34: 30 | F34: =+F33+Tabla25[[#This Row],[Pagos]] -> 607 | G34: a | J34: 45695 | K34: 168 | L34: 16726 | M34: ILUMINADA BONILLA VIDAL | N34: 2 | O34: a
A35: 45703.354 | B35: 16752 | C35: BANCA MOVIL TRANSFERENCIA DE NORMA JAY SKERRITT VALENTINE Pago de seguridad ene y feb 2025 | D35: D-05 | E35: 30 | F35: =+F34+Tabla25[[#This Row],[Pagos]] -> 637 | G35: a
A36: 45703.354 | B36: 16753 | C36: YAPPY DE DAIZA BRU TORRES | D36: 143 | E36: 15 | F36: =+F35+Tabla25[[#This Row],[Pagos]] -> 652 | G36: a | N36: =SUM(N9:N34) -> 52
A37: 45703.354 | B37: 16754 | C37: BANCA MOVIL TRANSFERENCIA DE LUIS ENRIQUE AMADOR MARTINEZ A TERCEROS | D37: 195 | E37: 15 | F37: =+F36+Tabla25[[#This Row],[Pagos]] -> 667 | G37: a
A38: 45704.354 | B38: 16755 | C38: BANCA MOVIL TRANSFERENCIA DE DAYANARA ITZEL BENJAMIN DE DE LEON mens casa D 12 Flia De Leo | D38: D-12 | E38: 15 | F38: =+F37+Tabla25[[#This Row],[Pagos]] -> 682 | G38: a
A39: 45704.354 | B39: 16756 | C39: BANCA MOVIL TRANSFERENCIA DE CELIA ESTHER SALAZAR de PAULT Mes de enero casa 183 | D39: 183 | E39: 15 | F39: =+F38+Tabla25[[#This Row],[Pagos]] -> 697 | G39: a
A40: 45704.354 | B40: 16757 | C40: YAPPY DE JAIME ALBERTO PEREZ MERO | D40: 205 | E40: 15 | F40: =+F39+Tabla25[[#This Row],[Pagos]] -> 712 | G40: a
A41: 45704.354 | B41: 16758 | C41: YAPPY DE VANESSA VICTORIA PARNTHER LUZCANDO POR Mant casa 75 enero 2025 | D41: 75 | E41: 15 | F41: =+F40+Tabla25[[#This Row],[Pagos]] -> 727 | G41: a
A42: 45704.354 | B42: 16759 | C42: YAPPY DE MARTIN LUIS MENESES TESIS POR casa 57 Piedad del Cid | D42: 57 | E42: 15 | F42: =+F41+Tabla25[[#This Row],[Pagos]] -> 742 | G42: a
A43: 45704.354 | B43: 16760 | C43: YAPPY DE YARITZA YAMILKA COOPER CHIFUNDO POR Casa 202 Mes de Enero 2025 Schifundo - YCoope | D43: 202 | E43: 15 | F43: =+F42+Tabla25[[#This Row],[Pagos]] -> 757 | G43: a
A44: 45705.354 | B44: 16761 | C44: BANCA MOVIL TRANSFERENCIA DE ADELSA AYARIS AGUILAR ALVARADO casa D9 | D44: D9 | E44: 30 | F44: =+F43+Tabla25[[#This Row],[Pagos]] -> 787 | G44: a
A45: 45705.354 | B45: 16762 | C45: Magaly de Vivero | D45: 145 | E45: 15 | F45: =+F44+Tabla25[[#This Row],[Pagos]] -> 802 | G45: a
A46: 45705.354 | B46: 16763 | C46: BANCA MOVIL TRANSFERENCIA DE NILKA LORENA DEL CASTILLO ZELAYA seguridad y mantenimiento ca | D46: 135 | E46: 30 | F46: =+F45+Tabla25[[#This Row],[Pagos]] -> 832 | G46: a
A47: 45705.354 | B47: 16764 | C47: YAPPY DE YOLANDA ENEIDA LOPER ALABARCA POR mantenimiento febrero 2025 casa 271 | D47: 271 | E47: 20 | F47: =+F46+Tabla25[[#This Row],[Pagos]] -> 852 | G47: a
A48: 45705.354 | B48: 16765 | C48: YAPPY DE JAZMINA ITZEL VEGA de SMITH POR seguridad y Mant enero y feb 2025 casa 328 n | D48: 328 | E48: 30 | F48: =+F47+Tabla25[[#This Row],[Pagos]] -> 882 | G48: a
A49: 45705.354 | B49: 16766 | C49: YAPPY DE EDGAR PAUL ORTEGA PIMENTEL POR Mant Casa 323 Flia Ortega Ene y Feb | D49: 323 | E49: 30 | F49: =+F48+Tabla25[[#This Row],[Pagos]] -> 912 | G49: a
A50: 45705.354 | B50: 16767 | C50: BANCA MOVIL TRANSFERENCIA DE BARBARA ANN BENDIGO DE SANTAMARIA Mantenimiento Enero y Feb 2 | D50: 44 | E50: 30 | F50: =+F49+Tabla25[[#This Row],[Pagos]] -> 942 | G50: a
A51: 45705.354 | B51: 16768 | C51: YAPPY DE YELENA DELIBETH ALVEAR ARCIA | D51: 174 | E51: 30 | F51: =+F50+Tabla25[[#This Row],[Pagos]] -> 972 | G51: a
A52: 45705.354 | B52: 16769 | C52: YAPPY DE VANESSA VICTORIA PARNTHER LUZCANDO POR Mant mes de Febrero casa 30 y casa 75 2da | D52: 30 y 75 | E52: 30 | F52: =+F51+Tabla25[[#This Row],[Pagos]] -> 1002 | G52: a
A53: 45706.354 | B53: 16770 | C53: YAPPY DE NAYRA DEL CARMEN RAMOS RAMOS (O) JERONIMO VALENTIN HERNANDEZ POR gasto de garita | D53: 54 | E53: 15 | F53: =+F52+Tabla25[[#This Row],[Pagos]] -> 1017 | G53: a
A54: 45706.354 | B54: 16771 | C54: YAPPY DE NITZIA ITZEL AGUILAR GALVAN POR pago de garita | D54: 56 | E54: 15 | F54: =+F53+Tabla25[[#This Row],[Pagos]] -> 1032 | G54: a
A55: 45706.354 | B55: 16772 | C55: YAPPY DE OSVALDO HERRERA CARRIAZO POR Casa 53 Flia Herrera Garita | D55: 53 | E55: 15 | F55: =+F54+Tabla25[[#This Row],[Pagos]] -> 1047 | G55: a
A56: 45706.354 | B56: 16773 | C56: YAPPY DE ELOISA MALENY JAEN GUTIERREZ | D56: 185 | E56: 15 | F56: =+F55+Tabla25[[#This Row],[Pagos]] -> 1062 | G56: a
A57: 45706.354 | B57: 16774 | C57: YAPPY DE CRISALIDA SOLIS CAMERON | D57: 52 | E57: 15 | F57: =+F56+Tabla25[[#This Row],[Pagos]] -> 1077 | G57: a
A58: 45706.354 | B58: 16775 | C58: ANULADO | E58: 0 | F58: =+F57+Tabla25[[#This Row],[Pagos]] -> 1077 | G58: a
A59: 45706 | B59: 16859 | C59: YAPPY DE EMMANUEL ESTEBAN CABRERA MARTINEZ POR Flia Bennett casa 56 | D59: 55 | E59: 15 | F59: =+F58+Tabla25[[#This Row],[Pagos]] -> 1092
A60: 45707.354 | B60: 16776 | C60: BANCA MOVIL TRANSFERENCIA DE MIGUEL ROGELIO SANCHEZ PALACIO (O) GICELLE NATALIA HENRIQUEZ | D60: 6 | E60: 30 | F60: =+F59+Tabla25[[#This Row],[Pagos]] -> 1122 | G60: a
A61: 45707.354 | B61: 16777 | C61: YAPPY DE MALIBETZA FAUSTINA CEBALLOS de COMBE | D61: 35 | E61: 15 | F61: =+F60+Tabla25[[#This Row],[Pagos]] -> 1137 | G61: a
A62: 45708 | B62: 16778 | C62: DEPOSITO CUENTA DE AHORROS SIN LIBRETA | D62: 95 | E62: 30 | F62: =+F61+Tabla25[[#This Row],[Pagos]] -> 1167 | G62: a
A63: 45708.64 | B63: 16779 | C63: YAPPY DE MIOZOTIS DEL CARMEN OLMOS LARA | D63: 10 | E63: 30 | F63: =+F62+Tabla25[[#This Row],[Pagos]] -> 1197 | G63: a
A64: 45708.64 | B64: 16780 | C64: YAPPY DE CARLOS ENRIQUE GARAY DOMINGUEZ | D64: 4 | E64: 15 | F64: =+F63+Tabla25[[#This Row],[Pagos]] -> 1212 | G64: a
A65: 45708.64 | B65: 16781 | C65: BANCA MOVIL TRANSFERENCIA DE JOSE LUIS GONZALEZ FLETCHER (O) MAIQUEL ITZELA POLLACK MENDO | D65: 247 | E65: 15 | F65: =+F64+Tabla25[[#This Row],[Pagos]] -> 1227 | G65: a
A66: 45709.64 | B66: 16782 | C66: YAPPY DE ANSELMO EMILIANO FORDE CHRISTOPHER POR Anselmo Forde casa 5 Ira Oeste | D66: 5 | E66: 15 | F66: =+F65+Tabla25[[#This Row],[Pagos]] -> 1242 | G66: a
A67: 45709.64 | B67: 16783 | C67: YAPPY DE NATALIA KATIUSKA WARDROPE SANCHEZ POR German Martinez 4ta oeste casa 166 | D67: 166 | E67: 30 | F67: =+F66+Tabla25[[#This Row],[Pagos]] -> 1272 | G67: a
A68: 45710.64 | B68: 16784 | C68: BANCA MOVIL TRANSFERENCIA DE NATIVIDAD VALENCIA de JIMENEZ Familia Jimenez Casa 26 Mant En | D68: 26 | E68: 30 | F68: =+F67+Tabla25[[#This Row],[Pagos]] -> 1302 | G68: a
A69: 45710.64 | B69: 16785 | C69: YAPPY DE DANIEL ALEXIS FORBES AVILA POR pago de enero y febrerocasa 204 | D69: 204 | E69: 30 | F69: =+F68+Tabla25[[#This Row],[Pagos]] -> 1332 | G69: a
A70: 45710.64 | B70: 16786 | C70: YAPPY DE YARIBEL RUIZ DE GRACIA POR casa 41 calle 1 familia Betegon | D70: 41 | E70: 20 | F70: =+F69+Tabla25[[#This Row],[Pagos]] -> 1352 | G70: a
A71: 45710.64 | B71: 16787 | C71: YAPPY DE DIANA MARIA SANCHEZ FLORES | D71: D-24 | E71: 15 | F71: =+F70+Tabla25[[#This Row],[Pagos]] -> 1367 | G71: a
A72: 45710.64 | B72: 16788 | C72: YAPPY DE VIELKA GISELA MORAN MC COY de LOPEZ POR Familia Lopez casa 65 febrero marzo abril | D72: 65 | E72: 60 | F72: =+F71+Tabla25[[#This Row],[Pagos]] -> 1427 | G72: a
A73: 45710.64 | B73: 16789 | C73: YAPPY DE EDIANI YENISEL MARTINEZ ARAUZ POR Mensualidad febrero casa 198 | D73: 198 | E73: 15 | F73: =+F72+Tabla25[[#This Row],[Pagos]] -> 1442 | G73: a
A74: 45711.64 | B74: 16790 | C74: BANCA MOVIL TRANSFERENCIA DE YENITZA NAYROBIS ASHAW SMALL cuota de febrero casa 261 | D74: 261 | E74: 15 | F74: =+F73+Tabla25[[#This Row],[Pagos]] -> 1457 | G74: a
A75: 45711.64 | B75: 16791 | C75: YAPPY DE GABRIEL BURNHAM CHARRIS POR Casa 242 Familia Burnham Mes De Febrero 2025 | D75: 242 | E75: 15 | F75: =+F74+Tabla25[[#This Row],[Pagos]] -> 1472 | G75: a
A76: 45712.64 | B76: 16792 | C76: YAPPY DE ANTONIO ALCEDO AGUIRRE POR Casa 217 Febrero | D76: 217 | E76: 15 | F76: =+F75+Tabla25[[#This Row],[Pagos]] -> 1487 | G76: a
A77: 45712.64 | B77: 16793 | C77: ACH - PAMELA PATRICIA PETERS BAILEY | D77: 177 | E77: 45 | F77: =+F76+Tabla25[[#This Row],[Pagos]] -> 1532 | G77: a
A78: 45707.354 | B78: 16794 | C78: YAPPY DE TAIRIN TATIANA ROBINSON de LASSONDE | D78: 49 | E78: 15 | F78: =+F77+Tabla25[[#This Row],[Pagos]] -> 1547 | G78: a
A79: 45712.64 | B79: 16795 | C79: DEPOSITO CUENTA DE AHORROS SIN LIBRETA | E79: 15 | F79: =+F78+Tabla25[[#This Row],[Pagos]] -> 1562 | G79: a
A80: 45712.64 | B80: 16796 | C80: ACH - SYAHMAR MILENN ORTIZ CASTILLO | D80: 46 | E80: 30 | F80: =+F79+Tabla25[[#This Row],[Pagos]] -> 1592 | G80: a
A81: 45712.64 | B81: 16797 | C81: YAPPY DE MANUEL DE JESUS MEDINA ORTEGA POR Casa 25 - Flia Medina enero-febrero | D81: 25 | E81: 30 | F81: =+F80+Tabla25[[#This Row],[Pagos]] -> 1622 | G81: a
A82: 45712.64 | B82: 16798 | C82: YAPPY DE EMELINA IVETT CATUY ALARCON | D82: 68 | E82: 15 | F82: =+F81+Tabla25[[#This Row],[Pagos]] -> 1637 | G82: a
A83: 45713.64 | B83: 16799 | C83: YAPPY DE ERIC ARIEL VILLANUEVA (O) AIMAR ELIESER VILLANUEVA ARCHIBALD POR pago seguridad f | D83: 236 | E83: 15 | F83: =+F82+Tabla25[[#This Row],[Pagos]] -> 1652 | G83: a
A84: 45713.64 | B84: 16800 | C84: YAPPY DE MANUEL ENRIQUE VILLARREAL GUILLEN POR seguridad enero febrero 2025 casa 103 | D84: 103 | E84: 30 | F84: =+F83+Tabla25[[#This Row],[Pagos]] -> 1682 | G84: a
A85: 45713 | B85: 16801 | C85: YAPPY DE ISABEL RIQUELME MARTINEZ POR Enero y Febrero Casa277 flia Riquelme Luque | D85: 277 | E85: 30 | F85: =+F84+Tabla25[[#This Row],[Pagos]] -> 1712 | G85: a
A86: 45714 | B86: 16802 | C86: YAPPY DE YURIBETH YAILYN LEE | D86: 64 | E86: 30 | F86: =+F85+Tabla25[[#This Row],[Pagos]] -> 1742 | G86: a
A87: 45714 | B87: 16803 | C87: DARINKA CASA 8 FEBRERO Y MARZO | D87: 8 | E87: 30 | F87: =+F86+Tabla25[[#This Row],[Pagos]] -> 1772 | G87: a
A88: 45714 | B88: 16804 | C88: DAYRA CANALES - ENERO Y FEBRERO | D88: 240 | E88: 28 | F88: =+F87+Tabla25[[#This Row],[Pagos]] -> 1800 | G88: a
A89: 45714 | C89: BANCA MÓVIL TIGO HOGAR - PYME (88280329) | E89: -168.81 | F89: =+F88+E89 -> 1631.19
A90: 45714 | C90: PAGO IDAAN | E90: -275.47 | F90: =+F89+E90 -> 1355.72
A91: 45714 | C91: BANCA EN LÍNEA ENSA (ELEKTRA NORESTE) (000000882669) | E91: -108.86 | F91: =+F90+E91 -> 1246.86
A92: 45714.375 | B92: 16805 | C92: BANCA MOVIL TRANSFERENCIA DE GYSELLE DEYANIRA GRANT DE SIMPSON FEBRERO CASA 265 Gyselle Gr | D92: 265 | E92: 15 | F92: =+F91+E92 -> 1261.86 | G92: a
A93: 45714.375 | B93: 16806 | C93: YAPPY DE AMILKAR MORENO RIOS POR Mantenimiento Casa 36 Enero y Febrero | D93: 36 | E93: 30 | F93: =+F92+E93 -> 1291.86 | G93: a
A94: 45714.375 | B94: 16807 | C94: YAPPY DE NIDIA EDITH RODRIGUEZ ORTIZ POR Pago del mes de febrero Flia Rodriguez casa 267 | D94: 267 | E94: 15 | F94: =+F93+E94 -> 1306.86 | G94: a
A95: 45715.375 | B95: 16808 | C95: BANCA MOVIL TRANSFERENCIA DE CARLOS ANTONIO MORAN MC COY Seguridad y mantenimiento familia | D95: 251 | E95: 15 | F95: =+F94+E95 -> 1321.86 | G95: a
A96: 45715.375 | B96: 16809 | C96: ACH - EMILIO STERLING LOVET WILSON | D96: 67 | E96: 15 | F96: =+F95+E96 -> 1336.86 | G96: a
A97: 45715.375 | B97: 16810 | C97: BANCA EN LINEA TRANSFERENCIA DE DAYRA ISABEL FLORES DE MORENO CASA D1 FEB MAR ABR | D97: D-01 | E97: 45 | F97: =+F96+E97 -> 1381.86 | G97: a
A98: 45715.375 | B98: 16811 | C98: YAPPY DE GLADYS OSIRIS VILLANUEVA DE AGUILAR | D98: 37 | E98: 15 | F98: =+F97+E98 -> 1396.86 | G98: a
A99: 45716.375 | B99: 16812 | C99: YAPPY DE MARTIN LUIS MENESES TESIS POR FLIAMeneses 58 Febrero | D99: 58 | E99: 15 | F99: =+F98+E99 -> 1411.86 | G99: a
A100: 45716.375 | B100: 16813 | C100: YAPPY DE JENIFER ODALILIA MORENO DE WELLER POR Febrero - Familia Weller Moreno casa 146 | D100: 146 | E100: 15 | F100: =+F99+E100 -> 1426.86 | G100: a
A101: 45716.375 | B101: 16814 | C101: BANCA MOVIL TRANSFERENCIA DE DALIS YADIRA BANDINI AGUSTINE Pago Seg y mant CASA 178 FLIA B | D101: 178 | E101: 30 | F101: =+F100+E101 -> 1456.86 | G101: a
A102: 45716.375 | B102: 16815 | C102: YAPPY DE JAIME DAVID ANDERSON SINCLAIR | D102: 172 | E102: 15 | F102: =+F101+E102 -> 1471.86 | G102: a
A103: 45716.375 | B103: 16816 | C103: YAPPY DE SHARYN TAVANE DELGADO ROWE POR Casa 199 - mes de febrero | D103: 199 | E103: 15 | F103: =+F102+E103 -> 1486.86 | G103: a
A104: 45716.375 | B104: 16817 | C104: YAPPY DE KAISHA TAMARA RIVAS JULIO | D104: 79 | E104: 15 | F104: =+F103+E104 -> 1501.86 | G104: a
A105: 45716.375 | B105: 16818 | C105: YAPPY DE IDA CEMA JACKSON de VALENCIA | D105: 270 | E105: 15 | F105: =+F104+E105 -> 1516.86
A106: 45716.375 | C106: INTERES CUENTA DE AHORROS | E106: 0.56 | F106: =+F105+E106 -> 1517.42

Sheet pagos marzo 2025
A1: DETALLE DE PAGOS EN BANCO
B2: MES DE MARZO DE 2025
A4: Cuenta:Alborada 04-11-00-000468-4
A8: Fecha | B8: Recibo | C8: Descripción | D8: No.Casa | E8: Pagos | F8: Saldo total
A10: 45716.375 | C10: SALDO AL 28 DE FEBRERO DE 2025 | E10: 1517.42 | F10: =+E10 -> 1517.42
A11: 45717.375 | B11: 16819 | C11: YAPPY DE ROBERTO RODRIGUEZ PEREIRA POR Paga casa 43 familia Rodriguez enero y febrero | D11: 43 | E11: 30 | F11: =+F13+E11 -> 1622.42 | G11: a
A12: 45717.375 | B12: 16820 | C12: EFECTIVO FLIA VANEGAS -CASA 200 ENERO -FEBRERO Y MARZO | D12: 200 | E12: 45 | F12: =+F10+E12 -> 1562.42 | G12: a
A13: 45717.375 | B13: 16821 | C13: EFECTIVO DELANO SANDERS - CASA 285 FEBRERO Y MARZO | D13: 285 | E13: 30 | F13: =+F12+E13 -> 1592.42 | G13: a
A14: 45717.375 | B14: 16822 | C14: YAPPY DE PASTOR CAMARENA SMITH | D14: D-10 | E14: 30 | F14: =+F11+E14 -> 1652.42 | G14: a
A15: 45718.375 | B15: 16823 | C15: YAPPY DE JULIO ENRIQUE MEJIA POR Seguridad y mantenimiento Casa 291 Flia Mejia Nino | D15: 291 | E15: 30 | F15: =+F14+E15 -> 1682.42 | G15: a
A16: 45718.375 | B16: 16824 | C16: BANCA MOVIL TRANSFERENCIA DE LEOPOLDO QUINTERO VALDES (O) LUZMILA ELENA PORTER DE QUINTER | D16: 47 | E16: 30 | F16: =+F15+E16 -> 1712.42 | G16: a
A17: 45718.375 | B17: 16825 | C17: YAPPY DE YAVIRITZEL DEL CARMEN PANAY POR Enero y febrero casa 187 | D17: 187 | E17: 30 | F17: =+F16+E17 -> 1742.42 | G17: a
A18: 45718.375 | B18: 16826 | C18: YAPPY DE YESICA MARLENE CHIFUNDO DE PRESTAN POR Seguridad y mantenimiento de casa 210 Flia | D18: 210 | E18: 30 | F18: =+F17+E18 -> 1772.42 | G18: a
A19: 45718.375 | B19: 16827 | C19: YAPPY DE SARALIZ LORENA HUSBAND DE VELASQUEZ POR casa 117 tercera oeste flia Velasquez | D19: 117 | E19: 30 | F19: =+F18+E19 -> 1802.42 | G19: a
A20: 45718.375 | B20: 16828 | C20: YAPPY DE SUMAYKIRA YANILET GRENALD FERREIRA POR Pago de Casa 136 familia Grenald mantenimi | D20: 136 | E20: 30 | F20: =+F19+E20 -> 1832.42 | G20: a
A21: 45718.375 | B21: 16829 | C21: YAPPY DE NATIVIDAD SANCHEZ DE FORBES | D21: 175 | E21: 30 | F21: =+F20+E21 -> 1862.42 | G21: a
A22: 45718.375 | B22: 16830 | C22: YAPPY DE ISAIAS FRANCISCO TATE BENJAMIN POR mes de enero casa 239 Tate | D22: 239 | E22: 15 | F22: =+F21+E22 -> 1877.42 | G22: a
A23: 45718.375 | B23: 16831 | C23: YAPPY DE YARITZA YAMILKA COOPER CHIFUNDO POR Mes de febrero Casa 202 Silvina Chifundo Yari | D23: 202 | E23: 15 | F23: =+F22+E23 -> 1892.42 | G23: a
A24: 45718.375 | B24: 16832 | C24: YAPPY DE ANTONIO ALCEDO AGUIRRE POR Casa 217 Enero | D24: 217 | E24: 15 | F24: =+F23+E24 -> 1907.42 | G24: a
A25: 45718.375 | B25: 16833 | C25: BANCA MOVIL TRANSFERENCIA DE FELICIA OLIVIA GITTENS MERCHANT Casa 40 Flia GittensZachary m | D25: 40 | E25: 45 | F25: =+F24+E25 -> 1952.42 | G25: a
A26: 45718.375 | B26: 16834 | C26: BANCA MOVIL TRANSFERENCIA DE NATIVIDAD VALENCIA de JIMENEZ mantenimiento de marzo Casa N 2 | D26: 26 | E26: 15 | F26: =+F25+E26 -> 1967.42 | G26: a
... A50: 45722 | B50: 16858 | C50: Luis Levy - mant. -febrero | D50: 234 | E50: 15 | F50: =+F49+E50 -> 2487.42 | G50: a
B51: 16859 | C51: recibo reemplazo recibo 16775 del 18/02/2025 | E51: 0 | F51: =+F50+E51 -> 2487.42 | G51: a
A52: 45724 | B52: 16860 | C52: Delano Saunders - mant, enero | D52: 285 | E52: 15 | F52: =+F51+E52 -> 2502.42 | G52: a
A53: 45724 | B53: 16861 | C53: Pablo Mejia - mant. Marzo y abril | D53: 50 | E53: 30 | F53: =+F52+E53 -> 2532.42 | G53: a
A54: 45724 | B54: 16862 | C54: Ilka Mack -mant-marzo | D54: 59 | E54: 15 | F54: =+F53+E54 -> 2547.42 | G54: a
A55: 45724 | B55: 16863 | C55: Flia. Mc Laughlin - mant. Enero y febrero | D55: 161 | E55: 30 | F55: =+F54+E55 -> 2577.42 | G55: a
A56: 45721 | B56: 16864 | C56: BANCA MOVIL TRANSFERENCIA DE TAMARA YEZENIA CATUY de PACHECO SEG ENERO FEBRERO MARZO C160 | D56: 160 | E56: 45 | F56: =+F55+E56 -> 2622.42 | G56: a
A57: 45722 | B57: 16865 | C57: BANCA MOVIL TRANSFERENCIA DE MARLENE BOYCE DAWKINS casa 181 Enero y febrero | D57: 181 | E57: 30 | F57: =+F56+E57 -> 2652.42 | G57: a
A58: 45722 | B58: 16866 | C58: YAPPY DE YOLANDA ENEIDA LOPER ALABARCA POR mantenimiento marzo 2025 casa 271 | D58: 271 | E58: 20 | F58: =+F57+E58 -> 2672.42 | G58: a
A59: 45722 | B59: 16867 | C59: ACH - YOHANA LISBETH MOLINAR MARIN DE GONDOLA- febrero | D59: 113 | E59: 15 | F59: =+F58+E59 -> 2687.42 | G59: a
A60: 45722 | B60: 16868 | C60: YAPPY DE MARTHA BIBIANA ACOSTA MARULANDA POR casa 105 familia Estrada meses de enero a mar | D60: 105 | E60: 45 | F60: =+F59+E60 -> 2732.42 | G60: a
A61: 45722 | B61: 16869 | C61: YAPPY DE IRASEMA ESTHER MURILLO DE SMALL | D61: 119 | E61: 30 | F61: =+F60+E61 -> 2762.42 | G61: a
A62: 45722 | B62: 16870 | C62: YAPPY DE MIOZOTIS DEL CARMEN OLMOS LARA- marzo | D62: 10 | E62: 15 | F62: =+F61+E62 -> 2777.42 | G62: a
A63: 45723 | B63: 16871 | C63: YAPPY DE YAZMIN DAMARIS SOTO PIMENTEL | D63: 162 | E63: 30 | F63: =+F62+E63 -> 2807.42 | G63: a
... A97: 45733 | B97: 16905 | C97: AURA HURTADO - ENERO A MARZO | D97: 9 | E97: 45 | F97: =+F96+E97 -> 4047.42 | G97: a
B98: 16906 | C98: ANULADO | F98: =+F97+E98 -> 4047.42 | G98: a
B99: 16907 | C99: ANULADO | F99: =+F98+E99 -> 4047.42 | G99: a
A100: 45727.8 | B100: 16908 | C100: BANCA MOVIL TRANSFERENCIA DE DAMARIS ESTHER SARMIENTO de MARTINEZ CASA 324 MARTINEZ SARMIE -ENERO Y FEBRERO | D100: 324 | E100: 30 | F100: =+F99+E100 -> 4077.42 | G100: a
A101: 45727.8 | B101: 16909 | C101: BANCA MOVIL TRANSFERENCIA DE GISELA GONZALEZ QUIROZ Casa 88 Gisela Gonzalez Enero a Abril | D101: 88 | E101: 60 | F101: =+F100+E101 -> 4137.42 | G101: a
A102: 45727.8 | B102: 16910 | C102: YAPPY DE NIDIA ROSA BOHORQUEZ de MARTINEZ enero - febrero | D102: 63 | E102: 30 | F102: =+F101+E102 -> 4167.42 | G102: a
A103: 45727.8 | B103: 16911 | C103: FLIA CHIRU | D103: 292 | E103: 15 | F103: =+F102+E103 -> 4182.42 | G103: a
A104: 45727.8 | B104: 16912 | C104: YAPPY DE EMELINA IVETT CATUY ALARCON POR casa 68 familia Pacheco catuy recibo al nombre de | D104: 68 | E104: 15 | F104: =+F103+E104 -> 4197.42 | G104: a
A105: 45728.8 | B105: 16913 | C105: BANCA MOVIL TRANSFERENCIA DE MARCELA PAVIA de LAJON (TRANSPORTE LAJON) Pago Enero Febrero | D105: D-06 | E105: 45 | F105: =+F104+E105 -> 4242.42 | G105: a
A106: 45728.8 | B106: 16914 | C106: DEPOSITO CUENTA DE AHORROS SIN LIBRETA FLIA CAMPOS - | D106: 304 | E106: 15 | F106: =+F105+E106 -> 4257.42 | G106: a
A107: 45728.8 | B107: 16915 | C107: ACH - MUNOZ BALLARD YIRA ENERO -ABRIL CASA 73 | D107: 73 | E107: 60 | F107: =+F106+E107 -> 4317.42 | G107: a
A108: 45728.8 | B108: 16916 | C108: BANCA MOVIL TRANSFERENCIA DE ALEXANDRIA URSULA TAYLOR pago seguridad enero a dic 2024 | D108: 226 | E108: 180 | F108: =+F107+E108 -> 4497.42 | G108: a
A109: 45728.8 | B109: 16917 | C109: BANCA MOVIL TRANSFERENCIA DE CARLOS ERNESTO LAMBERT PEREZ A TERCEROS | D109: 223 | E109: 30 | F109: =+F108+E109 -> 4527.42 | G109: a
A110: 45728.8 | B110: 16918 | C110: YAPPY DE MARIBEL ARISPE de VEGA - ENERO Y FEBRERO | D110: 296 | E110: 30 | F110: =+F109+E110 -> 4557.42 | G110: a
A111: 45728.8 | B111: 16919 | C111: YAPPY DE SONIA ISABEL RODRIGUEZ de MURILLO POR Familia MurilloRodriguez casa 34 enerofebre | D111: 34 | E111: 45 | F111: =+F110+E111 -> 4602.42 | G111: a
A112: 45728.8 | B112: 16920 | C112: BANCA MOVIL TRANSFERENCIA DE BOLIVAR RODRIGUEZ TORIBIO Alborada casa 295 flia Rodriguez Le | D112: 295 | E112: 45 | F112: =+F111+E112 -> 4647.42 | G112: a
A113: 45729.8 | B113: 16921 | C113: YAPPY DE ADDIS MASSIEL BETEGON ROSALES POR Casa 33 enero febrero marzo Familia Betegon Ros | D113: 33 | E113: 45 | F113: =+F112+E113 -> 4692.42 | G113: a
A114: 45729.8 | B114: 16922 | C114: YAPPY DE ROSEMENE SERVILIUS MEDIEU (CARIBBEAN FOOD GOURMET) | D114: 182 | E114: 15 | F114: =+F113+E114 -> 4707.42 | G114: a | H114: casa 182
A115: 45729.8 | B115: 16923 | C115: YAPPY DE MAUREL MARIAM MIER de ESCOBAR -FLIA escobar - febrero y marzo | D115: 221 | E115: 30 | F115: =+F114+E115 -> 4737.42 | G115: a | H115: CASA 221 EN ABRIL
A116: 45729.8 | B116: 16924 | C116: ACH - JASMIN SUSAN JOHNSON FORBES - ENERO | D116: 42 | E116: 15 | F116: =+F115+E116 -> 4752.42 | G116: a
A117: 45729.8 | B117: 16925 | C117: YAPPY DE VANESSA VICTORIA PARNTHER LUZCANDO POR Mant casa 80 de Enero a Abril 2025 calle 2 | D117: 80 | E117: 60 | F117: =+F116+E117 -> 4812.42 | G117: a
A118: 45729.8 | B118: 16926 | C118: YAPPY DE EDGAR PAUL ORTEGA PIMENTEL POR Casa 323 Flia Ortega Mar y Abr | D118: 323 | E118: 30 | F118: =+F117+E118 -> 4842.42 | G118: a
A119: 45729.8 | B119: 16927 | C119: YAPPY DE JOSE DAVID BONILLA ALVARADO POR Pago Garita Enero y Febrero 2025 Casa D14 Flia Bo | D119: D-14 | E119: 30 | F119: =+F118+E119 -> 4872.42 | G119: a
A120: 45730.8 | B120: 16928 | C120: YAPPY DE JAIME ALBERTO PEREZ MERO - MARZO | D120: 205 | E120: 15 | F120: =+F119+E120 -> 4887.42 | G120: a
A121: 45730.8 | B121: 16929 | C121: YAPPY DE LINETH GISSEL SANTOS MELENDEZ POR enero febrero y marzo familia Paz casa 7 | D121: 7 | E121: 45 | F121: =+F120+E121 -> 4932.42 | G121: a
A122: 45735.696 | B122: 16930 | C122: CASA 89 LORREAINE ALEXANDER - MARZO | D122: 89 | E122: 15 | F122: =+F121+E122 -> 4947.42 | G122: a
A123: 45737 | B123: 16931 | C123: PIEDAD DEL CID - CASA 57 | D123: 57 | E123: 15 | F123: =+F122+E123 -> 4962.42 | G123: a
A124: 45730.8 | B124: 16932 | C124: BANCA MOVIL TRANSFERENCIA DE LINDA YAJAIRA LAJON ANDERSON Casa 219 marzo y abril | D124: 219 | E124: 30 | F124: =+F123+E124 -> 4992.42 | G124: a
A125: 45730.8 | B125: 16933 | C125: BANCA EN LINEA TRANSFERENCIA DE HUMBERTO LUIS GUEVARA SERRACIN CASA No 23 MESES ENERO FEBR | D125: 23 | E125: 45 | F125: =+F124+E125 -> 5037.42 | G125: a
A126: 45730.8 | B126: 16934 | C126: FLIA CHIRU | D126: 292 | E126: 15 | F126: =+F125+E126 -> 5052.42 | G126: a
A127: 45730.8 | B127: 16935 | C127: BANCA MOVIL TRANSFERENCIA DE TWIRA TASHAWNNA ALLEYNE CLARK Casa 316 Ignacio Dreckett ENE a | D127: 316 | E127: 45 | F127: =+F126+E127 -> 5097.42 | G127: a
A128: 45730.8 | B128: 16936 | C128: YAPPY DE GIRLY ALEXIA ROBINSON MATOS POR Pago mantenimiento casa 257 mes de marzo | D128: 257 | E128: 15 | F128: =+F127+E128 -> 5112.42 | G128: a
A129: 45730.8 | B129: 16937 | C129: YAPPY DE ANALIDA JORDAN de GALVAN -FEBRERO Y MARZO | D129: 48 | E129: 30 | F129: =+F128+E129 -> 5142.42 | G129: a
A130: 45730.8 | B130: 16938 | C130: YAPPY DE DIANA MARIA SANCHEZ FLORES | D130: D-24 | E130: 30 | F130: =+F129+E130 -> 5172.42 | G130: a
A131: 45730.8 | B131: 16939 | C131: YAPPY DE GLADYS OSIRIS VILLANUEVA DE AGUILAR | D131: 37 | E131: 30 | F131: =+F130+E131 -> 5202.42 | G131: a
A132: 45730.8 | B132: 16940 | C132: BANCA MOVIL TRANSFERENCIA DE FERNANDO CHAVERRA PINEDA Fernando Chaverra casa 317 Marzo | D132: 317 | E132: 15 | F132: =+F131+E132 -> 5217.42 | G132: a
A133: 45730.8 | B133: 16941 | C133: BANCA MOVIL TRANSFERENCIA DE NORMA JAY SKERRITT VALENTINE Pago de mantenimiento Familia BETEGON -MARZO | D133: D-5 | E133: 15 | F133: =+F132+E133 -> 5232.42 | G133: a
A134: 45730.8 | B134: 16942 | C134: BANCA MOVIL TRANSFERENCIA DE ORLANDO ENRIQUE ARGUELLES CUESTA Enero a abril casa 313 | D134: 313 | E134: 60 | F134: =+F133+E134 -> 5292.42 | G134: a
A135: 45730.8 | B135: 16943 | C135: BANCA MOVIL TRANSFERENCIA DE JOSE MANUEL TUÑON RAMOS Pago de Enero a Marzo Casa 137 Famili | D135: 137 | E135: 45 | F135: =+F134+E135 -> 5337.42 | G135: a
A136: 45730.8 | B136: 16944 | C136: YAPPY DE ANA MICHELLE PILE OSSA (O) ARELIS VANESSA OSSA DIAZ POR enero y febrero Casa 106 | D136: 106 | E136: 30 | F136: =+F135+E136 -> 5367.42 | G136: a
A137: 45730.8 | B137: 16945 | C137: YAPPY DE MARIET BROOKS SALAMANCA POR mantenimiento casa 78 | D137: 78 | E137: 30 | F137: =+F136+E137 -> 5397.42 | G137: a
A138: 45731.8 | B138: 16946 | C138: YAPPY DE ANSELMO EMILIANO FORDE CHRISTOPHER- MARZO | D138: 5 | E138: 15 | F138: =+F137+E138 -> 5412.42 | G138: a
A139: 45731.8 | B139: 16947 | C139: YAPPY DE GENEVA KAYLYN CORBIN GREENAWAY (O) GEORGE CORBIN GARRICK (O) POR Casa 307 calle 6 | D139: 307 | E139: 30 | F139: =+F138+E139 -> 5442.42 | G139: a
A140: 45731.8 | B140: 16948 | C140: YAPPY DE KASHMAH SHAMMETH CADOGAN de LEWIS MARZO | D140: 150 | E140: 15 | F140: =+F139+E140 -> 5457.42 | G140: a
A141: 45731.8 | B141: 16949 | C141: DEPOSITO CUENTA DE AHORROS SIN LIBRETA- FLIA BEJARANO -ENE-FEB | D141: 218 | E141: 30 | F141: =+F140+E141 -> 5487.42 | G141: a
A142: 45731.8 | B142: 16950 | C142: YAPPY DE ARTURO ROGELIO ROBINSON WILLIAMS - ENERO -ABRIL | D142: 173 | E142: 60 | F142: =+F141+E142 -> 5547.42 | G142: a
A143: 45731.8 | B143: 16951 | C143: YAPPY DE KATIRIA YATHZEEL ORTEGA CASTILLO POR casa 283 | D143: 283 | E143: 15 | F143: =+F142+E143 -> 5562.42 | G143: a
A144: 45731.8 | B144: 16952 | C144: BANCA MOVIL TRANSFERENCIA DE FERNANDO DE CASTRO BUENDIA A TERCEROS - ENERO -FEB-MARZO | D144: 311 | E144: 45 | F144: =+F143+E144 -> 5607.42 | G144: a
A145: 45732.8 | B145: 16953 | C145: YAPPY DE ALAIN AMINT ARAUZ POWELL POR casa numero 1 enero y febrero | D145: 1 | E145: 30 | F145: =+F144+E145 -> 5637.42 | G145: a
... A147: 45732.8 | B147: 16955 | C147: YAPPY DE OSVALDO HERRERA CARRIAZO POR marzo casa 53 familia Herrera BAMBY | D147: 53 | E147: 15 | F147: =+F146+E147 -> 5697.42 | G147: a
A148: 45732.8 | C148: TRANSFERENCIA A 0499013332792 JERONIMO HERNANDEZ- MATERIALES ELECTRICOS | D148: - | E148: -21.14 | F148: =+F147+E148 -> 5676.28 | G148: a
A149: 45732.8 | B149: 16956 | C149: YAPPY DE CELESTINA RODRIGUEZ casa 51 - pago hasta abril 2025 | D149: 51 | E149: 60 | F149: =+F148+E149 -> 5736.28 | G149: a
A150: 45732.8 | B150: 16957 | C150: YAPPY DE LIGIA ELENA ADLES JIMENEZ casa 91 enero a marzo | D150: 91 | E150: 45 | F150: =+F149+E150 -> 5781.28 | G150: a
A151: 45732.8 | B151: 16958 | C151: BANCA MOVIL TRANSFERENCIA DE YOMAIRA YAISET ASHAW SMALL cuota Febrero y Marzo Casa 293 | D151: 293 | E151: 30 | F151: =+F150+E151 -> 5811.28 | G151: a
A152: 45732.8 | B152: 16959 | C152: YAPPY DE AURA MERCEDES PINEDA de SANTAMARIA POR Casa31 familia Santamaria | D152: 31 | E152: 60 | F152: =+F151+E152 -> 5871.28 | G152: a
A153: 45732.8 | B153: 16960 | C153: BANCA MOVIL TRANSFERENCIA DE LISSETH HERMINIA DE LA ESPADA de DE NICOLO mensualidad marzo | D153: 194 | E153: 15 | F153: =+F152+E153 -> 5886.28 | G153: a
A154: 45732.8 | B154: 16961 | C154: BANCA MOVIL TRANSFERENCIA DE YISEL BONET ALTAMIRANDA DE YARD pago casa 156 flia Yard mes d | D154: 156 | E154: 15 | F154: =+F153+E154 -> 5901.28 | G154: a
A155: 45732.8 | B155: 16962 | C155: YAPPY DE WYLMA ISUALY MATURANA DE ESCOBAR | D155: 85 | E155: 15 | F155: =+F154+E155 -> 5916.28 | G155: a
A156: 45732.8 | B156: 16963 | C156: YAPPY DE YESICA MARLENE CHIFUNDO DE PRESTAN POR seguridad del mes de marzo Flia Prestan ca | D156: 210 | E156: 15 | F156: =+F155+E156 -> 5931.28 | G156: a
A157: 45732.8 | B157: 16964 | C157: YAPPY DE SUMAYKIRA YANILET GRENALD FERREIRA POR Pago de casa 136 familia Grenald mantenimi | D157: 136 | E157: 15 | F157: =+F156+E157 -> 5946.28 | G157: a
A158: 45732.8 | B158: 16965 | C158: BANCA MOVIL TRANSFERENCIA DE MIGUEL ANTONIO TAMAYO MARTINEZ CASA D19 FLIA TAMAYO MES DE MA | D158: D-19 | E158: 15 | F158: =+F157+E158 -> 5961.28 | G158: a
A159: 45733.8 | B159: 16966 | C159: YAPPY DE JOANNA VANESSA EVERSLEY DE VALDES POR casa 71 FEB-MAR | D159: 71 | E159: 30 | F159: =+F158+E159 -> 5991.28 | G159: a
A160: 45733.8 | B160: 16967 | C160: YAPPY DE JULIO ENRIQUE MEJIA POR Pago de Mant y Garita de Marzo Casa 291 Flia Mejia | D160: 291 | E160: 15 | F160: =+F159+E160 -> 6006.28 | G160: a
A161: 45733.8 | B161: 16968 | C161: YAPPY DE ERNESTO GALVAN LEON (FANCYS CLUB)- ENERO | D161: 139 | E161: 15 | F161: =+F160+E161 -> 6021.28 | G161: a
A162: 45733.8 | B162: 16969 | C162: YAPPY DE ERNESTO GALVAN LEON (FANCYS CLUB) FEBRERO- MARZO | D162: 139 | E162: 30 | F162: =+F161+E162 -> 6051.28 | G162: a
...

Sheet pagos abril 2025
A1: DETALLE DE PAGOS EN BANCO
B2: MES DE ABRIL DE 2025
A4: Cuenta:Alborada 04-11-00-000468-4
A8: Fecha | B8: Recibo | C8: Descripción | D8: No.Casa | E8: Pagos | F8: Saldo total
A11: 45748.327 | B11: 17057 | C11: BANCA MOVIL TRANSFERENCIA DE NELSON AZARIAS MORENO MAGDALENO pago de mantenimiento la albo | D11: 310 | E11: 15 | F11: =+'abril Saraliz'!G9+E11 -> 4926.93 | G11: a
A12: 45748.327 | B12: 17058 | C12: BANCA MOVIL TRANSFERENCIA DE LUIS ENRIQUE AMADOR MARTINEZ Pago Seguridad mes Abril | D12: 195 | E12: 15 | F12: =+F11+E12 -> 4941.93 | G12: a
A13: 45748.327 | B13: 17059 | C13: BANCA EN LINEA TRANSFERENCIA DE 0427120001653 DAYRA LUCILA CANALES de SWANSTON casa 306 ro | D13: 306 | E13: 30 | F13: =+F12+E13 -> 4971.93 | G13: a
A14: 45748.327 | B14: 17060 | C14: YAPPY DE VANESSA VICTORIA PARNTHER LUZCANDO POR Mant casa 28 flia Sanchez Ene y Febrero ca | D14: 28 | E14: 30 | F14: =+F13+E14 -> 5001.93 | G14: a
A15: 45748.327 | B15: 17061 | C15: YAPPY DE GUILLERMO CHALHOUB RODRIGUEZ POR Marzo y Abril 2025 Casa 250 Alborada | D15: 250 | E15: 30 | F15: =+F14+E15 -> 5031.93
A16: 45748.327 | B16: 17062 | C16: YAPPY DE MARTIN LUIS MENESES TESIS POR casa 58 FLIA Meneses | D16: 58 | E16: 15 | F16: =+F15+E16 -> 5046.93
A17: 45748.327 | B17: 17063 | C17: YAPPY DE KAISHA TAMARA RIVAS JULIO -casa 79 | D17: 79 | E17: 15 | F17: =+F16+E17 -> 5061.93
A18: 45748.327 | B18: 17064 | C18: YAPPY DE PORFIRIO JUSTAVINO CEDEÑO | D18: 289 | E18: 15 | F18: =+F17+E18 -> 5076.93
A19: 45748.327 | B19: 17065 | C19: BANCA MOVIL TRANSFERENCIA DE LEOPOLDO QUINTERO VALDES (O) LUZMILA ELENA PORTER DE QUINTER | D19: 47 | E19: 15 | F19: =+F18+E19 -> 5091.93
A20: 45748.327 | B20: 17066 | C20: YAPPY DE SUNILA GITA PATEL SALDAÑA POR Casa 29 josefina de Patel mant febrero y marzo 2025 | D20: 29 | E20: 30 | F20: =+F19+E20 -> 5121.93
A21: 45749.327 | B21: 17067 | C21: BANCA MOVIL TRANSFERENCIA DE 0427120001653 DAYRA LUCILA CANALES de SWANSTON casa 278 enero | D21: 278 | E21: 30 | F21: =+F20+E21 -> 5151.93
A22: 45749.327 | B22: 17068 | C22: YAPPY DE ANTONIO ALCEDO AGUIRRE POR Casa 217 abril | D22: 217 | E22: 15 | F22: =+F21+E22 -> 5166.93
A23: 45749.327 | B23: 17069 | C23: YAPPY DE OSVALDO HERRERA CARRIAZO POR Mes de Abril casa 53 Flia Herrera | D23: 53 | E23: 15 | F23: =+F22+E23 -> 5181.93
F24: =+F23+E24 -> 5181.93

Sheet abril Saraliz
A2: Últimos movimientos
A4: Cuenta:ALBORADA 04-11-00-000468-4
A8: Fecha | B8: Recibo | C8: Descripción | D8: Casa | E8: Crédito | G8: Saldo total
A9: 45747 | C9: SALDO AL 31 DE MARZO DE 2025 | E9: =+'pagos marzo 2025'!F261 -> 4911.93 | G9: =+E9 -> 4911.93
A10: 45748.1 | B10: 17058 | C10: BANCA MOVIL TRANSFERENCIA DE NELSON AZARIAS MORENO MAGDALENO pago de mantenimiento la albo | D10: 310 | E10: 15 | G10: =+G9+E10+F10 -> 4926.93
A11: 45748.1 | B11: 17059 | C11: BANCA MOVIL TRANSFERENCIA DE LUIS ENRIQUE AMADOR MARTINEZ Pago Seguridad mes Abril | D11: 195 | E11: 15 | G11: =+G10+E11+F11 -> 4941.93
A12: 45748.1 | B12: 17060 | C12: BANCA EN LINEA TRANSFERENCIA DE 0427120001653 DAYRA LUCILA CANALES de SWANSTON casa 306 ro | D12: 306 | E12: 30 | G12: =+G11+E12+F12 -> 4971.93
A13: 45748.1 | B13: 17061 | C13: YAPPY DE VANESSA VICTORIA PARNTHER LUZCANDO POR Mant casa 28 flia Sanchez Ene y Febrero ca | D13: 28 | E13: 30 | G13: =+G12+E13+F13 -> 5001.93
A14: 45748.1 | B14: 17062 | C14: YAPPY DE GUILLERMO CHALHOUB RODRIGUEZ POR Marzo y Abril 2025 Casa 250 Alborada | D14: 250 | E14: 30 | G14: =+G13+E14+F14 -> 5031.93
A15: 45748.1 | B15: 17063 | C15: YAPPY DE MARTIN LUIS MENESES TESIS POR casa 58 FLIA Meneses | D15: 58 | E15: 15 | G15: =+G14+E15+F15 -> 5046.93
A16: 45748.1 | B16: 17064 | C16: YAPPY DE KAISHA TAMARA RIVAS JULIO | D16: 79 | E16: 15 | G16: =+G15+E16+F16 -> 5061.93
A17: 45748.1 | B17: 17065 | C17: YAPPY DE PORFIRIO JUSTAVINO CEDEÑO | D17: 289 | E17: 15 | G17: =+G16+E17+F17 -> 5076.93
A18: 45748.1 | B18: 17066 | C18: BANCA MOVIL TRANSFERENCIA DE LEOPOLDO QUINTERO VALDES (O) LUZMILA ELENA PORTER DE QUINTER | D18: 47 | E18: 15 | G18: =+G17+E18+F18 -> 5091.93
A19: 45748.1 | B19: 17067 | C19: YAPPY DE SUNILA GITA PATEL SALDAÑA POR Casa 29 josefina de Patel mant febrero y marzo 2025 | D19: 29 | E19: 30 | G19: =+G18+E19+F19 -> 5121.93
A20: 45749.1 | B20: 17068 | C20: BANCA MOVIL TRANSFERENCIA DE 0427120001653 DAYRA LUCILA CANALES de SWANSTON casa 278 enero | D20: 278 | E20: 30 | G20: =+G19+E20+F20 -> 5151.93
A21: 45749.1 | B21: 17069 | C21: YAPPY DE ANTONIO ALCEDO AGUIRRE POR Casa 217 abril | D21: 217 | E21: 15 | G21: =+G20+E21+F21 -> 5166.93
A22: 45749.1 | B22: 17070 | C22: YAPPY DE OSVALDO HERRERA CARRIAZO POR Mes de Abril casa 53 Flia Herrera | D22: 53 | E22: 15 | G22: =+G21+E22+F22 -> 5181.93
A23: 45759.069 | B23: 17071, 17072,17073, 17074,17075, 17087, 17094, 17096, 17101, 17102, 17105 | C23: DEPOSITO CUENTA DE AHORROS SIN LIBRETA DEPOSITADO POR SARALIZ CASAS: 59, 179, 285, 4, 116, 294, 57, 55, 334, 318, 246 | D23: VARIAS CASAS | E23: 360 | G23: =+G22+E23+F23 -> 5541.93
A24: 45750.1 | B24: 17076 | C24: YAPPY DE ELOISA MALENY JAEN GUTIERREZ | D24: 185 | E24: 15 | G24: =+G23+E24+F24 -> 5556.93
A25: 45749.1 | B25: 17077 | C25: YAPPY DE NITZIA ITZEL AGUILAR GALVAN POR mes de abril Familia Aguilar Casa 56 | D25: 56 | E25: 15 | G25: =+G24+E25+F25 -> 5571.93
A26: 45749.1 | B26: 17078 | C26: YAPPY DE YOLANDA ENEIDA LOPER ALABARCA POR mantenimiento casa 271 abril 2025 | D26: 271 | E26: 20 | G26: =+G25+E26+F26 -> 5591.93
A27: 45749.1 | B27: 17079 | C27: YAPPY DE YANETH YAMILKA BADILLA PINEDA POR cuota abril casa 157 Yaneth Badilla | D27: 157 | E27: 15 | G27: =+G26+E27+F27 -> 5606.93
A28: 45749.1 | B28: 17080 | C28: YAPPY DE YURIBETH YAILYN LEE | D28: 64 | E28: 30 | G28: =+G27+E28+F28 -> 5636.93
A29: 45750.1 | B29: 17081 | C29: ACH - DEMETRIO CELSO PRESCOTT RODRIGUEZ | D29: 241 | E29: 15 | G29: =+G28+E29+F29 -> 5651.93
A30: 45749.1 | B30: 17082 | C30: YAPPY DE YUMITZIE ANNELIS HARWOOD de CEDEÑO POR mes de marzo casa 192 Flia Cedeno | D30: 192 | E30: 15 | G30: =+G29+E30+F30 -> 5666.93
A31: 45750.1 | B31: 17083 | C31: YAPPY DE TAIRIN TATIANA ROBINSON de LASSONDE | D31: 49 | E31: 15 | G31: =+G30+E31+F31 -> 5681.93
A32: 45750.1 | B32: 17084 | C32: ACH - DENNIS BARNES GRAHAM | D32: 148 | E32: 15 | G32: =+G31+E32+F32 -> 5696.93
A33: 45750.1 | B33: 17085 | C33: YAPPY DE ANSELMO EMILIANO FORDE CHRISTOPHER | D33: 5 | E33: 15 | G33: =+G32+E33+F33 -> 5711.93
A34: 45750.1 | B34: 17086 | C34: YAPPY DE SARALIZ LORENA HUSBAND DE VELASQUEZ POR casa 117 marzo y abril flia velasquez | D34: 117 | E34: 30 | G34: =+G33+E34+F34 -> 5741.93 | K34: DEPOSITADO 12 DE ABRIL
A35: 45750.1 | B35: COMPRA | C35: BANCA MOVIL TRANSFERENCIA A 0311010007897 COPYMATIC (CONSORCIO EJECUTIVO, S.A.) LIBRO RECO | D35: _ | F35: -21.35 | G35: =+G34+E35+F35 -> 5720.58 | K35: CASA | L35: MONTO | M35: RECIBOS
A36: 45750.1 | B36: PAGO | C36: BANCA MÓVIL TIGO HOGAR - PYME (88280329) | D36: _ | F36: -90.19 | G36: =+G35+E36+F36 -> 5630.39 | K36: 59 | L36: 30 | M36: 17071
A37: 45750.1 | B37: PAGO | C37: BANCA MÓVIL ENSA (ELEKTRA NORESTE) (000000882669) | D37: _ | F37: -22.68 | G37: =+G36+E37+F37 -> 5607.71 | K37: 179 | L37: 30 | M37: 17072
A38: 45750.1 | B38: 17231 | C38: familia vivero casa 145 | D38: 145 | E38: 15 | G38: =+G37+E38+F38 -> 5622.71 | K38: 285 | L38: 15 | M38: 17073
A39: 45751.1 | B39: 17088 | C39: ACH - EMILIO STERLING LOVET WILSON | D39: 67 | E39: 30 | G39: =+G38+E39+F39 -> 5652.71 | K39: 4 | L39: 30 | M39: 17074
A40: 45752.1 | B40: 17089 | C40: YAPPY DE EDGAR PAUL ORTEGA PIMENTEL POR Mant Casa 323 Flia Ortega mayo y junio | D40: 323 | E40: 30 | G40: =+G39+E40+F40 -> 5682.71 | K40: 116 | L40: 15 | M40: 17075
A41: 45754.1 | B41: 17090 | C41: ACH - YARABY ORQUIDIA JIMENEZ JONES DE ABRAHAM | D41: 303 | E41: 45 | G41: =+G40+E41+F41 -> 5727.71 | K41: 294 | L41: 90 | M41: 17087
A42: 45754.1 | B42: 17091 | C42: ACH - PAMELA PATRICIA PETERS BAILEY\ belford | D42: 177 | E42: 45 | G42: =+G41+E42+F42 -> 5772.71 | K42: 57 | L42: 15 | M42: 17094
A43: 45751.1 | B43: 17092 | C43: YAPPY DE DAVID KERR RUDY MONTERO POR casa 32 mes Abril familia Rudy | D43: 32 | E43: 15 | G43: =+G42+E43+F43 -> 5787.71 | K43: 55 | L43: 45 | M43: 17096
A44: 45752.1 | B44: 17093 | C44: YAPPY DE MANUEL DE JESUS MEDINA ORTEGA | D44: 25 | E44: 30 | G44: =+G43+E44+F44 -> 5817.71 | K44: 334 | L44: 60 | M44: 17101
A45: 45753.1 | B45: 17095 | C45: BANCA MOVIL TRANSFERENCIA DE ALIZA EMERITA JIMENEZ | D45: 30 | E45: 15 | G45: =+G44+E45+F45 -> 5832.71 | K45: 318 | L45: 15 | M45: 17102
A46: 45753.1 | B46: 17097 | C46: BANCA MOVIL TRANSFERENCIA DE KRISTIANY QUERUBE OGLIVIE SANCLEMENTE Abril casa 186 | D46: 186 | E46: 15 | G46: =+G45+E46+F46 -> 5847.71 | K46: 246 | L46: 15 | M46: 17105
A47: 45754.1 | B47: 17098 | C47: BANCA MOVIL TRANSFERENCIA DE LILIAN JAZMIN TUÑON DE TOULIER enero febrero marzo casa 332 | D47: 332 | E47: 45 | G47: =+G46+E47+F47 -> 5892.71 | L47: =SUM(L36:L46) -> 360
A48: 45755.1 | B48: 17099 | C48: BANCA MOVIL TRANSFERENCIA DE NUDIA ESTHER MORALES de GUERRA marzo 315 | D48: 315 | E48: 15 | G48: =+G47+E48+F48 -> 5907.71
A49: 45755.1 | B49: 17100 | C49: YAPPY DE KASHMAH SHAMMETH CADOGAN DE LEWIS | D49: 150 | E49: 15 | G49: =+G48+E49+F49 -> 5922.71 | K49: EFECTIVO QUE TIENE SARALIZ | N49: recibos x revisar
A50: 45756.069 | B50: 17103 | C50: BANCA MOVIL TRANSFERENCIA DE MARLENE BOYCE DAWKINS Casa 181 Familia Boyce | D50: 181 | E50: 15 | G50: =+G49+E50+F50 -> 5937.71 | K50: 2 | L50: OMAR CUETO | M50: 30 | N50: 17163
A51: 45756.069 | B51: 17104 | C51: YAPPY DE YEMIL DENISE RODRIGUEZ GONDOLA POR casa 330 flia Vergara Rodriguez Yemil | D51: 330 | E51: 30 | G51: =+G50+E51+F51 -> 5967.71 | J51: OK | K51: 200 | L51: FLIA VANEGAS | M51: 30 | N51: 17189
A52: 45757.069 | B52: 17106 | C52: BANCA MOVIL TRANSFERENCIA DE BENITO PACHECO DAVIS FEB MAR ABR MAY JUN CASA D3 BPacheco | D52: D3 | E52: 75 | G52: =+G51+E52+F52 -> 6042.71
A53: 45757.069 | B53: 17107 | C53: BANCA MOVIL TRANSFERENCIA DE GREGORIA HEIDI BRYAN RAMOS abril casa 196 | D53: 196 | E53: 15 | G53: =+G52+E53+F53 -> 6057.71
A54: 45757.069 | B54: 17108 | C54: YAPPY DE EDGARDO CHIARI FRANCO | D54: 329 | E54: 45 | G54: =+G53+E54+F54 -> 6102.71
A55: 45757.069 | B55: 17109 | C55: BANCA MOVIL TRANSFERENCIA DE CARLOS ERNESTO LAMBERT PEREA | D55: 223 | E55: 30 | G55: =+G54+E55+F55 -> 6132.71
A56: 45757.069 | B56: 17110 | C56: BANCA MOVIL TRANSFERENCIA DE JOSSUA EMMIR WILLIAMS RIOS Pago de Mant y Seg Familia William | D56: 327 | E56: 30 | G56: =+G55+E56+F56 -> 6162.71
A57: 45755.1 | B57: 17111 | C57: YAPPY DE CARLOS MANRIQUE GONZALEZ JAEN POR Pago de mantenimiento casa-99 enero-junio | D57: 99 | E57: 90 | G57: =+G56+E57+F57 -> 6252.71
A58: 45758.069 | B58: 17112 | C58: BANCA MOVIL TRANSFERENCIA DE YOLANDA MAGALI CAMPOS GONZALEZ mes de marzo 2025 | D58: 304 | E58: 15 | G58: =+G57+E58+F58 -> 6267.71
A59: 45758.069 | B59: PAGO | C59: BANCA MOVIL TRANSFERENCIA A 0472996299559 PEDRO ANTONIO GLASGOW BARRETT CORTE HIERBA FRANJ | D59: _ | F59: -60 | G59: =+G58+E59+F59 -> 6207.71
A60: 45759.069 | B60: 17113 | C60: YAPPY DE DAYANARA ITZEL BENJAMIN DE DE LEON POR casa D 12 marzo y abril | D60: D12 | E60: 30 | G60: =+G59+E60+F60 -> 6237.71
A61: 45759.069 | B61: 17114 | C61: BANCA MOVIL TRANSFERENCIA DE JOSE MANUEL TUÑON RAMOS Pago de Abril Casa 137 Familia Tunon | D61: 137 | E61: 15 | G61: =+G60+E61+F61 -> 6252.71
A62: 45759.069 | B62: 17115 | C62: YAPPY DE YANIZA INDIRA ATENCIO DE DRECKETT | D62: 18 | E62: 15 | G62: =+G61+E62+F62 -> 6267.71
A63: 45760.069 | B63: 17116 | C63: YAPPY DE NIDIA EDITH RODRIGUEZ ORTIZ POR Flia Rodriguez casa 267 pago del mes de marzo 202 | D63: 267 | E63: 15 | G63: =+G62+E63+F63 -> 6282.71
A64: 45761.069 | B64: 17117 | C64: YAPPY DE VICENTE ROOK FRUTO POR Fla Rook casa 309 enero y febrero | D64: 309 | E64: 30 | G64: =+G63+E64+F64 -> 6312.71
A65: 45761.069 | B65: 17118 | C65: YAPPY DE GIRLY ALEXIA ROBINSON MATOS \ FLIA ICASA | D65: 257 | E65: 15 | G65: =+G64+E65+F65 -> 6327.71
A66: 45761.069 | B66: 17119 | C66: YAPPY DE SUMAYKIRA YANILET GRENALD FERREIRA POR Pago de casa 136 familia Grenald mes de Ab | D66: 136 | E66: 15 | G66: =+G65+E66+F66 -> 6342.71
A67: 45761.069 | B67: 17120 | C67: YAPPY DE MARIBEL ARISPE de VEGA\ FLIA VEGA ARISPE | D67: 296 | E67: 15 | G67: =+G66+E67+F67 -> 6357.71
A68: 45759.069 | B68: 17121 | C68: YAPPY DE QUERUBI LIZET NEREIDA de HILTON | D68: 19 | E68: 15 | G68: =+G67+E68+F68 -> 6372.71
A69: 45761.069 | B69: 17122 | C69: BANCA MOVIL TRANSFERENCIA DE YISEL BONET ALTAMIRANDA DE YARD mes de abril casa 156 flia Yard | D69: 156 | E69: 15 | G69: =+G68+E69+F69 -> 6387.71
A70: 45760.069 | B70: 17123 | C70: YAPPY DE SHANI NG de CHIU POR Pago Marzo Casa 292 | D70: 292 | E70: 15 | G70: =+G69+E70+F70 -> 6402.71
A71: 45758.069 | B71: 17124 | C71: YAPPY DE ROBERTO RODRIGUEZ PEREIRA POR Casa 43 primera calle oeste Roberto Rodriguez | D71: 43 | E71: 30 | G71: =+G70+E71+F71 -> 6432.71
A72: 45761.069 | B72: 17125 | C72: YAPPY DE MARTHA BIBIANA ACOSTA MARULANDA POR casa 105 familia Estrada mes abril | D72: 105 | E72: 15 | G72: =+G71+E72+F72 -> 6447.71
... A74: 45761.069 | B74: 17127 | C74: YAPPY DE VIELKA LUZMILA CUSATTI ANAYA | D74: 20 | E74: 15 | G74: =+G73+E74+F74 -> 6492.71
A75: 45762.465 | B75: 17128 | C75: ACH - ELISA INDIRA POWELL RODRIGUEZ | D75: 1 | E75: 45 | G75: =+G74+E75+F75 -> 6537.71
A76: 45761.069 | B76: 17129 | C76: YAPPY DE ARIEL CORPAS BETEGON\ FLIA CORPAS QUINN | D76: 319 | E76: 45 | G76: =+G75+E76+F76 -> 6582.71
A77: 45762.465 | B77: 17130 | C77: ACH - IRINA JOANNA LEWIS HAYNES | D77: 302 | E77: 30 | G77: =+G76+E77+F77 -> 6612.71
A78: 45762.465 | B78: 17131 | C78: ACH - JOSE LUIS GONZALEZ FLETCHER | D78: 247 | E78: 15 | G78: =+G77+E78+F78 -> 6627.71
A79: 45761.069 | B79: 17132 | C79: YAPPY DE ERIC ARIEL VILLANUEVA (O) AIMAR ELIESER VILLANUEVA ARCHIBALD POR pago de segurida | D79: 236 | E79: 15 | G79: =+G78+E79+F79 -> 6642.71
A80: 45750.1 | B80: 17133 | C80: BANCA MOVIL TRANSFERENCIA DE NIDIA SILGADO LEON Casa 164 | D80: 164 | E80: 15 | G80: =+G79+E80+F80 -> 6657.71
A81: 45757.069 | B81: 17134 | C81: BANCA EN LINEA TRANSFERENCIA DE ENEIRA ESTHER BELTRAN DE KIRCHMAN MIRNA REED DE LEE CASA62 | D81: 62 | E81: 15 | G81: =+G80+E81+F81 -> 6672.71
A82: 45762.465 | B82: 17135 | C82: YAPPY DE JAIME ALBERTO PEREZ MERO | D82: 205 | E82: 15 | G82: =+G81+E82+F82 -> 6687.71
A83: 45762.465 | B83: 17136 | C83: BANCA MOVIL TRANSFERENCIA DE LINDA YAJAIRA LAJON ANDERSON pago Casa 219 abril y mayo segur | D83: 219 | E83: 30 | G83: =+G82+E83+F83 -> 6717.71
A84: 45762.465 | B84: 17137 | C84: YAPPY DE IRASEMA ESTHER MURILLO DE SMALL POR Flia Small casa 119 calle 3ra oeste | D84: 119 | E84: 30 | G84: =+G83+E84+F84 -> 6747.71
A85: 45762.465 | B85: 17138 | C85: BANCA EN LINEA TRANSFERENCIA DE HUMBERTO LUIS GUEVARA SERRACIN Casa No 23 Flia Guevara Mes | D85: 23 | E85: 45 | G85: =+G84+E85+F85 -> 6792.71
A86: 45762.465 | B86: 17139 | C86: BANCA MOVIL TRANSFERENCIA DE NORMA JAY SKERRITT VALENTINE Pago de mantenimiento Familia Be | D86: D5 | E86: 15 | G86: =+G85+E86+F86 -> 6807.71
A87: 45762.465 | B87: 17140 | C87: YAPPY DE YESICA MARLENE CHIFUNDO DE PRESTAN POR pago de mantenimiento del mes de abril Fli | D87: 210 | E87: 15 | G87: =+G86+E87+F87 -> 6822.71
A88: 45762.465 | B88: 17141 | C88: BANCA MOVIL TRANSFERENCIA DE YOLANDA MAGALI CAMPOS GONZALEZ seguridad abril | D88: 304 | E88: 15 | G88: =+G87+E88+F88 -> 6837.71
A89: 45762.465 | B89: 17142 | C89: BANCA MOVIL TRANSFERENCIA DE FERNANDO DE CASTRO BUENDIA | D89: 311 | E89: 15 | G89: =+G88+E89+F89 -> 6852.71
A90: 45762.465 | B90: 17143 | C90: YAPPY DE YAVIRITZEL DEL CARMEN PANAY POR mensualidad abril casa 187 | D90: 187 | E90: 15 | G90: =+G89+E90+F90 -> 6867.71
A91: 45762.465 | B91: 17144 | C91: BANCA MOVIL TRANSFERENCIA DE ETILCIA EDILMA EVANS ROMERO A TERCEROS / FLIA HERRERA | D91: 312 | E91: 30 | G91: =+G90+E91+F91 -> 6897.71
A92: 45762.465 | B92: 17145 | C92: YAPPY DE DIANA MARIA SANCHEZ FLORES / FLIA VEGA | D92: D24 | E92: 15 | G92: =+G91+E92+F92 -> 6912.71
A93: 45761.069 | B93: 17146 | C93: YAPPY DE GLADYS OSIRIS VILLANUEVA DE AGUILAR POR Casa 37 Flia Villanueva Abril | D93: 37 | E93: 15 | G93: =+G92+E93+F93 -> 6927.71
A94: 45758.069 | B94: 17147 | C94: YAPPY DE SONIA ISABEL RODRIGUEZ de MURILLO POR Abril familia Murillo casa34 | D94: 34 | E94: 15 | G94: =+G93+E94+F94 -> 6942.71
A95: 45763.465 | B95: 17148 | C95: YAPPY DE MALIBETZA FAUSTINA CEBALLOS de COMBE | D95: 35 | E95: 30 | G95: =+G94+E95+F95 -> 6972.71
A96: 45763.465 | B96: 17149 | C96: YAPPY DE TIFFANY DEL CARMEN DELGADO JAEN | D96: 185 | E96: 15 | G96: =+G95+E96+F96 -> 6987.71
A97: 45763.465 | B97: 17150 | C97: YAPPY DE NURIA ELENA JIMENEZ de ABREGO POR casa193 | D97: 193 | E97: 15 | G97: =+G96+E97+F97 -> 7002.71
A98: 45763.465 | B98: 17151 | C98: YAPPY DE FABIOLA DE JESUS RAMIREZ de ALVEY (O) SULAY DE JESUS ALVEY R POR mes abril casa 188 | D98: 188 | E98: 15 | G98: =+G97+E98+F98 -> 7017.71
A99: 45763.465 | B99: 17152 | C99: BANCA MOVIL TRANSFERENCIA DE CARLENI ANYURE CLOP FLORES mensualidad de abril | D99: 149 | E99: 15 | G99: =+G98+E99+F99 -> 7032.71
A100: 45763.465 | B100: 17153 | C100: BANCA MOVIL TRANSFERENCIA DE FERNANDO CHAVERRA PINEDA Fernando Chaverra 3 86 1038 casa 317 | D100: 317 | E100: 15 | G100: =+G99+E100+F100 -> 7047.71
A101: 45763.465 | B101: 17154 | C101: BANCA MOVIL TRANSFERENCIA DE MIGUEL ANTONIO TAMAYO MARTINEZ Alborada D19 Flia Tamayo Abril | D101: D19 | E101: 15 | G101: =+G100+E101+F101 -> 7062.71
A102: 45763.465 | B102: 17155 | C102: YAPPY DE LUCAS ANTONIO CORTES SURGEON POR casa 134abril familia Cortes | D102: 134 | E102: 15 | G102: =+G101+E102+F102 -> 7077.71
A103: 45763.465 | B103: 17156 | C103: BANCA MOVIL TRANSFERENCIA DE ERNESTO GALVAN LEON (FANCYS CLUB) A TERCEROS / FLIA SELLES | D103: 139 | E103: 15 | G103: =+G102+E103+F103 -> 7092.71
A104: 45764.465 | B104: 17157 | C104: BANCA MOVIL TRANSFERENCIA DE NATIVIDAD VALENCIA de JIMENEZ Casa 26 flia Jimenez mes de Abr | D104: 26 | E104: 15 | G104: =+G103+E104+F104 -> 7107.71
A105: 45764.465 | B105: 17158 | C105: BANCA MOVIL TRANSFERENCIA DE DALIS YADIRA BANDINI AGUSTINE Pago seguridad CASA 178 flia Ba | D105: 178 | E105: 15 | G105: =+G104+E105+F105 -> 7122.71
A106: 45764.465 | B106: 17159 | C106: BANCA MOVIL TRANSFERENCIA DE ROMELIA ORISSA HALL JOHNSON Abril | D106: 201 | E106: 15 | G106: =+G105+E106+F106 -> 7137.71
...

Sheet pagos mayo 2025
A1: DETALLE DE PAGOS EN BANCO
B2: MES DE MAYO DE 2025
A4: Cuenta:Alborada 04-11-00-000468-4
A8: Fecha | B8: Recibo | C8: Descripción | D8: No.Casa | E8: Cobros | F8: Pagos | G8: Saldo total
A10: 45777 | C10: SALDO AL 30 DE ABRIL DE 2025 | E10: =+'abril Saraliz'!G166 -> 7943.65 | G10: =+E10 -> 7943.65
A11: 45778.609 | B11: 17215 | C11: YAPPY DE JOSE DAVID BONILLA ALVARADO POR Casa D14 Bonilla Gonzalez Mes Abril 2025 Garita | D11: D-14 | E11: 15 | G11: =+G10+E11+F11 -> 7958.65 | H11: a
A12: 45778.609 | B12: 17216 | C12: YAPPY DE ANSELMO EMILIANO FORDE CHRISTOPHER POR Casa 5 1ra Oeste familia Forde | D12: 5 | E12: 15 | G12: =+G11+E12+F12 -> 7973.65 | H12: a
A13: 45778.609 | B13: 17217 | C13: YAPPY DE VANESSA VICTORIA PARNTHER LUZCANDO POR Mant mes de abril casa 75 familia Parnther | D13: 75 | E13: 15 | G13: =+G12+E13+F13 -> 7988.65 | H13: a
A14: 45778.609 | B14: 17218 | C14: BANCA EN LINEA TRANSFERENCIA DE MARCELA PAVIA de LAJON (TRANSPORTE LAJON) pago de segurida | D14: D-06 | E14: 45 | G14: =+G13+E14+F14 -> 8033.65 | H14: a
A15: 45778.609 | B15: 17219 | C15: YAPPY DE KASHMAH SHAMMETH CADOGAN de LEWIS | D15: 150 | E15: 15 | G15: =+G14+E15+F15 -> 8048.65 | H15: a
A16: 45778.609 | B16: 17220 | C16: YAPPY DE MIXIA LIBETH MURILLO AYARZA POR Francisca Ayarza | D16: D-04 | E16: 60 | G16: =+G15+E16+F16 -> 8108.65 | H16: a
A17: 45779.609 | B17: 17221 | C17: BANCA MOVIL TRANSFERENCIA DE LUIS ENRIQUE AMADOR MARTINEZ pago mensual Mayo | D17: 195 | E17: 15 | G17: =+G16+E17+F17 -> 8123.65 | H17: a
A18: 45779.609 | B18: 17222 | C18: YAPPY DE ORLANDO ENRIQUE ARGUELLES CUESTA POR Casa 313 mayo junio | D18: 313 | E18: 30 | G18: =+G17+E18+F18 -> 8153.65 | H18: a
A19: 45779.609 | B19: PAGOS | C19: BANCA MOVIL TRANSFERENCIA A 0338011480674 TIGER SECURITY COMPANY AND TRAINING CENTER, S.A. | F19: -1819 | G19: =+G18+E19+F19 -> 6334.65
A20: 45779.609 | B20: 17223 | C20: ACH - EMILIO STERLING LOVET WILSON | D20: 67 | E20: 15 | G20: =+G19+E20+F20 -> 6349.65 | H20: a
A21: 45779.609 | B21: 17224 | C21: YAPPY DE SARALIZ LORENA HUSBAND DE VELASQUEZ POR casa 117 flia Velasquez | D21: 117 | E21: 15 | G21: =+G20+E21+F21 -> 6364.65 | H21: a
A22: 45779.609 | B22: 17225 | C22: ACH - HAMILTON GONZALEZ IRIS ELIZABETH DE | D22: 111 | E22: 30 | G22: =+G21+E22+F22 -> 6394.65 | H22: a
A23: 45779.609 | B23: 17226 | C23: nelson casa 31 | D23: 310 | E23: 45 | G23: =+G22+E23+F23 -> 6439.65 | H23: a
A24: 45779.609 | B24: 17227 | C24: isaias tate casa 239 mes de abril | D24: 239 | E24: 15 | G24: =+G23+E24+F24 -> 6454.65 | H24: a
A25: 45779.609 | B25: 17228 | C25: YAPPY DE CIARA LUZ JIMENEZ CONCEPCION MANT. MAYO | D25: 16 | E25: 15 | G25: =+G24+E25+F25 -> 6469.65 | H25: a
A26: 45780 | B26: 17229 | C26: FLIA. CEREZO - ABRIL A JULIO/25 | D26: 253 | E26: 60 | G26: =+G25+E26+F26 -> 6529.65 | H26: a
A27: 45781 | B27: 17230 | C27: FLIA SAUNDERS - MAYO Y JUNIO | D27: 285 | E27: 30 | G27: =+G26+E27+F27 -> 6559.65 | H27: a
B28: 17231 | C28: PAGO SE HIZO EL 03-ABRIL-2025 | D28: 145 | E28: 0 | G28: =+G27+E28+F28 -> 6559.65 | H28: a
A29: 45780.299 | B29: 17232 | C29: FLIA. VIVERO - ENERO Y ABRIL | D29: 145 | E29: 30 | G29: =+G28+E29+F29 -> 6589.65 | H29: a
A30: 45781 | B30: 17233 | C30: FLIA - DE CASTRO - MANT. ABRIL/25 | D30: 246 | E30: 15 | G30: =+G29+E30+F30 -> 6604.65 | H30: a
A31: 45781 | B31: 17234 | C31: MARIBEL LAGUNA - MANT. JULIO Y AGOSTO/25 | D31: 294 | E31: 30 | G31: =+G30+E31+F31 -> 6634.65 | H31: a
A32: 45779.299 | B32: 17235 | C32: YAPPY DE YULIXA DEL CARMEN ESPADA de SIERRA POR Flia Sierra casa 110 marzo | D32: 110 | E32: 15 | G32: =+G31+E32+F32 -> 6649.65 | H32: a
A33: 45779.299 | B33: 17236 | C33: YAPPY DE YUMITZIE ANNELIS HARWOOD de CEDEÑO POR mes de abril Flia Cedeno casa 192 | D33: 192 | E33: 15 | G33: =+G32+E33+F33 -> 6664.65 | H33: a
A34: 45779.299 | B34: 17237 | C34: BANCA MOVIL TRANSFERENCIA DE DALIS YADIRA BANDINI MANT. MAYO AGUSTINE Pago de mantenimiento flia Band | D34: 178 | E34: 15 | G34: =+G33+E34+F34 -> 6679.65 | H34: a
A35: 45780.299 | B35: 17238 | C35: BANCA MOVIL TRANSFERENCIA DE NIDIA SILGADO LEON Casa 164 mayo | D35: 164 | E35: 15 | G35: =+G34+E35+F35 -> 6694.65 | H35: a
A36: 45780.299 | B36: 17239 | C36: YAPPY DE YANETH YAMILKA BADILLA PINEDA POR cuota mayo casa 157 | D36: 157 | E36: 15 | G36: =+G35+E36+F36 -> 6709.65 | H36: a
A37: 45780.299 | B37: 17240 | C37: BANCA MOVIL TRANSFERENCIA DE FERNANDO CHAVERRA PINEDA Fernando Chaverra casa 317 junio | D37: 317 | E37: 15 | G37: =+G36+E37+F37 -> 6724.65 | H37: a
A38: 45780.299 | B38: 17241 | C38: BANCA MOVIL TRANSFERENCIA DE DAIZA BRU TORRES A TERCEROS mayo y junio | D38: 143 | E38: 30 | G38: =+G37+E38+F38 -> 6754.65 | H38: a
A39: 45780.299 | B39: 17242 | C39: BANCA MOVIL TRANSFERENCIA DE LILIAN JAZMIN TUÑON DE TOULIER abril mayo | D39: 332 | E39: 30 | G39: =+G38+E39+F39 -> 6784.65 | H39: a
A40: 45780.299 | B40: 17243 | C40: YAPPY DE IDA CEMA JACKSON de VALENCIA-abril | D40: 270 | E40: 15 | G40: =+G39+E40+F40 -> 6799.65 | H40: a
... A43: 45781.299 | B43: 17246 | C43: YAPPY DE JAZMINA ITZEL VEGA de SMITH POR seguridad y mantenimiento casa 328 Flia Vega mayo Y JUNIIO | D43: 328 | E43: 30 | G43: =+G42+E43+F43 -> 6874.65 | H43: a
A44: 45781.299 | B44: PAGOS | C44: BANCA MOVIL TRANSFERENCIA A 0495996629370 SANTOS DIOMEDES ARAUZ MEDINA mantenimiento porto | F44: -85 | G44: =+G43+E44+F44 -> 6789.65
A45: 45781.299 | B45: 17247 | C45: YAPPY DE MANUEL DE JESUS MEDINA ORTEGA POR seguridad de mayo y junio | D45: 25 | E45: 30 | G45: =+G44+E45+F45 -> 6819.65 | H45: a
A46: 45782.299 | B46: 17248 | C46: YAPPY DE NAYRA DEL CARMEN RAMOS RAMOS (O) JERONIMO VALENTIN HERNANDEZ POR pago de segurida MAYO | D46: 54 | E46: 15 | G46: =+G45+E46+F46 -> 6834.65 | H46: a
A47: 45782.299 | B47: 17249 | C47: BANCA EN LINEA TRANSFERENCIA DE 0427120001653 DAYRA LUCILA CANALES de SWANSTON casa 240 ma | D47: 240 | E47: 30 | G47: =+G46+E47+F47 -> 6864.65 | H47: a
A48: 45782.299 | B48: 17250 | C48: ACH - GEORGIANA GAVIRIA PACHECO - mant. Enero a mayo | D48: 86 | E48: 75 | G48: =+G47+E48+F48 -> 6939.65 | H48: a
A49: 45782.299 | B49: 17251 | C49: FLIA MURDOCK - ABRIL | D49: 95 | E49: 15 | G49: =+G48+E49+F49 -> 6954.65 | H49: a
A50: 45782.299 | B50: 17252 | C50: BANCA MOVIL TRANSFERENCIA DE JOSE ALEJANDRO BARROWS ROBINSON casa 154 mayo | D50: 154 | E50: 15 | G50: =+G49+E50+F50 -> 6969.65 | H50: a
A51: 45782.299 | B51: 17253 | C51: YAPPY DE JAIRO ABDIEL BUITRAGO VASQUEZ POR Mensualidad abril casa 100 | D51: 100 | E51: 15 | G51: =+G50+E51+F51 -> 6984.65 | H51: a
A52: 45782.299 | B52: 17254 | C52: BANCA MOVIL TRANSFERENCIA DE LEOPOLDO QUINTERO VALDES (O) LUZMILA ELENA PORTER DE QUINTER | D52: 47 | E52: 15 | G52: =+G51+E52+F52 -> 6999.65 | H52: a
A53: 45782.299 | B53: 17255 | C53: FLIA JIMENEZ - MANT. MAYO | D53: 30 | E53: 15 | G53: =+G52+E53+F53 -> 7014.65 | H53: a
A54: 45782.299 | B54: 17256 | C54: FLIA. PEREZ- DIAZ - MANT. MAYO | D54: 205 | E54: 15 | G54: =+G53+E54+F54 -> 7029.65 | H54: a
A55: 45782.299 | B55: 17257 | C55: YAPPY DE YOLANDA ENEIDA LOPER ALABARCA POR mantenimiento casa 271 mayo 2025 | D55: 271 | E55: 20 | G55: =+G54+E55+F55 -> 7049.65 | H55: a
A56: 45783.299 | B56: 17258 | C56: YAPPY DE MIGUEL ROGELIO SANCHEZ PALACIO POR Casa 6 Oeste Miguel Sanchez mant Mayo y Junio | D56: 6 | E56: 30 | G56: =+G55+E56+F56 -> 7079.65 | H56: a
... A70: 45785.298 | B70: 17272 | C70: BANCA MOVIL TRANSFERENCIA DE NICOLE NAZARETH MICK BARRIOS familia james mant- mayo, junio, julio y agosto | D70: 27 | E70: 60 | G70: =+G69+E70+F70 -> 7454.65 | H70: a
A71: 45785.298 | B71: 17273 | C71: DEPOSITO - OFELIA MITCHELL- MARZO ABRIL Y MAYO | D71: 260 | E71: 45 | G71: =+G70+E71+F71 -> 7499.65
A72: 45785.298 | B72: 17274 | C72: YAPPY DE ROBERTO ANTONIO JENKINS RENTERIA POR Casa 306 Roberto Jenkins paga mayo | D72: 306 | E72: 15 | G72: =+G71+E72+F72 -> 7514.65 | H72: a
A73: 45785.298 | B73: 17275 | C73: YAPPY DE WYLMA ISUALY MATURANA DE ESCOBAR | D73: 85 | E73: 15 | G73: =+G72+E73+F73 -> 7529.65 | H73: a
A74: 45785.298 | B74: 17276 | C74: BANCA MOVIL TRANSFERENCIA DE FELICIA OLIVIA GITTENS MERCHANT Casa 40 GittensZachary Mant Abril y mayo | D74: 40 | E74: 30 | G74: =+G73+E74+F74 -> 7559.65 | H74: a
A75: 45786.298 | B75: 17277 | C75: YAPPY DE OSVALDO HERRERA CARRIAZO POR mes Mayo familia Herrera Bamby | D75: 53 | E75: 15 | G75: =+G74+E75+F75 -> 7574.65 | H75: a
A76: 45786.298 | B76: PAGOS | C76: BANCA EN LÍNEA TIGO HOGAR - PYME (88280329) | F76: -82.97 | G76: =+G75+E76+F76 -> 7491.68
A77: 45786.298 | B77: PAGOS | C77: BANCA EN LINEA TRANSFERENCIA A 0427120001653 DAYRA LUCILA CANALES de SWANSTON ENSA ELEKTRA | F77: -95.99 | G77: =+G76+E77+F77 -> 7395.69
A78: 45786.298 | B78: 17278 | C78: YAPPY DE PORFIRIO JUSTAVINO CEDEÑO POR mes mayo casa 289 | D78: 289 | E78: 15 | G78: =+G77+E78+F78 -> 7410.69 | H78: a
A79: 45786.298 | B79: 17279 | C79: BANCA MOVIL TRANSFERENCIA DE RAQUEL MAGALI RACERO de LAWRENCE casa 120 familia lawrence mes de marzo y abril | D79: 120 | E79: 30 | G79: =+G78+E79+F79 -> 7440.69 | H79: a
A80: 45786.298 | B80: 17280 | C80: YAPPY DE KIZAIDA NAYUDI OBREGON CHIFUNDO POR Pago mes de abril casa 115 Familia Augustine | D80: 115 | E80: 15 | G80: =+G79+E80+F80 -> 7455.69 | H80: a
A81: 45786.298 | B81: 17281 | C81: BANCA MOVIL TRANSFERENCIA DE GREGORIA HEIDI BRYAN RAMOS mayo casa 196 | D81: 196 | E81: 15 | G81: =+G80+E81+F81 -> 7470.69 | H81: a
A82: 45786.298 | B82: 17282 | C82: BANCA MOVIL TRANSFERENCIA DE YOLANDA MAGALI CAMPOS GONZALEZ casa 304 Yolanda Campos mes de mayo | D82: 304 | E82: 15 | G82: =+G81+E82+F82 -> 7485.69 | H82: a
A83: 45786.298 | B83: 17283 | C83: YAPPY DE ISAAC ANTONIO FRANCIS BARRERA POR Abril - Junio 2025 Casa 288 Familia Francis | D83: 288 | E83: 45 | G83: =+G82+E83+F83 -> 7530.69 | H83: a
A84: 45786.298 | B84: 17284 | C84: YAPPY DE SUNILA GITA PATEL SALDAÑA POR Josefina de patel casa 29 mantenimiento abril y may | D84: 29 | E84: 30 | G84: =+G83+E84+F84 -> 7560.69 | H84: a
A85: 45787.298 | B85: 17285 | C85: BANCA MOVIL TRANSFERENCIA DE HECTOR GABRIEL IBARGUEN MURILLO mes marzo flia ibarguen casa | D85: 21 | E85: 15 | G85: =+G84+E85+F85 -> 7575.69 | H85: a
A86: 45787.298 | B86: 17286 | C86: BANCA MOVIL TRANSFERENCIA DE JOSE MANUEL TUÑON RAMOS Pago de Mayo Casa 137 Familia Tunon | D86: 137 | E86: 15 | G86: =+G85+E86+F86 -> 7590.69 | H86: a
A87: 45787.298 | B87: 17287 | C87: YAPPY DE DAYANARA ITZEL BENJAMIN DE DE LEON POR casa D -12 mes de mayo familia De Leon | D87: D-12 | E87: 15 | G87: =+G86+E87+F87 -> 7605.69 | H87: a
A88: 45787.298 | B88: 17288 | C88: BANCA MOVIL TRANSFERENCIA DE NILKA LORENA DEL CASTILLO ZELAYA casa 135 | D88: 135 | E88: 15 | G88: =+G87+E88+F88 -> 7620.69 | H88: a
A89: 45787.298 | B89: PAGOS | C89: BANCA MOVIL TRANSFERENCIA A 0472996299559 PEDRO ANTONIO GLASGOW BARRETT corte de yerba | F89: -150 | G89: =+G88+E89+F89 -> 7470.69
A90: 45787.298 | B90: 17289 | C90: BANCA EN LINEA TRANSFERENCIA DE DALIA ZORAIDA PETERS PAYNE Famila Peters casa 121 y 104 en | D90: 121 Y 104 | E90: 90 | G90: =+G89+E90+F90 -> 7560.69 | H90: a
A91: 45788.298 | B91: 17290 | C91: BANCA MOVIL TRANSFERENCIA DE VIELKA YADIRA TUÑON GALVAN Enero Febrero Marzo | D91: 227 | E91: 45 | G91: =+G90+E91+F91 -> 7605.69 | H91: a
A92: 45788.298 | B92: 17291 | C92: YAPPY DE YELENA DELIBETH ALVEAR ARCIA POR abril y mayo casa 174 | D92: 174 | E92: 30 | G92: =+G91+E92+F92 -> 7635.69 | H92: a
A93: 45789.298 | B93: 17292 | C93: YAPPY DE MARIBEL ARISPE de VEGA mes de mayo | D93: 296 | E93: 15 | G93: =+G92+E93+F93 -> 7650.69 | H93: a
A94: 45789.298 | B94: PAGOS | C94: BANCA EN LÍNEA IDAAN (41789) | F94: -39.66 | G94: =+G93+E94+F94 -> 7611.03
A95: 45789.298 | B95: 17293 | C95: ACH - SYAHMAR MILENN ORTIZ CASTILLO - mayo y junio | D95: 46 | E95: 30 | G95: =+G94+E95+F95 -> 7641.03 | H95: a
A96: 45790.298 | B96: 17294 | C96: YAPPY DE LUZ MARIA BETEGON GARIBALDI POR casa 274 LuzMariabetegonOrlandobarrios | D96: 274 | E96: 30 | G96: =+G95+E96+F96 -> 7671.03 | H96: a
A97: 45790.298 | B97: 17295 | C97: YAPPY DE OKIANIS DEL CARMEN ROBINSON DE KENTISH POR Enero a Mayo Familia Kentish casa 259 | D97: 259 | E97: 75 | G97: =+G96+E97+F97 -> 7746.03 | H97: a
A98: 45791.298 | B98: 17296 | C98: ACH - YARABY ORQUIDIA JIMENEZ JONES DE ABRAHAM | E98: 15 | G98: =+G97+E98+F98 -> 7761.03
A99: 45791.298 | B99: 17297 | C99: DEPOSITO CUENTA DE AHORROS SIN LIBRETA | E99: 15 | G99: =+G98+E99+F99 -> 7776.03
A100: 45791.298 | B100: PAGOS | C100: YAPPY A HERNAN DARIO ROJAS LOPEZ POR Corte hierba 2 paruqes 6ta y 1 parque 4ta | F100: -100 | G100: =+G99+E100+F100 -> 7676.03
A101: 45791.298 | B101: 17298 | C101: YAPPY DE YAVIRITZEL DEL CARMEN PANAY POR mayo casa 187 familia Panay mes de mayo | D101: 187 | E101: 15 | G101: =+G100+E101+F101 -> 7691.03 | H101: a
A102: 45791.298 | B102: 17299 | C102: YAPPY DE ROMELIA ORISSA HALL JOHNSON | D102: 201 | E102: 15 | G102: =+G101+E102+F102 -> 7706.03 | H102: a
A103: 45791.298 | B103: 17300 | C103: YAPPY DE NUDIA ESTHER MORALES de GUERRA | D103: 315 | E103: 15 | G103: =+G102+E103+F103 -> 7721.03 | H103: a
A104: 45791.298 | B104: 17301 | C104: ACH XPRESS - JOSE LUIS GONZALEZ FLETCHER O MAIQUEL ITZELA POLLACK mes de mayo | D104: 247 | E104: 15 | G104: =+G103+E104+F104 -> 7736.03 | H104: a
A105: 45791.298 | B105: 17302 | C105: YAPPY DE GIRLY ALEXIA ROBINSON MATOS POR Casa 257 mantenimiento mes de Mayo | D105: 257 | E105: 15 | G105: =+G104+E105+F105 -> 7751.03 | H105: a
A106: 45792.298 | B106: 17303 | C106: flia ceballos - mes de junio | D106: 13 | E106: 15 | G106: =+G105+E106+F106 -> 7766.03 | H106: a
A107: 45792.298 | B107: PAGOS | C107: YAPPY A HERNAN DARIO ROJAS LOPEZ POR Corte hierba vereda este calle circunvalacion | F107: -60 | G107: =+G106+E107+F107 -> 7706.03
A108: 45792.298 | B108: 17304 | C108: BANCA MOVIL TRANSFERENCIA DE YISEL BONET ALTAMIRANDA de YARD pago mes de mayo casa 156 fli | D108: 156 | E108: 15 | G108: =+G107+E108+F108 -> 7721.03 | H108: a
A109: 45792.298 | B109: 17305 | C109: YAPPY DE VANESSA VICTORIA PARNTHER LUZCANDO POR Mant casa 80 mes de mayo y junio Familia Sinclair | D109: 80 | E109: 30 | G109: =+G108+E109+F109 -> 7751.03 | H109: a
A110: 45792.298 | B110: 17306 | C110: YAPPY DE MELANY DEL CARMEN TAYLOR DELGADO POR Mes de mayo casa 107 | D110: 107 | E110: 15 | G110: =+G109+E110+F110 -> 7766.03 | H110: a
A111: 45792.298 | B111: 17307 | C111: YAPPY DE SERGIO JOSE DE CASTRO BUENDIA POR Casa 246 Cuota mes de mayo | D111: 246 | E111: 15 | G111: =+G110+E111+F111 -> 7781.03 | H111: a
A112: 45792.298 | B112: 17308 | C112: YAPPY DE JACQUELINE YOVANIA VILLAMIL TORRES mes de abril | D112: 298 | E112: 15 | G112: =+G111+E112+F112 -> 7796.03 | H112: a
A113: 45792.298 | B113: 17309 | C113: ACH - JASMIN SUSAN JOHNSON FORBES | D113: 42 | E113: 15 | G113: =+G112+E113+F113 -> 7811.03 | H113: a
A114: 45792.298 | B114: 17310 | C114: BANCA MOVIL TRANSFERENCIA DE MIGUEL ANTONIO TAMAYO MARTINEZ Casa D19 mes de Mayo Flia Tama | D114: D-19 | E114: 15 | G114: =+G113+E114+F114 -> 7826.03 | H114: a
A115: 45792.298 | B115: 17311 | C115: YAPPY DE YANIZA INDIRA ATENCIO DE DRECKETT- mes de mayo y junio | D115: 18 | E115: 30 | G115: =+G114+E115+F115 -> 7856.03 | H115: a
A116: 45792.298 | B116: 17312 | C116: YAPPY DE SUGEIRIS YANIRETH BARRETT JIMENEZ | D116: 326 | E116: 15 | G116: =+G115+E116+F116 -> 7871.03 | H116: a
A117: 45792.298 | B117: 17313 | C117: BANCA MOVIL TRANSFERENCIA DE ODALIS DEL CARMEN JAEN DE MENESES pago de mant casa 49 Eric Lasonder- mes de abril | D117: 49 | E117: 15 | G117: =+G116+E117+F117 -> 7886.03 | H117: a
A118: 45792.298 | B118: 17314 | C118: BANCA MOVIL TRANSFERENCIA DE FERNANDO DE CASTRO BUENDIA mes de mayo | D118: 311 | E118: 15 | G118: =+G117+E118+F118 -> 7901.03 | H118: a
A119: 45793.298 | B119: 17315 | C119: BANCA MOVIL TRANSFERENCIA DE TOYA DELMINA BINGHAM de BETEGON Pago de Mantenimiento Familia BETEGON MES DE MAYO | D119: D-05 | E119: 15 | G119: =+G118+E119+F119 -> 7916.03 | H119: a
A120: 45793 | B120: 17316 | C120: BANCA MOVIL TRANSFERENCIA DE GYSELLE DEYANIRA GRANT WELCH Casa 265 ABR 2025 | D120: 265 | E120: 15 | G120: =+G119+E120+F120 -> 7931.03 | H120: a
...

Sheet pagos junio 2025
A1: DETALLE DE PAGOS EN BANCO
B2: MES DE JUNIO DE 2025
A4: Cuenta:Alborada 04-11-00-000468-4
A8: Fecha | B8: Recibo | C8: Descripción | D8: No.Casa | E8: Cobros | F8: Pagos | G8: Saldo total
A10: 45808 | C10: SALDO AL 31 DE MAYO DE 2025 | E10: =+'pagos mayo 2025'!G183 -> 7117.91 | G10: =+E10 -> 7117.91
A11: 45809.388 | B11: PAGOS | C11: BANCA MOVIL TRANSFERENCIA A 0338011480674 TIGER SECURITY COMPANY AND TRAINING CENTER, S.A. | D11: PAGOS | F11: -1819 | G11: =+G10+E11+F11 -> 5298.91 | H11: a
A12: 45809.388 | B12: 17374 | C12: YAPPY DE MIOZOTIS DEL CARMEN OLMOS LARA casa 10 mes de junio | D12: 10 | E12: 15 | G12: =+G11+E12+F12 -> 5313.91 | H12: a
A13: 45809.388 | B13: 17375 | C13: BANCA MOVIL TRANSFERENCIA DE YOLANDA FORBES FERNANDEZ mes de mayo casa 155 | D13: 155 | E13: 15 | G13: =+G12+E13+F13 -> 5328.91 | H13: a
A14: 45809.388 | B14: 17376 | C14: YAPPY DE LISSETH HERMINIA DE LA ESPADA de DE NICOLO POR casa 194 mensualidad abril- mayo | D14: 194 | E14: 30 | G14: =+G13+E14+F14 -> 5358.91 | H14: a
A15: 45809.388 | B15: 17377 | C15: BANCA MOVIL TRANSFERENCIA DE VICENTE ROOK FRUTO Pago de marzo y abril Fla Rook casa 309 | D15: 309 | E15: 30 | G15: =+G14+E15+F15 -> 5388.91 | H15: a
A16: 45809.388 | B16: 17378 | C16: BANCA MOVIL TRANSFERENCIA DE CARLOS ERNESTO LAMBERT PEREA MES DE MAYO Y JUNIO | D16: 223 | E16: 30 | G16: =+G15+E16+F16 -> 5418.91 | H16: a
A17: 45810.356 | B17: 17379 | C17: BANCA MOVIL TRANSFERENCIA DE CARLOS ANTONIO MORAN MC COY Mant-mayo casa 251 | D17: 251 | E17: 15 | G17: =+G16+E17+F17 -> 5433.91 | H17: a
A18: 45809.388 | B18: 17380 | C18: YAPPY DE ANSELMO EMILIANO FORDE CHRISTOPHER mes de junio | D18: 5 | E18: 15 | G18: =+G17+E18+F18 -> 5448.91 | H18: a
A19: 45811 | B19: 17355 | C19: EFECTIVO- FLIA. MENDOZA - MES DE ABRIL Y MAYO CASA 244 | D19: 244 | E19: 30 | G19: =+G18+E19+F19 -> 5478.91 | H19: a
A20: 45810 | B20: 17381 | C20: EFECTIVO - SAADIA MACKENZI - CASA 263 MES DE ENERO A ABRIL | D20: 263 | E20: 60 | G20: =+G19+E20+F20 -> 5538.91 | H20: a
A21: 45810 | B21: 17382 | C21: EFECTIVO - FLIA. DEL VALLE - CASA 90 MANT. ENERO A ABRIL | D21: 90 | E21: 60 | G21: =+G20+E21+F21 -> 5598.91 | H21: a
A22: 45810.356 | B22: 17383 | C22: deposito- Raul Murdock casa 95 - mant. Mayo | D22: 95 | E22: 15 | G22: =+G21+E22+F22 -> 5613.91
A23: 45810.356 | B23: 17384 | C23: YAPPY DE GUILLERMO CHALHOUB RODRIGUEZ POR Mayo y Junio 2025 Casa 250 Alborada | D23: 250 | E23: 30 | G23: =+G22+E23+F23 -> 5643.91 | H23: a
A24: 45810.356 | B24: 17385 | C24: BANCA MOVIL TRANSFERENCIA DE HECTOR GABRIEL IBARGUEN MURILLO mes de mayo flia Ibarguen | D24: 21 | E24: 15 | G24: =+G23+E24+F24 -> 5658.91 | H24: a
A25: 45811.356 | B25: 17386 | C25: YAPPY DE NAYRA DEL CARMEN RAMOS RAMOmes de junio casa 54 | D25: 54 | E25: 15 | G25: =+G24+E25+F25 -> 5673.91 | H25: a
A26: 45811.356 | B26: 17387 | C26: BANCA MOVIL TRANSFERENCIA DE LUIS ENRIQUE AMADOR MARTINEZ pago consergeria mes Junio | D26: 195 | E26: 15 | G26: =+G25+E26+F26 -> 5688.91 | H26: a
A27: 45811.466 | B27: 17388 | C27: YAPPY DE MANUEL ENRIQUE VILLARREAL GUILLEN -MES ABRIL Y MAYO | D27: 103 | E27: 30 | G27: =+G26+E27+F27 -> 5718.91 | H27: a
A28: 45811.466 | B28: 17389 | C28: YAPPY DE MANUEL ENRIQUE VILLARREAL GUILLEN -MES JUNIO | D28: 103 | E28: 15 | G28: =+G27+E28+F28 -> 5733.91 | H28: a
A29: 45811.466 | B29: 17390 | C29: BANCA MOVIL TRANSFERENCIA DE JESSENIA MAGALI FRUTO DE BETHANCOURT casa 112 Flia Bethancour | D29: 112 | E29: 45 | G29: =+G28+E29+F29 -> 5778.91 | H29: a
A30: 45811.466 | B30: 17391 | C30: YAPPY DE IDA CEMA JACKSON de VALENCIA - MAYO | D30: 270 | E30: 15 | G30: =+G29+E30+F30 -> 5793.91 | H30: a
A31: 45812.466 | B31: 17392 | C31: YAPPY DE PORFIRIO JUSTAVINO CEDEÑO casa 289 MES DE JUNIO | D31: 289 | E31: 15 | G31: =+G30+E31+F31 -> 5808.91 | H31: a
A32: 45812.466 | B32: 17393 | C32: YAPPY DE JACQUELINE YOVANIA VILLAMIL TORRES casa 298 - mayo | D32: 298 | E32: 15 | G32: =+G31+E32+F32 -> 5823.91 | H32: a
A33: 45812.466 | B33: 17394 | C33: BANCA MOVIL TRANSFERENCIA DE ISABEL RIQUELME MARTINEZ mensualidad junio casa 277 flia Riquelme | D33: 277 | E33: 15 | G33: =+G32+E33+F33 -> 5838.91 | H33: a
A34: 45812.466 | B34: 17395 | C34: BANCA MOVIL TRANSFERENCIA DE MARLENE BOYCE DAWKINS Garita 181 Abril | D34: 181 | E34: 15 | G34: =+G33+E34+F34 -> 5853.91 | H34: a
... A53: 45815.319 | B53: 17414 | C53: YAPPY DE YOLANDA ENEIDA LOPER ALABARCA POR mantenimiento junio 2025 casa 271 | D53: 271 | E53: 20 | G53: =+G52+E53+F53 -> 6328.91 | H53: a
A54: 45815.319 | B54: 17415 | C54: BANCA MOVIL TRANSFERENCIA DE DALIA ZORAIDA PETERS PAYNE Familia Peters casa 121 y 104 abriL Y MAYO | D54: 121 Y 104 | E54: 60 | G54: =+G53+E54+F54 -> 6388.91 | H54: a
A55: 45815.319 | B55: PAGOS | C55: BANCA MOVIL TRANSFERENCIA A 0472996299559 PEDRO ANTONIO GLASGOW BARRETT corte de hierba | D55: PAGOS | F55: -150 | G55: =+G54+E55+F55 -> 6238.91 | H55: a
A56: 45815.319 | B56: 17416 | C56: BANCA MOVIL TRANSFERENCIA DE FERNANDO CHAVERRA PINEDA Fernando Chaverra 3 86 1038 casa 317 MES DE JULIO | D56: 317 | E56: 15 | G56: =+G55+E56+F56 -> 6253.91 | H56: a
A57: 45815.319 | B57: PAGOS | C57: YAPPY A RODERICK ANEL CHIRU VALDES POR CIRTE HIERBA PARQUE 6TA OESTE PEQ Y CENTRO Y VEREDA | D57: PAGOS | F57: -188 | G57: =+G56+E57+F57 -> 6065.91 | H57: a
A58: 45815.319 | B58: PAGOS | C58: YAPPY A MIGUEL ROGELIO SANCHEZ PALACIO POR Bolsas de Basura corte hierba Alborada | D58: PAGOS | F58: -12.38 | G58: =+G57+E58+F58 -> 6053.53 | H58: a
A59: 45815.319 | B59: PAGOS | C59: YAPPY A RODERICK ANEL CHIRU VALDES POR Excedentes corte hierba | D59: PAGOS | F59: -22 | G59: =+G58+E59+F59 -> 6031.53 | H59: a
A60: 45815.319 | B60: 17417 | C60: BANCA MOVIL TRANSFERENCIA DE YOLANDA MAGALI CAMPOS GONZALEZ seguridad y mant junio 2025 | D60: 304 | E60: 15 | G60: =+G59+E60+F60 -> 6046.53 | H60: a
A61: 45816.319 | B61: 17418 | C61: YAPPY DE CIARA LUZ JIMENEZ CONCEPCION - MES JUNIO Y JULIO | D61: 16 | E61: 30 | G61: =+G60+E61+F61 -> 6076.53 | H61: a
A62: 45816.319 | B62: 17419 | C62: BANCA MOVIL TRANSFERENCIA DE DALIS YADIRA BANDINI AGUSTINE Pago MES DE JULIO seguridad flia Bandini Cha | D62: 178 | E62: 15 | G62: =+G61+E62+F62 -> 6091.53 | H62: a
A63: 45817.319 | B63: PAGOS | C63: YAPPY A MELVIN CARLTON FOSTER GALASTICA POR PODA PARQUES 3A Y CUARTA CENTRO | D63: PAGOS | F63: -60 | G63: =+G62+E63+F63 -> 6031.53 | H63: a
A64: 45824 | B64: 17420 | C64: BANCA MOVIL TRANSFERENCIA DE 0427120001653 casa 200 mes d junio y julio | D64: 200 | E64: 30 | G64: =+G63+E64+F64 -> 6061.53 | H64: a
A65: 45833 | B65: 17421 | C65: BANCA EN LINEA TRANSFERENCIA DE 0427120001653 casa 61 flia Gittens- abril y mayo | D65: 61 | E65: 30 | G65: =+G64+E65+F65 -> 6091.53 | H65: a
A66: 45819 | B66: PAGOS | C66: YAPPY A JOSE ALBERTO MARCIAGA BRAVO POR MATERIALES REFORZAMIENTO PUERTA PEATONAL DE ENTRAD | D66: PAGOS | E66: 0 | F66: -182.95 | G66: =+G65+E66+F66 -> 5908.58 | H66: a
A67: 45819 | B67: 17422 | C67: BANCA MOVIL TRANSFERENCIA DE ROMELIA ORISSA HALL JOHNSON Junio 201 | D67: 201 | E67: 15 | G67: =+G66+E67+F67 -> 5923.58 | H67: a
A68: 45819 | B68: 17423 | C68: ACH XPRESS - EMILIO STERLING LOVET WILSON -mayo | D68: 67 | E68: 15 | G68: =+G67+E68+F68 -> 5938.58 | H68: a
A69: 45820 | B69: 17424 | C69: YAPPY DE JAIME ALBERTO PEREZ MERO junio casa 205 | D69: 205 | E69: 15 | G69: =+G68+E69+F69 -> 5953.58 | H69: a
A70: 45820 | B70: 17425 | C70: BANCA MOVIL TRANSFERENCIA DE JANINA ANGELINNA BORELLY de MELO Pago de garita de abril mayo Y JUNIO | D70: 279 | E70: 45 | G70: =+G69+E70+F70 -> 5998.58 | H70: a
A71: 45820 | B71: 17426 | C71: YAPPY DE GIRLY ALEXIA ROBINSON MATOS POR Mes Junio casa 257 Flia Icaza | D71: 257 | E71: 15 | G71: =+G70+E71+F71 -> 6013.58 | H71: a
A72: 45820 | B72: 17427 | C72: YAPPY DE ARTURO ROGELIO ROBINSON WILLIAMS POR Pago mantenimiento casa 173 de mayo a agosto | D72: 173 | E72: 60 | G72: =+G71+E72+F72 -> 6073.58 | H72: a
A73: 45820 | B73: PAGOS | C73: YAPPY A JOSE ALBERTO MARCIAGA BRAVO POR CANC REP PUERTA PEATONAL ENTRADA PRINCIPAL | D73: PAGOS | E73: 0 | F73: -117 | G73: =+G72+E73+F73 -> 5956.58 | H73: a
A74: 45821 | B74: 17428 | C74: BANCA MOVIL TRANSFERENCIA DE LINDA YAJAIRA LAJON ANDERSON Casa 219 junio y julio | D74: 219 | E74: 30 | G74: =+G73+E74+F74 -> 5986.58 | H74: a
A75: 45821 | B75: 17429 | C75: YAPPY DE VANESSA VICTORIA PARNTHER LUZCANDO POR Mant casa 80 mes de julio y agosto Sra Flo | D75: 80 | E75: 30 | G75: =+G74+E75+F75 -> 6016.58 | H75: a
A76: 45821 | B76: 17430 | C76: YAPPY DE VANESSA VICTORIA PARNTHER LUZCANDO POR Mant casa 75 calle 2da Este mes de Mayo y junio | D76: 75 | E76: 30 | G76: =+G75+E76+F76 -> 6046.58 | H76: a
A77: 45821 | B77: 17431 | C77: YAPPY DE ANTONIO ROMAN HALL JAEN- enero febrero y marzo casa 331 | D77: 331 | E77: 45 | G77: =+G76+E77+F77 -> 6091.58 | H77: a
A78: 45821 | B78: 17432 | C78: BANCA MOVIL TRANSFERENCIA DE YISEL BONET ALTAMIRANDA de YARD pago junio mant y Seg casa 156 | D78: 156 | E78: 15 | G78: =+G77+E78+F78 -> 6106.58 | H78: a
A79: 45821 | B79: 17433 | C79: BANCA MOVIL TRANSFERENCIA DE TOYA DELMINA BINGHAM de BETEGON Pago de mantenimiento Junio | D79: D-05 | E79: 15 | G79: =+G78+E79+F79 -> 6121.58 | H79: a
A80: 45821 | B80: 17434 | C80: ACH - SERGIO JOSE DE CASTRO BUENDIA | D80: 246 | E80: 15 | G80: =+G79+E80+F80 -> 6136.58 | H80: a
A81: 45821 | B81: 17435 | C81: BANCA MOVIL TRANSFERENCIA DE YAVIRITZEL DEL CARMEN PANAY junio casa 187 familia Panay | D81: 187 | E81: 15 | G81: =+G80+E81+F81 -> 6151.58 | H81: a
A82: 45821 | B82: 17436 | C82: YAPPY DE SUGEIRIS YANIRETH BARRETT JIMENEZ - FLIA DIAZ -MES MAYO | D82: 326 | E82: 15 | G82: =+G81+E82+F82 -> 6166.58 | H82: a
A83: 45822 | B83: 17437 | C83: BANCA MOVIL TRANSFERENCIA DE YENITZA NAYROBIS ASHAW SMALL cuota mes de junio casa 261 | D83: 261 | E83: 15 | G83: =+G82+E83+F83 -> 6181.58 | H83: a
A84: 45822 | B84: 17438 | C84: ACH XPRESS - JOSE LUIS GONZALEZ FLETCHER O MAIQUEL ITZELA POLLACK MES DE JUNIO | D84: 247 | E84: 15 | G84: =+G83+E84+F84 -> 6196.58 | H84: a
A85: 45822 | B85: 17439 | C85: YAPPY DE MARIBEL ARISPE de VEGA MES DE JUNIO | D85: 296 | E85: 15 | G85: =+G84+E85+F85 -> 6211.58 | H85: a
A86: 45822 | B86: 17440 | C86: YAPPY DE LISSIBETH- FLIA BEJARANO - MES DE MAYO Y JUNIO | D86: 218 | E86: 30 | G86: =+G85+E86+F86 -> 6241.58 | H86: a
A87: 45822 | B87: 17441 | C87: YAPPY DE YESICA MARLENE CHIFUNDO DE PRESTAN - MES DE JUNIO | D87: 210 | E87: 15 | G87: =+G86+E87+F87 -> 6256.58 | H87: a
A88: 45822 | B88: 17442 | C88: BANCA MOVIL TRANSFERENCIA DE JOSE MANUEL TUÑON RAMOS Pago de Junio Casa 137 Familia Tunon | D88: 137 | E88: 15 | G88: =+G87+E88+F88 -> 6271.58 | H88: a
A89: 45822 | B89: 17443 | C89: YAPPY DE SHARYN TAVANE DELGADO ROWE POR Junio casa 199 Sharyn Delgado | D89: 199 | E89: 15 | G89: =+G88+E89+F89 -> 6286.58 | H89: a
A90: 45822 | B90: 17444 | C90: YAPPY DE NIDIA EDITH RODRIGUEZ ORTIZ POR Familia Rodriguez casa 267 - ABRIL | D90: 267 | E90: 15 | G90: =+G89+E90+F90 -> 6301.58 | H90: a
A91: 45823 | B91: 17445 | C91: YAPPY DE ANTONIO ALCEDO AGUIRRE POR Alcedo casa 217 julio agosto y septiembre | D91: 217 | E91: 45 | G91: =+G90+E91+F91 -> 6346.58 | H91: a
... A97: 45825 | B97: 17451 | C97: BANCA MOVIL TRANSFERENCIA DE NATIVIDAD VALENCIA de JIMENEZ Familia Jimenez Casa 26 mes de JUNIO | D97: 26 | E97: 15 | G97: =+G96+E97+F97 -> 6436.58 | H97: a
A98: 45825 | B98: 17452 | C98: BANCA MOVIL TRANSFERENCIA DE MIGUEL ANTONIO TAMAYO MARTINEZ ALBORADA FLIA TAMAYO CASA D19 -MES DE JUNIO | D98: D-19 | E98: 15 | G98: =+G97+E98+F98 -> 6451.58 | H98: a
A99: 45825 | B99: 17453 | C99: DEPOSITO - YAMILKA PARRIS - CASA 278 MES DE MAYO | D99: 278 | E99: 15 | G99: =+G98+E99+F99 -> 6466.58 | H99: a
A100: 45826 | B100: 17454 | C100: BANCA MOVIL TRANSFERENCIA DE DALIS YADIRA BANDINI AGUSTINE Pago seguridad CASA 178 fMES DE AGOSTO | D100: 178 | E100: 15 | G100: =+G99+E100+F100 -> 6481.58 | H100: a
A101: 45826 | B101: 17455 | C101: YAPPY BG DE SUMAYKIRA YANILET GRENALD FERREIRA POR Pago de casa 136 Familia Grenald MES DE JUNIO | D101: 136 | E101: 15 | G101: =+G100+E101+F101 -> 6496.58 | H101: a
A102: 45826 | B102: 17456 | C102: ACH XPRESS - YOHANA MOLINAR MES DE MAYO | D102: 113 | E102: 15 | F102: 0 | G102: =+G101+E102+F102 -> 6511.58 | H102: a
A103: 45826 | B103: PAGOS | C103: PAGO YAPPY BG A lumicentro- Compra de lamparas Garita | D103: PAGOS | E103: 0 | F103: -136.1 | G103: =+G102+E103+F103 -> 6375.48 | H103: a
A104: 45818 | B104: 17457 | C104: BANCA MOVIL TRANSFERENCIA DE JOSSUA EMMIR WILLIAMS RIOS - Flia Williams - casa 327 Marzo | D104: 327 | E104: 15 | G104: =+G103+E104+F104 -> 6390.48 | H104: a
A105: 45819 | B105: 17458 | C105: BANCA MOVIL TRANSFERENCIA DE RAQUEL MAGALI RACERO de LAWRENCE mes de mayo familia Lawrence | D105: 120 | E105: 15 | G105: =+G104+E105+F105 -> 6405.48 | H105: a
A106: 45826 | B106: 17459 | C106: YAPPY BG DE ADDIS MASSIEL BETEGON ROSALES POR abril y mayo casa 33 Betegon Rosales | D106: 33 | E106: 30 | G106: =+G105+E106+F106 -> 6435.48 | H106: a
A107: 45826 | B107: 17460 | C107: YAPPY BG DE ALAIN AMINT ARAUZ POWELL POR Casa1 mes de junio | D107: 1 | E107: 15 | G107: =+G106+E107+F107 -> 6450.48 | H107: a
A108: 45827 | B108: 17461 | C108: BANCA MOVIL TRANSFERENCIA DE JOSSUA EMMIR WILLIAMS RIOS flia Williams, casa 327 abril | D108: 327 | E108: 15 | G108: =+G107+E108+F108 -> 6465.48 | H108: a
A109: 45827 | B109: 17462 | C109: YAPPY BG DE NATIVIDAD SANCHEZ DE FORBES- junio | D109: 175 | E109: 15 | G109: =+G108+E109+F109 -> 6480.48 | H109: a
A110: 45827 | B110: 17463 | C110: YAPPY BG DE JAZMIN MENDOZA CASTRILLON POR Casa 170 | D110: 170 | E110: 20 | G110: =+G109+E110+F110 -> 6500.48 | H110: a
A111: 45827 | B111: 17464 | C111: YAPPY BG DE LUCAS ANTONIO CORTES SURGEON POR Casa 134 mayo junio | D111: 134 | E111: 30 | G111: =+G110+E111+F111 -> 6530.48 | H111: a
A112: 45827 | B112: PAGOS | C112: BANCA EN LINEA GLOBAL BANK 23332000633 Enrique Silvera | D112: PAGOS | E112: 0 | F112: -777.5 | G112: =+G111+E112+F112 -> 5752.98 | H112: a
A113: 45828 | B113: 17465 | C113: BANCA MOVIL TRANSFERENCIA DE JAIME CEBALLOS ANDRADE Casa 147 familia Ceballos abr may jun | D113: 147 | E113: 45 | G113: =+G112+E113+F113 -> 5797.98 | H113: a
A114: 45828 | B114: 17466 | C114: ACH - EDWIN IDEL CEDEÃ?O CARDENAS - abril- mayo y junio | D114: 258 | E114: 45 | G114: =+G113+E114+F114 -> 5842.98 | H114: a
A115: 45828 | B115: 17467 | C115: YAPPY BG DE PASTOR CAMARENA SMITH - ABRIL, MAYO Y JUNIO | D115: D-10 | E115: 45 | G115: =+G114+E115+F115 -> 5887.98 | H115: a
A116: 45828 | B116: 17468 | C116: YAPPY BG DE JAIME DAVID ANDERSON SINCLAIR- MES DE JUNIO | D116: 172 | E116: 15 | G116: =+G115+E116+F116 -> 5902.98 | H116: a
A117: 45828 | B117: 17469 | C117: YAPPY BG DE JAIRO ABDIEL BUITRAGO VASQUEZ POR Mensualidad mes de mayo | D117: 100 | E117: 15 | G117: =+G116+E117+F117 -> 5917.98 | H117: a
A118: 45828 | B118: 17470 | C118: YAPPY BG DE IRASEMA ESTHER MURILLO DE SMALL POR casa 119 Flia Small 3ra Oeste seguridad mES MAYO Y JUNIO | D118: 119 | E118: 30 | G118: =+G117+E118+F118 -> 5947.98 | H118: a
A119: 45829 | B119: 17471 | C119: YAPPY BG DE OSVALDO HERRERA CARRIAZO POR casa 53 BAMBY HERRERA junio | D119: 53 | E119: 15 | G119: =+G118+E119+F119 -> 5962.98 | H119: a
A120: 45832 | B120: 17472 | C120: DEPOSITO- FLIA CEBALLOS - MES DE JUNIO Y JULIO | D120: 13 | E120: 30 | G120: =+G119+E120+F120 -> 5992.98 | H120: a
A121: 45833 | B121: PAGOS | C121: BANCA EN LINEA TRANSFERENCIA A 0427120001653 IDAAN GARITA | D121: PAGOS | E121: 0 | F121: -39.66 | G121: =+G120+E121+F121 -> 5953.32 | H121: a
A122: 45833 | B122: PAGOS | C122: BANCA EN LÍNEA TIGO HOGAR - PYME (88280329) | D122: PAGOS | E122: 0 | F122: -113.26 | G122: =+G121+E122+F122 -> 5840.06 | H122: a
A123: 45833 | B123: PAGOS | C123: BANCA EN LÍNEA ENSA (ELEKTRA NORESTE) (000000882669) | D123: PAGOS | E123: 0 | F123: -25.25 | G123: =+G122+E123+F123 -> 5814.81 | H123: a
A124: 45834 | B124: PAGOS | C124: BANCA MOVIL TRANSFERENCIA A 0427120001653 lamparas para garita | D124: PAGOS | E124: 0 | F124: -29 | G124: =+G123+E124+F124 -> 5785.81 | H124: a
A125: 45828 | B125: 17473 | C125: Carlos Garay - mes -junio casa 4 | D125: 4 | E125: 15 | G125: =+G124+E125+F125 -> 5800.81 | H125: a
B126: 17474 | C126: RECIBO DE JULIO 2025 | D126: JULIO | E126: 0 | F126: 0 | G126: =+G125+E126+F126 -> 5800.81 | H126: a
A127: 45834 | B127: 17475 | C127: BANCA MOVIL TRANSFERENCIA DE YOMAIRA YAISET ASHAW SMALL cuota de mayo y Junio casa 293 | D127: 293 | E127: 30 | F127: 0 | G127: =+G126+E127+F127 -> 5830.81 | H127: a
A128: 45834 | B128: 17476 | C128: BANCA MOVIL TRANSFERENCIA DE GISELA GONZALEZ QUIROZ Mant y Seguridad Casa 88 Gisela Gonzal | D128: 88 | E128: 45 | G128: =+G127+E128+F128 -> 5875.81 | H128: a
...

Sheet pagos julio 2025
A1: DETALLE DE PAGOS EN BANCO
A2: MES DE JULIO DE 2025
A4: Cuenta:Alborada 04-11-00-000468-4
A8: Fecha | B8: Recibo | C8: Descripción | D8: No.Casa | E8: Cobros | F8: Pagos | G8: Saldo total
A10: 45838 | C10: SALDO AL 30 DE JUNIO DE 2025 | E10: =+'pagos junio 2025'!G158 -> 4424.69 | G10: =+E10 -> 4424.69
A11: 45843 | B11: 17474 | C11: Efectivo - casa 306 Roberto Jenkins - mes de Junio | D11: 306 | E11: 15 | G11: =+G10+E11+F11 -> 4439.69
A12: 45839 | B12: 17504 | C12: YAPPY BG DE MIOZOTIS DEL CARMEN OLMOS LARA- MES DE JULIO | D12: 10 | E12: 15 | G12: =+G11+E12+F12 -> 4454.69 | H12: a
A13: 45839 | B13: 17505 | C13: BANCA MOVIL TRANSFERENCIA DE BARBARA ANN BENDIGO DE SANTAMARIA Agosto 2025 Flia Santamaria | D13: 44 | E13: 15 | G13: =+G12+E13+F13 -> 4469.69 | H13: a
A14: 45839 | B14: 17506 | C14: YAPPY BG DE JACQUELINE YOVANIA VILLAMIL TORRES- MES DE JUNIO | D14: 298 | E14: 15 | G14: =+G13+E14+F14 -> 4484.69 | H14: a
A15: 45839 | B15: 17507 | C15: BANCA MOVIL TRANSFERENCIA DE FERNANDO JOSE PENAS BLANCO (O) FERNANDO ANTONIO PENAS DOMING MES DE MAYO | D15: 169 | E15: 15 | G15: =+G14+E15+F15 -> 4499.69 | H15: a
A16: 45839 | B16: 17508 | C16: YAPPY BG DE NAYRA DEL CARMEN RAMOS RAMOS (O) JERONIMO VALENTIN HERNANDEZ POR pago de Segu- JULIO | D16: 54 | E16: 15 | G16: =+G15+E16+F16 -> 4514.69 | H16: a
A17: 45839 | B17: 17509 | C17: BANCA MOVIL TRANSFERENCIA DE CELIA ESTHER SALAZAR de PAULT casa 183 mes de abril y mayo | D17: 183 | E17: 30 | G17: =+G16+E17+F17 -> 4544.69 | H17: a
A18: 45839 | B18: 17510 | C18: BANCA MOVIL TRANSFERENCIA DE ORLANDO ENRIQUE ARGUELLES CUESTA Julio Agosto casa 313 | D18: 313 | E18: 30 | G18: =+G17+E18+F18 -> 4574.69 | H18: a
A19: 45839 | B19: 17511 | C19: YAPPY BG DE YARITZA YAMILKA COOPER CHIFUNDO POR Casa 202 SChifundo YCooper mes de Junio 2 | D19: 202 | E19: 15 | G19: =+G18+E19+F19 -> 4589.69 | H19: a
A20: 45840 | B20: 17512 | C20: YAPPY BG DE MARIET BROOKS SALAMANCA POR seguridad flia Brooks- MAYO Y JUNIO | D20: 78 | E20: 30 | G20: =+G19+E20+F20 -> 4619.69 | H20: a
A21: 45840 | B21: 17513 | C21: YAPPY BG DE NELSON AZARIAS MORENO MAGDALENO POR Casa 310 mes de junio | D21: 310 | E21: 15 | G21: =+G20+E21+F21 -> 4634.69 | H21: a
A22: 45840 | B22: 17514 | C22: DEPOSITO -RAUL MURDOCK - JUNIO | D22: 95 | E22: 15 | G22: =+G21+E22+F22 -> 4649.69 | H22: a
A23: 45840 | B23: 17515 | C23: YAPPY BG DE LINETH GISSEL SANTOS MELENDEZ POR abril mayo junio Familia Paz casa 7 | D23: 7 | E23: 45 | G23: =+G22+E23+F23 -> 4694.69 | H23: a
... A34: 45841 | B34: 17526 | C34: ACH - GEORGIANA GAVIRIA PACHECO- JUNIO Y JULIO | D34: 86 | E34: 30 | G34: =+G33+E34+F34 -> 4989.69 | H34: a
A35: 45841 | B35: PAGOS | C35: BANCA MOVIL TRANSFERENCIA A 0427998627468 CHINA PANDA LIGHTS, S.A. lamparas garita | D35: PAGOS | E35: 0 | F35: -41.2 | G35: =+G34+E35+F35 -> 4948.49 | H35: a
A36: 45841 | B36: PAGOS | C36: BANCA MOVIL GLOBAL BANK 23332000633 Enrique Silvera | D36: PAGOS | E36: 0 | F36: -100 | G36: =+G35+E36+F36 -> 4848.49 | H36: a
A37: 45841 | B37: 17527 | C37: YAPPY BG DE SHANI NG de CHIU POR Familia Chiu pago de junio 2025 | D37: 292 | E37: 15 | G37: =+G36+E37+F37 -> 4863.49 | H37: a
A38: 45841 | B38: PAGOS | C38: BANCA MOVIL TRANSFERENCIA A 0454000010658 JOSE ALBERTO MARCIAGA BRAVO pintar y reparar por | D38: PAGOS | E38: 0 | F38: -100 | G38: =+G37+E38+F38 -> 4763.49 | H38: a
A39: 45842 | B39: 17528 | C39: BANCA MOVIL TRANSFERENCIA DE NIDIA SILGADO LEON Casa 164- JULIO | D39: 164 | E39: 15 | G39: =+G38+E39+F39 -> 4778.49 | H39: a
A40: 45842 | B40: 17529 | C40: YAPPY BG DE MANUEL DE JESUS MEDINA ORTEGA POR casa25 mensualidad julio y agosto | D40: 25 | E40: 30 | G40: =+G39+E40+F40 -> 4808.49 | H40: a
A41: 45842 | B41: 17530 | C41: BANCA MOVIL TRANSFERENCIA DE ADA ARGELIA CHONG CORREA - ABRIL Y MAYO | D41: 133 | E41: 30 | G41: =+G40+E41+F41 -> 4838.49 | H41: a
A42: 45843 | B42: 17531 | C42: YAPPY BG DE ANA MICHELLE PILE OSSA (O) ARELIS VANESSA OSSA DIAZ POR junio casa 106 AOssa | D42: 106 | E42: 15 | G42: =+G41+E42+F42 -> 4853.49 | H42: a
A43: 45843 | B43: 17532 | C43: YAPPY BG DE YULIXA DEL CARMEN ESPADA de SIERRA POR Casa 110 Flia Sierra Espada - MAYO | D43: 110 | E43: 15 | G43: =+G42+E43+F43 -> 4868.49 | H43: a
A44: 45843 | B44: 17533 | C44: YAPPY BG DE YOLANDA ENEIDA LOPER ALABARCA POR mantenimiento julio 25 casa 271 | D44: 271 | E44: 20 | G44: =+G43+E44+F44 -> 4888.49 | H44: a
A45: 45843 | B45: 17534 | C45: YAPPY BG DE LUZMILA ELENA PORTER DE QUINTERO POR 050625 LUZMILA PORTER PRIMERA C47 - JUNIO | D45: 47 | E45: 15 | G45: =+G44+E45+F45 -> 4903.49 | H45: a
A46: 45843 | B46: 17535 | C46: BANCA MOVIL TRANSFERENCIA DE FERNANDO CHAVERRA PINEDA Fernando Chaverra casa 317- AGOSTO | D46: 317 | E46: 15 | G46: =+G45+E46+F46 -> 4918.49 | H46: a
A47: 45843 | B47: 17536 | C47: YAPPY BG DE STEPHANIE MICHELLE ESPINOSA GONZALEZ POR Casa 123 flia Espinosa mes de junio- JULIO Y AGOSTO | D47: 123 | E47: 45 | G47: =+G46+E47+F47 -> 4963.49 | H47: a
A48: 45843 | B48: PAGOS | C48: YAPPY BG A RODERICK ANEL CHIRU VALDES POR Parques 6ta vereda Circunvalacion | D48: PAGOS | E48: 0 | F48: -210 | G48: =+G47+E48+F48 -> 4753.49 | H48: a
A49: 45843 | B49: PAGOS | C49: BANCA MOVIL GLOBAL BANK 23332000633 Enrique Silvera | D49: PAGOS | E49: 0 | F49: -400 | G49: =+G48+E49+F49 -> 4353.49 | H49: a
A50: 45843 | B50: PAGOS | C50: BANCA MOVIL TRANSFERENCIA A 0495996629370 SANTOS DIOMEDES ARAUZ MEDINA puerta peatonal | D50: PAGOS | E50: 0 | F50: -385.8 | G50: =+G49+E50+F50 -> 3967.69 | H50: a
A51: 45843 | B51: PAGOS | C51: BANCA MOVIL TRANSFERENCIA A 0472996299559 PEDRO ANTONIO GLASGOW BARRETT corte de hierba | D51: PAGOS | E51: 0 | F51: -150 | G51: =+G50+E51+F51 -> 3817.69 | H51: a
A52: 45843 | B52: 17537 | C52: YAPPY BG DE YANETH YAMILKA BADILLA PINEDA POR cuota julio casa 157 | D52: 157 | E52: 15 | G52: =+G51+E52+F52 -> 3832.69 | H52: a
A53: 45843 | B53: PAGOS | C53: YAPPY BG A MIGUEL ROGELIO SANCHEZ PALACIO POR Insumos corte hierba Alborada | D53: PAGOS | E53: 0 | F53: -23.57 | G53: =+G52+E53+F53 -> 3809.12 | H53: a
A54: 45843 | B54: 17538 | C54: YAPPY BG DE DIANA MARIA SANCHEZ FLORES - FLIA VEGA - JUNIO | D54: D-24 | E54: 15 | G54: =+G53+E54+F54 -> 3824.12 | H54: a
A55: 45844 | B55: 17539 | C55: YAPPY BG DE JAIME ALBERTO PEREZ MERO- JULIO 205 | D55: 205 | E55: 15 | G55: =+G54+E55+F55 -> 3839.12 | H55: a
A56: 45844 | B56: PAGOS | C56: YAPPY BG A MELVIN CARLTON FOSTER GALASTICA POR CORTE HIERBA PARQUES 3A Y 4TA | D56: PAGOS | E56: 0 | F56: -60 | G56: =+G55+E56+F56 -> 3779.12 | H56: a
A57: 45845 | B57: 17540 | C57: YAPPY BG DE MAUREL MARIAM MIER de ESCOBAR- junio | D57: 221 | E57: 15 | G57: =+G56+E57+F57 -> 3794.12 | H57: a
A58: 45845 | B58: 17541 | C58: YAPPY - flia ibarguen- MES DE JUNIO | D58: 21 | E58: 15 | G58: =+G57+E58+F58 -> 3809.12 | H58: a
A59: 45845 | B59: 17542 | C59: YAPPY BG DE TAHIMY GUADALUPE IGLESIAS HURTADO POR Aura hurtado casa 9 junio julio | D59: 9 | E59: 30 | G59: =+G58+E59+F59 -> 3839.12 | H59: a
A60: 45845 | B60: 17543 | C60: YAPPY BG DE PORFIRIO JUSTAVINO CEDEÑO POR casa 289 mes de julio | D60: 289 | E60: 15 | G60: =+G59+E60+F60 -> 3854.12 | H60: a
A61: 45845 | B61: 17544 | C61: YAPPY BG DE GILBERTO GUADALUPE GARCIA GONZALEZ- febrero | D61: 301 | E61: 15 | G61: =+G60+E61+F61 -> 3869.12 | H61: a
A62: 45848 | B62: 17545 | C62: Efectivo- casa 254 Ezequiel Molinar - Marzo, abril, Mayo y Junio | D62: 254 | E62: 60 | G62: =+G61+E62+F62 -> 3929.12 | H62: a
A63: 45852 | B63: 17546 | C63: Efectivo casa 57 Piedad del Cid- mes de Julio | D63: 57 | E63: 15 | G63: =+G62+E63+F63 -> 3944.12 | H63: a
A64: 45852 | B64: 17547 | C64: Efectivo - casa 285 Delano Saunders - mes de julio y agosto | D64: 285 | E64: 30 | G64: =+G63+E64+F64 -> 3974.12 | H64: a
A65: 45846 | B65: 17548 | C65: BANCA MOVIL TRANSFERENCIA DE ALIZA EMERITA JIMENEZ - JULIO Y AGOSTO | D65: 30 | E65: 15 | G65: =+G64+E65+F65 -> 3989.12 | H65: a
A66: 45846 | B66: 17549 | C66: YAPPY BG DE ILKA MELISA MARK HOY- MES DE JULIO | D66: 59 | E66: 30 | G66: =+G65+E66+F66 -> 4019.12 | H66: a
A67: 45846 | B67: 17550 | C67: YAPPY BG DE NITZIA ITZEL AGUILAR GALVAN POR Familia Aguilar Casa 56 2da calle oeste - ABRIL | D67: 56 | E67: 15 | G67: =+G66+E67+F67 -> 4034.12 | H67: a
A68: 45847 | B68: 17551 | C68: ACH XPRESS - DEMETRIO CELSO PRESCOTT RODRIGUEZ- mes de junio | D68: 241 | E68: 15 | G68: =+G67+E68+F68 -> 4049.12 | H68: a
... A76: 45849 | B76: 17559 | C76: YAPPY BG DE MANUEL ENRIQUE VILLARREAL GUILLEN MES DE JULIO | D76: 103 | E76: 15 | G76: =+G75+E76+F76 -> 4274.12 | H76: a
A77: 45849 | B77: PAGOS | C77: BANCA MOVIL GLOBAL BANK 23332000633 Enrique Silvera | D77: PAGOS | E77: 0 | F77: -100 | G77: =+G76+E77+F77 -> 4174.12 | H77: a
A78: 45850 | B78: 17560 | C78: YAPPY BG DE MADELEIN NOEMY TAYLOR DALEY POR casa 118 familia Taylor mes de Mayo y Junio | D78: 118 | E78: 30 | F78: 0 | G78: =+G77+E78+F78 -> 4204.12 | H78: a
A79: 45850 | B79: 17561 | C79: YAPPY BG DE VIELKA LUZMILA CUSATTI ANAYA- agosto | D79: 20 | E79: 15 | F79: 0 | G79: =+G78+E79+F79 -> 4219.12 | H79: a
A80: 45850 | B80: 17562 | C80: ACH XPRESS - JOSE LUIS GONZALEZ FLETCHER mes de Julio | D80: 247 | E80: 15 | F80: 0 | G80: =+G79+E80+F80 -> 4234.12 | H80: a
A81: 45852 | B81: 17563 | C81: YAPPY BG DE NUDIA ESTHER MORALES de GUERRA casa 315 Flia Morales - Junio y Julio | D81: 315 | E81: 30 | G81: =+G80+E81+F81 -> 4264.12 | H81: a
A82: 45852 | B82: 17564 | C82: YAPPY BG DE MARTHA BIBIANA ACOSTA MARULANDA POR casa 105 familia Estrada mes junio y juli | D82: 105 | E82: 30 | G82: =+G81+E82+F82 -> 4294.12 | H82: a
A83: 45852 | B83: 17565 | C83: YAPPY BG DE GIRLY ALEXIA ROBINSON MATOS POR Mantenimiento casa 257 Flia Icaza mes de Julio | D83: 257 | E83: 15 | G83: =+G82+E83+F83 -> 4309.12 | H83: a
A84: 45852 | B84: 17566 | C84: BANCA MOVIL TRANSFERENCIA DE YAVIRITZEL DEL CARMEN PANAY mensualidad de julio casa 187 fam | D84: 187 | E84: 15 | G84: =+G83+E84+F84 -> 4324.12 | H84: a
A85: 45852 | B85: 17567 | C85: YAPPY BG DE ERNESTO GALVAN LEON (FANCYS CLUB) mes de Julio | D85: 139 | E85: 15 | G85: =+G84+E85+F85 -> 4339.12 | H85: a
A86: 45853 | B86: 17568 | C86: YAPPY BG DE MELANY DEL CARMEN TAYLOR DELGADO POR Casa 107 familia Taylor 3era oeste mes de julio | D86: 107 | E86: 15 | G86: =+G85+E86+F86 -> 4354.12 | H86: a
A87: 45853 | B87: 17569 | C87: BANCA MOVIL TRANSFERENCIA DE YISEL BONET ALTAMIRANDA DE YARD pago seg y mabt casa 156 mes de Julio | D87: 156 | E87: 15 | G87: =+G86+E87+F87 -> 4369.12 | H87: a
A88: 45853 | B88: 17570 | C88: ACH - YARABY ORQUIDIA JIMENEZ JONES DE ABRAHAM mes de Julio | D88: 303 | E88: 15 | G88: =+G87+E88+F88 -> 4384.12 | H88: a
A89: 45853 | B89: 17571 | C89: TRANSFERENCIA - DAYRA LUCILA CANALES casa 240 mes Julio y Agosto | D89: 240 | E89: 32 | G89: =+G88+E89+F89 -> 4416.12 | H89: a
A90: 45853 | B90: 17572 | C90: EFECTIVO - casa 111 FLIA HAMILTON - MES DE JUNIO Y JULIO | D90: 111 | E90: 30 | G90: =+G89+E90+F90 -> 4446.12 | H90: a
A91: 45853 | B91: 17573 | C91: YAPPY BG DE SHARYN TAVANE DELGADO ROWE POR Julio casa 199 Sharyn Delgado | D91: 199 | E91: 15 | G91: =+G90+E91+F91 -> 4461.12 | H91: a
A92: 45853 | B92: 17574 | C92: ACH - SERGIO JOSE DE CASTRO BUENDIA- mes de julio | D92: 246 | E92: 15 | G92: =+G91+E92+F92 -> 4476.12 | H92: a
A93: 45853 | B93: 17575 | C93: BANCA MOVIL TRANSFERENCIA DE ROMELIA ORISSA HALL JOHNSON juliio | D93: 201 | E93: 15 | G93: =+G92+E93+F93 -> 4491.12 | H93: a
A94: 45853 | B94: 17576 | C94: BANCA MOVIL TRANSFERENCIA DE TOYA DELMINA BINGHAM de BETEGON Pago de mant-julio | D94: D-5 | E94: 15 | G94: =+G93+E94+F94 -> 4506.12 | H94: a
A95: 45853 | B95: 17577 | C95: YAPPY BG DE YESICA MARLENE CHIFUNDO DE PRESTAN POR pago del mantenimiento del mes de Julio | D95: 210 | E95: 15 | G95: =+G94+E95+F95 -> 4521.12 | H95: a
A96: 45853 | B96: 17578 | C96: BANCA MOVIL TRANSFERENCIA DE JANINA ANGELINNA BORELLY de MELO Pago de julio agosto sept ca | D96: 279 | E96: 45 | G96: =+G95+E96+F96 -> 4566.12 | H96: a
A97: 45853 | B97: 17579 | C97: BANCA MOVIL TRANSFERENCIA DE FERNANDO DE CASTRO BUENDIA | D97: 311 | E97: 15 | G97: =+G96+E97+F97 -> 4581.12 | H97: a
A98: 45854 | B98: PAGOS | C98: DAYRA CANALES - COMPRA DE FOCOS PARA LAMPARAS | D98: PAGOS | F98: -6.41 | G98: =+G97+E98+F98 -> 4574.71 | H98: a
A99: 45854 | B99: 17580 | C99: BANCA MOVIL TRANSFERENCIA DE MIGUEL ANTONIO TAMAYO MARTINEZ Mes de Julio Casa D19 Flia Tam | D99: D-19 | E99: 15 | G99: =+G98+E99+F99 -> 4589.71 | H99: a
A100: 45854 | B100: 17581 | C100: BANCA MOVIL TRANSFERENCIA DE YOLANDA FORBES FERNANDEZ- mes de julio | D100: 155 | E100: 15 | G100: =+G99+E100+F100 -> 4604.71 | H100: a
A101: 45854 | B101: 17582 | C101: YAPPY BG DE ARIEL CORPAS BETEGON- mes de julio | D101: 319 | E101: 15 | G101: =+G100+E101+F101 -> 4619.71 | H101: a
A102: 45854 | B102: 17583 | C102: BANCA MOVIL TRANSFERENCIA DE YENITZA NAYROBIS ASHAW SMALL cuota mes de julio casa 261 | D102: 261 | E102: 15 | G102: =+G101+E102+F102 -> 4634.71 | H102: a
A103: 45854 | B103: 17584 | C103: YAPPY BG DE SUGEIRIS YANIRETH BARRETT JIMENEZ- mes de junio | D103: 326 | E103: 15 | G103: =+G102+E103+F103 -> 4649.71 | H103: a
A104: 45854 | B104: 17585 | C104: YAPPY BG DE YANIZA INDIRA ATENCIO DE DRECKETT-julio y agosto | D104: 18 | E104: 30 | G104: =+G103+E104+F104 -> 4679.71 | H104: a
A105: 45855 | B105: 17586 | C105: BANCA MOVIL TRANSFERENCIA DE GYSELLE DEYANIRA GRANT WELCH CASA 265 JULIO 2025 | D105: 265 | E105: 15 | G105: =+G104+E105+F105 -> 4694.71 | H105: a
A106: 45855 | B106: 17587 | C106: BANCA EN LINEA TRANSFERENCIA DE DALIA ZORAIDA PETERS PAYNE Familia Peters casa 121 y 104 junio y julio | D106: 121 y 104 | E106: 60 | G106: =+G105+E106+F106 -> 4754.71 | H106: a
A107: 45855 | B107: PAGOS | C107: BANCA MOVIL GLOBAL BANK 23332000633 Enrique Silvera | D107: PAGOS | E107: 0 | F107: -175.5 | G107: =+G106+E107+F107 -> 4579.21 | H107: a
A108: 45855 | B108: PAGOS | C108: BANCA MOVIL TRANSFERENCIA A 0495996629370 SANTOS DIOMEDES ARAUZ MEDINA cancela trabajos re | D108: PAGOS | E108: 0 | F108: -257.2 | G108: =+G107+E108+F108 -> 4322.01 | H108: a
A109: 45855 | B109: DONACION | C109: ACH XPRESS - PAMELA PATRICIA PETERS BAILEY OR ALBERTO BELFORD MEL | D109: DONACION | E109: 100 | G109: =+G108+E109+F109 -> 4422.01 | H109: a
A110: 45855 | B110: 17588 | C110: YAPPY BG DE JULIO ENRIQUE MEJIA POR Flia Mejia Nino 291Manty seg agosto | D110: 291 | E110: 15 | G110: =+G109+E110+F110 -> 4437.01 | H110: a
A111: 45855 | B111: 17589 | C111: BANCA MOVIL TRANSFERENCIA DE YOLANDA MAGALI CAMPOS GONZALEZ pago seguridad julio 2025 | D111: 304 | E111: 15 | G111: =+G110+E111+F111 -> 4452.01 | H111: a
A112: 45856 | B112: 17590 | C112: YAPPY BG DE ILUMINADA BONILLA VIDAL (EL PARKIN.)- junio a noviembre | D112: 167 | E112: 100 | G112: =+G111+E112+F112 -> 4552.01 | H112: a
A113: 45856 | B113: 17591 | C113: BANCA MOVIL TRANSFERENCIA DE DAIZA BRU TORRES mes de julio y agosto | D113: 143 | E113: 30 | G113: =+G112+E113+F113 -> 4582.01 | H113: a
A114: 45856 | B114: 17592 | C114: BANCA MOVIL TRANSFERENCIA DE NATIVIDAD VALENCIA de JIMENEZ Casa 26 Flia Jimenez mes de Jul | D114: 26 | E114: 15 | G114: =+G113+E114+F114 -> 4597.01 | H114: a
A115: 45856 | B115: PAGOS | C115: PAGO YAPPY BG A ptyteccomputershop | D115: PAGOS | E115: 0 | F115: -255.71 | G115: =+G114+E115+F115 -> 4341.3 | H115: a
A116: 45856 | B116: 17593 | C116: YAPPY BG DE JOANNA VANESSA EVERSLEY DE VALDES POR casa 71 mayojunio | D116: 71 | E116: 30 | G116: =+G115+E116+F116 -> 4371.3 | H116: a
A117: 45856 | B117: PAGOS | C117: BANCA MOVIL TRANSFERENCIA A 0454000010658 JOSE ALBERTO MARCIAGA BRAVO pintar verjas | D117: PAGOS | E117: 0 | F117: -150 | G117: =+G116+E117+F117 -> 4221.3 | H117: a
A118: 45856 | B118: 17594 | C118: YAPPY BG DE SUNILA GITA PATEL SALDAÑA POR Josefina de Patel casa 29 mantenimiento junio y julio | D118: 29 | E118: 30 | G118: =+G117+E118+F118 -> 4251.3 | H118: a
A119: 45857 | B119: 17595 | C119: BANCA MOVIL TRANSFERENCIA DE LUIS ENRIQUE AMADOR MARTINEZ pago mensual mes julio | D119: 195 | E119: 15 | G119: =+G118+E119+F119 -> 4266.3 | H119: a
A120: 45857 | B120: 17596 | C120: YAPPY BG DE SHANI NG de CHIU POR Familia Chiu Casa 292 - julio | D120: 292 | E120: 15 | G120: =+G119+E120+F120 -> 4281.3 | H120: a
A121: 45857 | B121: 17597 | C121: BANCA MOVIL TRANSFERENCIA DE JOSE MANUEL TUÑON RAMOS Pago de Julio Casa 137 Familia Tunon | D121: 137 | E121: 15 | G121: =+G120+E121+F121 -> 4296.3 | H121: a
A122: 45858 | B122: 17598 | C122: YAPPY BG DE JAIRO ABDIEL BUITRAGO VASQUEZ POR Junio y julio casa 100 | D122: 100 | E122: 30 | G122: =+G121+E122+F122 -> 4326.3 | H122: a
...

Sheet pagos agosto 2025
A1: DETALLE DE PAGOS EN BANCO
A2: MES DE AGOSTO DE 2025
A4: Cuenta:Alborada 04-11-00-000468-4
A8: Fecha | B8: Recibo | C8: Descripción | D8: No.Casa | E8: Cobros | F8: Pagos | G8: Saldo total
A10: 45869 | C10: SALDO AL 31 DE JULIO DE 2025 | G10: =+'pagos julio 2025'!G172 -> 4235.22
A11: 45870 | B11: 17640 | C11: YAPPY BG DE YARITZA YAMILKA COOPER CHIFUNDO POR Mes de Julio 2025 Casa 202 SChifundo YCoo | D11: 202 | E11: 15 | G11: =+G10+E11+F11 -> 4250.22 | H11: a
A12: 45870 | B12: 17641 | C12: YAPPY BG DE QUERUBI LIZET NEREIDA de HILTON POR Pago mes de JuNIO Y JULIO | D12: 19 | E12: 30 | G12: =+G11+E12+F12 -> 4280.22 | H12: a
A13: 45870 | B13: 17642 | C13: BANCA MOVIL TRANSFERENCIA DE FERNANDO JOSE PENAS BLANCO (O) FERNANDO ANTONIO PENAS DOMING - JUNIO | D13: 169 | E13: 15 | G13: =+G12+E13+F13 -> 4295.22 | H13: a
A14: 45870 | B14: 17643 | C14: BANCA MOVIL TRANSFERENCIA DE FERNANDO CHAVERRA PINEDA Fernando Chaverra casa 317 OCTUBRE | D14: 317 | E14: 15 | G14: =+G13+E14+F14 -> 4310.22 | H14: a
A15: 45870 | B15: 17644 | C15: DEPOSITO - FLIA SMALL- MAYO Y JUNIO | D15: 39 | E15: 30 | G15: =+G14+E15+F15 -> 4340.22 | H15: a
A16: 45870 | B16: 17645 | C16: YAPPY BG DE ANA MICHELLE PILE OSSA (O) ARELIS VANESSA OSSA DIAZ POR casa 106-Arelis Ossa- MES DE JULIO | D16: 106 | E16: 15 | G16: =+G15+E16+F16 -> 4355.22 | H16: a
A17: 45870 | B17: PAGOS | C17: BANCA EN LINEA TRANSFERENCIA A 0338011480674 TIGER SECURITY COMPANY AND TRAINING CENTER, S | D17: PAGOS | E17: 0 | F17: -1819 | G17: =+G16+E17+F17 -> 2536.22 | H17: a
A18: 45874 | B18: 17646 | C18: EFECTIVO - PIEDAD DEL CID - MANT. -AGOSTO | D18: 57 | E18: 15 | G18: =+G17+E18+F18 -> 2551.22 | H18: a
A19: 45874 | B19: 17647 | C19: EFECTIVO - ALBERTO BENETT - MANT- MAYO, JUNIO Y JULIO | D19: 55 | E19: 45 | G19: =+G18+E19+F19 -> 2596.22 | H19: a
A20: 45877 | B20: 17648 | C20: EFECTIVO - OFELIA MITCHELL- MANT- JUNIO, JULIO Y AGOSTO | D20: 260 | E20: 45 | G20: =+G19+E20+F20 -> 2641.22 | H20: a
A21: 45877 | B21: 17649 | C21: EFECTIVO - PABLO MEJIA - MENS- JULIO A DICIEMBRE | D21: 50 | E21: 90 | G21: =+G20+E21+F21 -> 2731.22 | H21: a
A22: 45881 | B22: 17650 | C22: EFECTIVO - FLIA GUERRA - SALAZAR - MENS-ENERO A JULIO | D22: 255 | E22: 105 | G22: =+G21+E22+F22 -> 2836.22 | H22: a
A23: 45876 | B23: 17651 | C23: EFECTIVO - FLIA NORSE - MENS- MAYO, JUNIO Y JULIO | D23: 318 | E23: 45 | G23: =+G22+E23+F23 -> 2881.22 | H23: a
A24: 45877 | B24: 17652 | C24: YAPPY - CARLOS GARAY - MANT- AGOSTO | D24: 4 | E24: 15 | G24: =+G23+E24+F24 -> 2896.22 | H24: a
A25: 45876 | B25: 17653 | C25: YAPPY - Hector Ibarguen- MANT- JULIO | D25: 21 | E25: 15 | G25: =+G24+E25+F25 -> 2911.22 | H25: a
A26: 45870 | B26: 17654 | C26: BANCA MOVIL TRANSFERENCIA DE LILIAN JAZMIN TUÑON DE TOULIER Junio Julio 332 | D26: 332 | E26: 30 | G26: =+G25+E26+F26 -> 2941.22 | H26: a
A27: 45870 | B27: 17655 | C27: YAPPY BG DE YUMITZIE ANNELIS HARWOOD de CEDEÑO POR mes de julio Flia Cedeno casa 192 | D27: 192 | E27: 15 | G27: =+G26+E27+F27 -> 2956.22 | H27: a
A28: 45870 | B28: 17656 | C28: BANCA MOVIL TRANSFERENCIA DE MARCELA PAVIA de LAJON -julio, agosto y septiembre | D28: D-6 | E28: 45 | G28: =+G27+E28+F28 -> 3001.22 | H28: a
A29: 45870 | B29: PAGOS | C29: BANCA MOVIL TRANSFERENCIA A 0403014310197 DAGOBERTO DAVID PARIS ARIAS REGISTRO PUBLICO ALB | D29: PAGOS | E29: 0 | F29: -30 | G29: =+G28+E29+F29 -> 2971.22 | H29: a
A30: 45870 | B30: 17657 | C30: BANCA MOVIL TRANSFERENCIA DE ROSEMENE SERVILIUS MEDIEU- MES DE FEBRERO,MARZO Y ABRIL | D30: 182 | E30: 45 | G30: =+G29+E30+F30 -> 3016.22 | H30: a
A31: 45870 | B31: 17658 | C31: YAPPY BG DE WYLMA ISUALY MATURANA DE ESCOBAR- junio | D31: 85 | E31: 15 | G31: =+G30+E31+F31 -> 3031.22 | H31: a
A32: 45870 | B32: 17659 | C32: YAPPY BG DE LUCAS ANTONIO CORTES SURGEON POR Pago julio agosto casa 134 | D32: 134 | E32: 30 | G32: =+G31+E32+F32 -> 3061.22 | H32: a
A33: 45870 | B33: 17660 | C33: YAPPY BG DE ANSELMO EMILIANO FORDE CHRISTOPHER mes de agosto | D33: 5 | E33: 15 | G33: =+G32+E33+F33 -> 3076.22 | H33: a
A34: 45870 | B34: 17661 | C34: BANCA MOVIL TRANSFERENCIA DE ADA ARGELIA CHONG CORREA junio y julio | D34: 133 | E34: 30 | G34: =+G33+E34+F34 -> 3106.22 | H34: a
A35: 45870 | B35: 17662 | C35: YAPPY BG DE PORFIRIO JUSTAVINO CEDEÑO POR mes de agosto 289 | D35: 289 | E35: 15 | G35: =+G34+E35+F35 -> 3121.22 | H35: a
A36: 45870 | B36: 17663 | C36: BANCA MOVIL TRANSFERENCIA DE DALIS YADIRA BANDINI AGUSTINE Pago seguridad Flia Bandini - SEPTIEMBRE Y OCTUBRE | D36: 178 | E36: 30 | G36: =+G35+E36+F36 -> 3151.22 | H36: a
A37: 45870 | B37: 17664 | C37: YAPPY BG DE YULIXA DEL CARMEN ESPADA de SIERRA POR Casa 110 - JUNIO | D37: 110 | E37: 15 | G37: =+G36+E37+F37 -> 3166.22 | H37: a
A38: 45870 | B38: 17665 | C38: BANCA MOVIL TRANSFERENCIA DE LUIS ENRIQUE AMADOR MARTINEZ pago del mes de agosto | D38: 195 | E38: 15 | G38: =+G37+E38+F38 -> 3181.22 | H38: a
A39: 45871 | B39: 17666 | C39: BANCA EN LINEA TRANSFERENCIA DE DALIA ZORAIDA PETERS PAYNE Familia Peters casa 121 y 104 - mes de agosto | D39: 121 Y 104 | E39: 30 | G39: =+G38+E39+F39 -> 3211.22 | H39: a
A40: 45871 | B40: 17667 | C40: YAPPY BG DE NIDIA ROSA BOHORQUEZ de MARTINEZ POR pago 2 meses julio y agosto familia mart | D40: 63 | E40: 30 | G40: =+G39+E40+F40 -> 3241.22 | H40: a
A41: 45871 | B41: 17668 | C41: YAPPY BG DE JACQUELINE YOVANIA VILLAMIL TORRES- MES DE JULIO | D41: 298 | E41: 15 | G41: =+G40+E41+F41 -> 3256.22 | H41: a
A42: 45871 | B42: 17669 | C42: YAPPY BG DE JAIME DAVID ANDERSON SINCLAIR - mes de julio | D42: 172 | E42: 15 | G42: =+G41+E42+F42 -> 3271.22 | H42: a
A43: 45871 | B43: 17670 | C43: YAPPY BG DE JOSE DAVID BONILLA ALVARADO POR Garita Julio 2025 D14 Familia Bonilla | D43: D14 | E43: 15 | G43: =+G42+E43+F43 -> 3286.22 | H43: a
A44: 45871 | B44: PAGOS | C44: BANCA MOVIL TRANSFERENCIA A 0472996299559 PEDRO ANTONIO GLASGOW BARRETT corte de hierba de | D44: PAGOS | E44: 0 | F44: -150 | G44: =+G43+E44+F44 -> 3136.22 | H44: a
A45: 45871 | B45: PAGOS | C45: YAPPY BG A RODERICK ANEL CHIRU VALDES POR CORTE PARQUES SEXTA Y VEREDA CIRCUNVALACION | D45: PAGOS | E45: 0 | F45: -210 | G45: =+G44+E45+F45 -> 2926.22 | H45: a
A46: 45871 | B46: 17671 | C46: YAPPY BG DE SHERISKA YARILKA ESCOBAR SALADINO de HOOKER POR casa 12 familia Escobar -MES DE JULIO | D46: 12 | E46: 15 | G46: =+G45+E46+F46 -> 2941.22 | H46: a
A47: 45871 | B47: 17672 | C47: YAPPY BG DE YOLANDA ENEIDA LOPER ALABARCA POR mantenimiento agosto 2025 casa 271 | D47: 271 | E47: 20 | G47: =+G46+E47+F47 -> 2961.22 | H47: a
A48: 45871 | B48: 17673 | C48: YAPPY BG DE BETZAIDA ITZEL CABEZA DE FORBES POR pago seguridad casa 204 familia Forbes juLIO Y AGOSTO | D48: 204 | E48: 30 | G48: =+G47+E48+F48 -> 2991.22 | H48: a
A49: 45872 | B49: PAGOS | C49: YAPPY BG A MELVIN CARLTON FOSTER GALASTICA POR Corte hierba 3a y 4ta parques | D49: PAGOS | E49: 0 | F49: -60 | G49: =+G48+E49+F49 -> 2931.22 | H49: a
A50: 45873 | B50: 17674 | C50: BANCA MOVIL TRANSFERENCIA DE NIDIA SILGADO LEON Casa 164 - AGOSTO | D50: 164 | E50: 15 | G50: =+G49+E50+F50 -> 2946.22 | H50: a
A51: 45873 | B51: 17675 | C51: DEPOSITO CASA 145 FLIA VIVERO- MES DE JULIO | D51: 145 | E51: 15 | G51: =+G50+E51+F51 -> 2961.22 | H51: a
A52: 45873 | B52: 17676 | C52: DEPOSITO - FLIA PARRIS- JULIO | D52: 278 | E52: 15 | G52: =+G51+E52+F52 -> 2976.22 | H52: a
A53: 45873 | B53: 17677 | C53: YAPPY BG DE YELENA DELIBETH ALVEAR ARCIA POR junio y julio casa 174 familia Fitzroy | D53: 174 | E53: 30 | G53: =+G52+E53+F53 -> 3006.22 | H53: a
A54: 45873 | B54: 17678 | C54: YAPPY BG DE EMELINA IVETT CATUY ALARCON- MES DE JUNIO | D54: 68 | E54: 15 | G54: =+G53+E54+F54 -> 3021.22 | H54: a
A55: 45873 | B55: 17679 | C55: BANCA MOVIL TRANSFERENCIA DE JOSSUA EMMIR WILLIAMS RIOS Mantenimiento y Seguridad - junio | D55: 327 | E55: 15 | G55: =+G54+E55+F55 -> 3036.22 | H55: a
A56: 45873 | B56: 17680 | C56: YAPPY BG DE MIRNA CLOTILDE REED de LEE - MARZO | D56: 62 | E56: 15 | G56: =+G55+E56+F56 -> 3051.22 | H56: a
A57: 45874 | B57: 17681 | C57: YAPPY BG DE LUZMILA ELENA PORTER DE QUINTERO POR Familia QUINTERO C47 JULIO25 | D57: 47 | E57: 15 | G57: =+G56+E57+F57 -> 3066.22 | H57: a
A58: 45874 | B58: 17682 | C58: YAPPY BG DE MARIA DE LOS ANGELES MONTENEGRO DE LEON - JULIO | D58: 14 | E58: 15 | G58: =+G57+E58+F58 -> 3081.22 | H58: a
A59: 45874 | B59: 17683 | C59: ACH XPRESS - DEMETRIO CELSO PRESCOTT RODRIGUEZ -MES JULIO | D59: 241 | E59: 15 | G59: =+G58+E59+F59 -> 3096.22 | H59: a
A60: 45874 | B60: 17684 | C60: YAPPY BG DE JUAN RICARDO FLORES CARDALES POR julio agosto septiembre | D60: 280 | E60: 45 | G60: =+G59+E60+F60 -> 3141.22 | H60: a
A61: 45874 | B61: PAGOS | C61: YAPPY BG A ELVIS JESUS GARIBELLO MENDOZA POR DIFERENCIA NVR | D61: PAGOS | E61: 0 | F61: -17.11 | G61: =+G60+E61+F61 -> 3124.11 | H61: a
A62: 45874 | B62: PAGOS | C62: YAPPY BG A HERNAN DARIO ROJAS LOPEZ POR corte hierba tramo 6ta oeste | D62: PAGOS | E62: 0 | F62: -15 | G62: =+G61+E62+F62 -> 3109.11 | H62: a
A63: 45874 | B63: 17685 | C63: YAPPY BG DE DILAN ANDRES SANCHEZ BELTRAN POR Casa 28 Mantmarzoabrilmayo y junio 2025 | D63: 28 | E63: 60 | G63: =+G62+E63+F63 -> 3169.11 | H63: a
A64: 45875 | B64: 17686 | C64: BANCA MOVIL TRANSFERENCIA DE ALDO ANTONIO BOVELL FINDLEY Junio julio y agosto casa 229 | D64: 229 | E64: 45 | G64: =+G63+E64+F64 -> 3214.11 | H64: a
A65: 45875 | B65: 17687 | C65: YAPPY BG DE KAISHA TAMARA RIVAS JULIO- MES DE ABRIL | D65: 79 | E65: 15 | G65: =+G64+E65+F65 -> 3229.11 | H65: a
A66: 45875 | B66: 17688 | C66: YAPPY BG DE AMILKAR MORENO RIOS POR Mantenimiento Casa 36 Julio | D66: 36 | E66: 15 | G66: =+G65+E66+F66 -> 3244.11 | H66: a
A67: 45875 | B67: 17689 | C67: YAPPY BG DE YOHANA LISBETH MOLINAR DE GONDOLA - JUNIO | D67: 113 | E67: 15 | G67: =+G66+E67+F67 -> 3259.11 | H67: a
A68: 45875 | B68: 17690 | C68: YAPPY BG DE YANETH YAMILKA BADILLA PINEDA POR cuota casa 157 - AGOSTO | D68: 157 | E68: 15 | G68: =+G67+E68+F68 -> 3274.11 | H68: a
A69: 45875 | B69: 17691 | C69: BANCA MOVIL TRANSFERENCIA DE JOSE MANUEL TUÑON RAMOS Pago de Agosto Casa 137 Familia Tunon | D69: 137 | E69: 15 | G69: =+G68+E69+F69 -> 3289.11 | H69: a
A70: 45876 | B70: 17692 | C70: YAPPY BG DE MAUREL MARIAM MIER de ESCOBAR- mes de julio | D70: 221 | E70: 15 | G70: =+G69+E70+F70 -> 3304.11 | H70: a
A71: 45876 | B71: PAGOS | C71: BANCA EN LINEA TRANSFERENCIA A 0411991858937 MANUEL ANTONIO CAMPOS RODRIGUEZ confeccion de letreros | D71: PAGOS | E71: 0 | F71: -120 | G71: =+G70+E71+F71 -> 3184.11 | H71: a
A72: 45876 | B72: PAGOS | C72: BANCA EN LINEA TRANSFERENCIA A IMPRENTA COLON - CONFECCION DE RECIBOS | D72: PAGOS | E72: 0 | F72: -100 | G72: =+G71+E72+F72 -> 3084.11 | H72: a
A73: 45876 | B73: 17693 | C73: BANCA MOVIL TRANSFERENCIA DE YAZMIN DAMARIS SOTO PIMENTEL Pago casa 162 Yazmin Soto- mes de mayo, junio y julio | D73: 162 | E73: 45 | G73: =+G72+E73+F73 -> 3129.11 | H73: a
A74: 45876 | B74: PAGOS | C74: BANCA EN LINEA TRANSFERENCIA A 0304011165587 CORPORACION SOLUCIONES GLOBALES 2020, S.A. (@ | D74: PAGOS | E74: 0 | F74: -113.79 | G74: =+G73+E74+F74 -> 3015.32 | H74: a
A75: 45876 | B75: 17694 | C75: BANCA MOVIL TRANSFERENCIA DE ALIZA EMERITA JIMENEZ - mes de agosto | D75: 30 | E75: 15 | G75: =+G74+E75+F75 -> 3030.32 | H75: a
A76: 45876 | B76: 17695 | C76: BANCA MOVIL TRANSFERENCIA DE LISSETH HERMINIA DE LA ESPADA de DE NICOLO casa 194 - mes de junio y julio | D76: 194 | E76: 30 | G76: =+G75+E76+F76 -> 3060.32 | H76: a
A77: 45876 | B77: 17696 | C77: YAPPY BG DE ALAIN AMINT ARAUZ POWELL POR Casa1 Julio | D77: 1 | E77: 15 | G77: =+G76+E77+F77 -> 3075.32 | H77: a
A78: 45877 | B78: 17697 | C78: BANCA MOVIL TRANSFERENCIA DE JOSSUA EMMIR WILLIAMS RIOS Mantenimiento y Seguridad -mes de julio | D78: 327 | E78: 15 | G78: =+G77+E78+F78 -> 3090.32 | H78: a
A79: 45877 | B79: 17698 | C79: ACH- EXPRESS -FLIA HAMILTON - MES - AGOSTO Y SEPTIEMBRE | D79: 111 | E79: 30 | G79: =+G78+E79+F79 -> 3120.32 | H79: a
A80: 45877 | B80: PAGOS | C80: BANCA EN LINEA TRANSFERENCIA A 0411981361721 ELVIS JESUS GARIBELLO MENDOZA BANCA EN LINEA | D80: PAGOS | E80: 0 | F80: -125 | G80: =+G79+E80+F80 -> 2995.32 | H80: a
A81: 45877 | B81: PAGOS | C81: BANCA EN LINEA TRANSFERENCIA A 0454000010658 JOSE ALBERTO MARCIAGA BRAVO BANCA EN LINEA TR | D81: PAGOS | E81: 0 | F81: -200 | G81: =+G80+E81+F81 -> 2795.32 | H81: a
A82: 45880 | B82: 17699 | C82: BANCA MOVIL TRANSFERENCIA DE MARIA DEL CARMEN LOPEZ CANDELARIA junio a septiembre casa 8 | D82: 8 | E82: 60 | G82: =+G81+E82+F82 -> 2855.32 | H82: a
A83: 45880 | B83: 17700 | C83: YAPPY BG DE IDA CEMA JACKSON de VALENCIA- MES DE JULIO | D83: 270 | E83: 15 | G83: =+G82+E83+F83 -> 2870.32 | H83: a
A84: 45880 | B84: 17701 | C84: YAPPY BG DE CIARA LUZ JIMENEZ CONCEPCION - mes de agosto y septiembre | D84: 16 | E84: 30 | G84: =+G83+E84+F84 -> 2900.32 | H84: a
A85: 45881 | B85: 17702 | C85: BANCA MOVIL TRANSFERENCIA DE RAQUEL MAGALI RACERO de LAWRENCE mes de junio y julio casa 120 | D85: 120 | E85: 30 | G85: =+G84+E85+F85 -> 2930.32 | H85: a
A86: 45881 | B86: 17703 | C86: BANCA MOVIL TRANSFERENCIA DE DIEGO QUINTERO PITALUA Pago mes de enero a junio | D86: D-7 | E86: 90 | G86: =+G85+E86+F86 -> 3020.32 | H86: a
A87: 45881 | B87: 17704 | C87: BANCA MOVIL TRANSFERENCIA DE JOSE ALEJANDRO BARROWS ROBINSON casa 154 -mes de julio | D87: 154 | E87: 15 | G87: =+G86+E87+F87 -> 3035.32 | H87: a
A88: 45881 | B88: PAGOS | C88: BANCA EN LINEA TRANSFERENCIA A 0454000010658 JOSE ALBERTO MARCIAGA BRAVO BANCA EN LINEA TR | D88: PAGOS | E88: 0 | F88: -12.3 | G88: =+G87+E88+F88 -> 3023.02 | H88: a
A89: 45882 | B89: 17705 | C89: YAPPY BG DE GIRLY ALEXIA ROBINSON MATOS POR Mensualidad casa 257 Flia Icaza - mes de agosto | D89: 257 | E89: 15 | G89: =+G88+E89+F89 -> 3038.02 | H89: a
A90: 45882 | B90: RIFA | C90: YAPPY BG DE ILKA MELISA MARK HOY - RIFA -31/08/25 | D90: RIFA | E90: 10 | G90: =+G89+E90+F90 -> 3048.02 | H90: a
A91: 45883 | B91: 17706 | C91: YAPPY BG DE TAHIMY GUADALUPE IGLESIAS HURTADO- mes de agosto | D91: 9 | E91: 15 | G91: =+G90+E91+F91 -> 3063.02 | H91: a
A92: 45883 | B92: 17707 | C92: BANCA EN LINEA TRANSFERENCIA DE YAMILETH ALEIDA SANCHEZ DE ESPINOSA Mant y Seg ALBORADA Mes de mayo y junio | D92: 122 | E92: 30 | G92: =+G91+E92+F92 -> 3093.02 | H92: a
A93: 45883 | B93: 17708 | C93: YAPPY BG DE ADDIS MASSIEL BETEGON ROSALES POR Casa 33 julio y agosto Flia Betegon Rosales | D93: 33 | E93: 30 | G93: =+G92+E93+F93 -> 3123.02 | H93: a
A94: 45883 | B94: 17709 | C94: ACH - YARABY ORQUIDIA JIMENEZ JONES DE ABRAHAM - agosto | D94: 303 | E94: 15 | G94: =+G93+E94+F94 -> 3138.02 | H94: a
A95: 45883 | B95: 17710 | C95: YAPPY BG DE NIDIA EDITH RODRIGUEZ ORTIZ POR casa 267 fila Rodriguez- mes de mayo | D95: 267 | E95: 30 | G95: =+G94+E95+F95 -> 3168.02 | H95: a
A96: 45883 | B96: 17711 | C96: BANCA MOVIL TRANSFERENCIA DE ERIC ARIEL VILLANUEVA - mes de agosto | D96: 236 | E96: 15 | G96: =+G95+E96+F96 -> 3183.02 | H96: a
A97: 45883 | B97: PAGOS | C97: Dayra canales - Pintura para dentro de la Garita | D97: PAGOS | E97: 0 | F97: -60 | G97: =+G96+E97+F97 -> 3123.02 | H97: a
A98: 45883 | B98: 17712 | C98: DEPOSITO - FLIA SMALL - JULIO Y AGOSTO | D98: 39 | E98: 30 | G98: =+G97+E98+F98 -> 3153.02 | H98: a
A99: 45883 | B99: 17713 | C99: YAPPY BG DE MARTHA BIBIANA ACOSTA MARULANDA POR casa 105 agosto | D99: 105 | E99: 15 | G99: =+G98+E99+F99 -> 3168.02 | H99: a
A100: 45883 | B100: 17714 | C100: BANCA MOVIL TRANSFERENCIA DE MARLENE BOYCE DAWKINS Casa 181 Mayo y Junio | D100: 181 | E100: 30 | G100: =+G99+E100+F100 -> 3198.02 | H100: a
A101: 45883 | B101: 17715 | C101: BANCA MOVIL TRANSFERENCIA DE YOLANDA FORBES FERNANDEZ- AGOSTO | D101: 155 | E101: 15 | G101: =+G100+E101+F101 -> 3213.02 | H101: a
A102: 45883 | B102: 17716 | C102: BANCA MOVIL TRANSFERENCIA DE DAYRA ISABEL FLORES DE MORENO Casa D1 agosto y sept | D102: D-01 | E102: 30 | G102: =+G101+E102+F102 -> 3243.02 | H102: a
A103: 45883 | B103: 17717 | C103: YAPPY BG DE SHARYN TAVANE DELGADO ROWE POR Agosto casa 199 Sharyn Delgado | D103: 199 | E103: 15 | G103: =+G102+E103+F103 -> 3258.02 | H103: a
A104: 45883 | B104: 17718 | C104: YAPPY BG DE YESICA MARLENE CHIFUNDO DE PRESTAN POR mantenimiento de agosto Flia Prestan c | D104: 210 | E104: 15 | G104: =+G103+E104+F104 -> 3273.02 | H104: a
A105: 45883 | B105: 17719 | C105: YAPPY BG DE LIGIA ELENA ADLES JIMENEZ- MES DE JULIO, AGOSTO Y SEPTIEMBRE | D105: 91 | E105: 45 | G105: =+G104+E105+F105 -> 3318.02 | H105: a
...

Sheet pagos septiembre 2025
A1: DETALLE DE PAGOS EN BANCO
A2: MES DE SEPTIEMBRE DE 2025
A4: Cuenta:Alborada 04-11-00-000468-4
A8: Fecha | B8: Recibo | C8: Descripción | D8: No.Casa | E8: Cobros | F8: Pagos | G8: Saldo total
A10: 45900 | C10: SALDO AL 31 DE AGOSTO DE 2025 | G10: =+'pagos agosto 2025'!G223 -> 3835.26 | H10: a
A11: 45903 | B11: 17773 | C11: ACH XPRESS - DENNIS BARNES GRAHAM- SEPTIEMBRE Y OCTUBRE | D11: 148 | E11: 30 | G11: =+G10+E11+F11 -> 3865.26 | H11: a
A12: 45907 | B12: 17774 | C12: EFECTIVO - CARLOS LEOTEAU - MES DE SEPIEMBRE A DICIEMBRE | D12: 281 | E12: 60 | G12: =+G11+E12+F12 -> 3925.26 | H12: a
A13: 45901 | B13: 17794 | C13: DEPOSITO FLIA TACHAR - JULIO, AGOSTO Y SEPTIEMBRE | D13: 15 | E13: 45 | G13: =+G12+E13+F13 -> 3970.26 | H13: a
A14: 45901 | B14: RIFA | C14: BANCA EN LINEA TRANSFERENCIA DE 0427120001653 DAYRA LUCILA CANALES de SWANSTON rifa darish | D14: RIFA | E14: 10 | G14: =+G13+E14+F14 -> 3980.26 | H14: a
A15: 45901 | B15: RIFA | C15: BANCA EN LINEA TRANSFERENCIA DE 0427120001653 DAYRA LUCILA CANALES de SWANSTON rifa | D15: RIFA | E15: 40 | G15: =+G14+E15+F15 -> 4020.26 | H15: a
A16: 45901 | B16: RIFA | C16: ACH XPRESS - JOSE LUIS GONZALEZ FLETCHER O MAIQUEL ITZELA POLLACK | D16: RIFA | E16: 10 | G16: =+G15+E16+F16 -> 4030.26 | H16: a
A17: 45901 | B17: RIFA | C17: BANCA MOVIL TRANSFERENCIA DE YENITZA NAYROBIS ASHAW SMALL | D17: RIFA | E17: 10 | G17: =+G16+E17+F17 -> 4040.26 | H17: a
A18: 45901 | B18: 17795 | C18: YAPPY BG DE YARITZA YAMILKA COOPER CHIFUNDO POR Mes de agosto 2025 Casa 202 Silvina Chifu | D18: 202 | E18: 15 | G18: =+G17+E18+F18 -> 4055.26 | H18: a
A19: 45901 | B19: 17796 | C19: YAPPY BG DE MARIA DE LOS ANGELES MONTENEGRO DE LEON POR pago a casa 14 familia montenegro - AGOSTO Y SEPTIEMBRE | D19: 14 | E19: 30 | G19: =+G18+E19+F19 -> 4085.26 | H19: a
A20: 45901 | B20: 17797 | C20: BANCA MOVIL TRANSFERENCIA DE GISELA GONZALEZ QUIROZ Casa 88 GISELA GONZALEZ Seg AGOSTO A DICIEMBRE | D20: 88 | E20: 75 | G20: =+G19+E20+F20 -> 4160.26 | H20: a
A21: 45901 | B21: 17798 | C21: BANCA MOVIL TRANSFERENCIA DE MIGUEL ROGELIO SANCHEZ - MES DE AGOSTO Y SEPTIEMBRE | D21: 6 | E21: 30 | G21: =+G20+E21+F21 -> 4190.26 | H21: a
A22: 45901 | B22: PAGOS | C22: BANCA MOVIL TRANSFERENCIA A 0338011480674 TIGER SECURITY COMPANY AND TRAINING CENTER, S.A. | D22: PAGOS | E22: 0 | F22: -1819 | G22: =+G21+E22+F22 -> 2371.26 | H22: a
A23: 45901 | B23: 17799 | C23: YAPPY BG DE YULIXA DEL CARMEN ESPADA de SIERRA POR Casa 110 Flia Sierra MES DE JULIO | D23: 110 | E23: 15 | G23: =+G22+E23+F23 -> 2386.26 | H23: a
A24: 45901 | B24: RIFA | C24: YAPPY BG DE EMMANUEL ESTEBAN CABRERA MARTINEZ | D24: RIFA | E24: 10 | G24: =+G23+E24+F24 -> 2396.26 | H24: a
A25: 45903 | B25: 17800 | C25: EFECTIVO - LUIS LEVIS - MES DE MARZO Y ABRIL | D25: 234 | E25: 30 | G25: =+G24+E25+F25 -> 2426.26 | H25: a
A26: 45902 | B26: 17801 | C26: EFECTIVO - FLIA MENDOZA - SEPTIEMBRE Y OCTUBRE CASA 244 | D26: 244 | E26: 30 | G26: =+G25+E26+F26 -> 2456.26 | H26: a
A27: 45904 | B27: 17802 | C27: EFECTIVO - JAZMIN MENDOZA - MARZO $5 Y ABRIL $5 | D27: 170 | E27: 10 | G27: =+G26+E27+F27 -> 2466.26 | H27: a
A28: 45906 | B28: 17803 | C28: EFECTIVO - FLIA CUERO - AGOSTO Y SEPTIEMBRE - CASA 253 | D28: 253 | E28: 30 | G28: =+G27+E28+F28 -> 2496.26 | H28: a
A29: 45907 | B29: 17804 | C29: EFECTIVO - DELANO SAUNDERS - MAT. SEPTIEMBRE Y OCTUBRE | D29: 285 | E29: 30 | G29: =+G28+E29+F29 -> 2526.26 | H29: a
A30: 45907 | B30: 17805 | C30: EFECTIVO - PIEDAD DEL CID - MANT-SEPTIEMBRE -CASA 57 | D30: 57 | E30: 15 | G30: =+G29+E30+F30 -> 2541.26 | H30: a
A31: 45907 | B31: 17806 | C31: ACH XPRESS - PAMELA PATRICIA PETERS BAILEY OR ALBERTO BELFORD MEL | D31: 177 | E31: 45 | G31: =+G30+E31+F31 -> 2586.26 | H31: a
A32: 45905 | B32: 17807 | C32: ACH - GEORGIANA GAVIRIA PACHECO - mes de agosto y septiembre | D32: 86 | E32: 30 | G32: =+G31+E32+F32 -> 2616.26 | H32: a
A33: 45907 | B33: TARJETA | C33: ACH- EXPRESS - ALBERTO BELFORD - CASA 177- TARJETA | D33: TARJETA | E33: 10 | G33: =+G32+E33+F33 -> 2626.26 | H33: a
A34: 45907 | B34: 17808 | C34: EFECTIVO - FLIA DEL VALLE - MAYO A SEPTIEMBRE - CASA 90 | D34: 90 | E34: 75 | G34: =+G33+E34+F34 -> 2701.26 | H34: a
A35: 45907 | B35: 17809 | C35: EFECTIVO - KAREN GONZALEZ - MANT. ABRIL A SEPTIEMBRE | D35: 97 | E35: 90 | G35: =+G34+E35+F35 -> 2791.26 | H35: a
A36: 45907 | B36: 17810 | C36: EFECTIVO - IRACEMA DE SMALL- MES DE JULIO | D36: 119 | E36: 15 | G36: =+G35+E36+F36 -> 2806.26 | H36: a
A37: 45902 | B37: 17811 | C37: ACH XPRESS - DEMETRIO CELSO PRESCOTT RODRIGUEZ - AGOSTO Y SEPTIEMBRE | D37: 241 | E37: 30 | G37: =+G36+E37+F37 -> 2836.26 | H37: a
A38: 45907 | B38: 17812 | C38: EFECTIVO - FLIA HALL - MES DE ENERO A AGOSTO | D38: 197 | E38: 120 | G38: =+G37+E38+F38 -> 2956.26 | H38: a
A39: 45901 | B39: RIFA | C39: YAPPY BG DE NATALIA KATIUSKA WARDROPE SANCHEZ | D39: RIFA | E39: 40 | G39: =+G38+E39+F39 -> 2996.26 | H39: a
A40: 45901 | B40: TARJETA | C40: YAPPY BG DE YUMITZIE ANNELIS HARWOOD de CEDEÑO POR tarjeta casa 192 Flia Cedeno | D40: TARJETA | E40: 10 | G40: =+G39+E40+F40 -> 3006.26 | H40: a
A41: 45901 | B41: 17815 | C41: BANCA MOVIL TRANSFERENCIA DE JESSENIA MAGALI FRUTO DE BETHANCOURT casa 112 Bethancourt - JULIO, AGOSTO Y SEPTIEMBRE | D41: 112 | E41: 45 | G41: =+G40+E41+F41 -> 3051.26 | H41: a
A42: 45902 | B42: 17816 | C42: BANCA EN LINEA TRANSFERENCIA DE 0427120001653 DAYRA LUCILA CANALES de SWANSTON mes de septIEMBRE Y OCTUBRE | D42: 240 | E42: 30 | G42: =+G41+E42+F42 -> 3081.26 | H42: a
A43: 45902 | B43: RIFA | C43: BANCA EN LINEA TRANSFERENCIA DE 0427120001653 DAYRA LUCILA CANALES de SWANSTON rifa efecti | D43: RIFA | E43: 100 | G43: =+G42+E43+F43 -> 3181.26 | H43: a
A44: 45902 | B44: 17817 | C44: BANCA MOVIL TRANSFERENCIA DE FERNANDO JOSE PENAS BLANCO (O) FERNANDO ANTONIO PENAS DOMING- MES DE JULIO | D44: 169 | E44: 15 | G44: =+G43+E44+F44 -> 3196.26 | H44: a
A45: 45902 | B45: 17818 | C45: YAPPY BG DE NURIA ELENA JIMENEZ de ABREGO POR casa 193 - MAYO | D45: 193 | E45: 15 | G45: =+G44+E45+F45 -> 3211.26 | H45: a
A46: 45903 | B46: 17819 | C46: YAPPY BG DE ORLANDO ENRIQUE ARGUELLES CUESTA POR SEPTIEMBRE Y OCTUBRE casa 313 | D46: 313 | E46: 30 | G46: =+G45+E46+F46 -> 3241.26 | H46: a
A47: 45903 | B47: 17820 | C47: YAPPY BG DE BOLIVAR RODRIGUEZ TORIBIO POR Alborada calle 6ta casa 295 flia Rodriguez Lee- ABRIL- MAYO Y JUNIO | D47: 295 | E47: 45 | G47: =+G46+E47+F47 -> 3286.26 | H47: a
A48: 45903 | B48: 17821 | C48: YAPPY BG DE YOLANDA ENEIDA LOPER ALABARCA POR mantenimiento casa 271 SEP 2025 | D48: 271 | E48: 20 | G48: =+G47+E48+F48 -> 3306.26 | H48: a
A49: 45903 | B49: 17822 | C49: YAPPY BG DE YUMEIRYS YULIETTE IGLESIAS BRITO POR mes de septiembre casa 9 Aura Hurtado | D49: 9 | E49: 15 | G49: =+G48+E49+F49 -> 3321.26 | H49: a
A50: 45903 | B50: 17823 | C50: BANCA MOVIL TRANSFERENCIA DE LUIS ENRIQUE AMADOR MARTINEZ pago mensual septiembre | D50: 195 | E50: 15 | G50: =+G49+E50+F50 -> 3336.26 | H50: a
A51: 45903 | B51: 17824 | C51: YAPPY BG DE ISAAC ANTONIO FRANCIS BARRERA POR Mensualidad Julio-Agosto-Septiembre casa 28 | D51: 288 | E51: 45 | G51: =+G50+E51+F51 -> 3381.26 | H51: a
A52: 45903 | B52: 17825 | C52: YAPPY BG DE PORFIRIO JUSTAVINO CEDEÑO POR casa 289 mes septiembre | D52: 289 | E52: 15 | G52: =+G51+E52+F52 -> 3396.26 | H52: a
A53: 45904 | B53: 17826 | C53: DEPOSITO- YAMILKA PARRIS - MES DE AGOSTO | D53: 278 | E53: 15 | G53: =+G52+E53+F53 -> 3411.26 | H53: a
A54: 45904 | B54: 17827 | C54: BANCA MOVIL TRANSFERENCIA DE NIDIA SILGADO LEON- SEPTIEMBRE | D54: 164 | E54: 15 | G54: =+G53+E54+F54 -> 3426.26 | H54: a
A55: 45904 | B55: 17828 | C55: YAPPY BG DE MAUREL MARIAM MIER de ESCOBAR POR Casa 221 familia Escobar - MES DE agosto | D55: 221 | E55: 15 | G55: =+G54+E55+F55 -> 3441.26 | H55: a
A56: 45904 | B56: PAGOS | C56: YAPPY BG A MELVIN CARLTON FOSTER GALASTICA POR Corte hierba parques 3a y 4a | D56: PAGOS | E56: 0 | F56: -60 | G56: =+G55+E56+F56 -> 3381.26 | H56: a
A57: 45905 | B57: 17829 | C57: BANCA MOVIL TRANSFERENCIA DE CARLOS ANTONIO MORAN MC COY Mantenimiento y seguridad casa 251 - septiembre | D57: 251 | E57: 15 | G57: =+G56+E57+F57 -> 3396.26 | H57: a
A58: 45905 | B58: 17830 | C58: YAPPY BG DE YANETH YAMILKA BADILLA PINEDA POR casa 157 septiembre | D58: 157 | E58: 15 | G58: =+G57+E58+F58 -> 3411.26 | H58: a
A59: 45906 | B59: 17831 | C59: YAPPY BG DE LUZMILA ELENA PORTER DE QUINTERO - AGOSTO | D59: 47 | E59: 15 | G59: =+G58+E59+F59 -> 3426.26 | H59: a
A60: 45906 | B60: PAGOS | C60: BANCA MOVIL TRANSFERENCIA A 0454000010658 JOSE ALBERTO MARCIAGA BRAVO cancela trabajos gar | D60: PAGOS | E60: 0 | F60: -50 | G60: =+G59+E60+F60 -> 3376.26 | H60: a
A61: 45906 | B61: PAGOS | C61: YAPPY BG A RODERICK ANEL CHIRU VALDES POR CORTE HIERBA PARQUES PEQUENOS SEXTA | D61: PAGOS | E61: 0 | F61: -60 | G61: =+G60+E61+F61 -> 3316.26 | H61: a
A62: 45907 | B62: 17832 | C62: YAPPY BG DE YELENA DELIBETH ALVEAR ARCIA POR casa 174 agosto | D62: 174 | E62: 15 | G62: =+G61+E62+F62 -> 3331.26 | H62: a
A63: 45907 | B63: 17833 | C63: YAPPY BG DE LUCAS ANTONIO CORTES SURGEON POR Casa 134 septiembre | D63: 134 | E63: 15 | G63: =+G62+E63+F63 -> 3346.26 | H63: a
A64: 45907 | B64: TARJETA | C64: YAPPY BG DE YULIXA DEL CARMEN ESPADA de SIERRA POR Compra de tarjetas casa 110 | D64: TARJETA | E64: 20 | G64: =+G63+E64+F64 -> 3366.26 | H64: a
A65: 45907 | B65: PAGOS | C65: YAPPY BG A HERNAN DARIO ROJAS LOPEZ POR CORTE VEREDA CIRCUN ESTE | D65: PAGOS | E65: 0 | F65: -70 | G65: =+G64+E65+F65 -> 3296.26 | H65: a
A66: 45907 | B66: 17834 | C66: YAPPY BG DE SHERISKA YARILKA ESCOBAR SALADINO de HOOKER POR pago mes agosto casa 12 pago | D66: 12 | E66: 15 | G66: =+G65+E66+F66 -> 3311.26 | H66: a
A67: 45907 | B67: TARJETA | C67: YAPPY BG DE SHERISKA YARILKA ESCOBAR SALADINO de HOOKER POR pago mes agosto casa 12 pago | D67: TARJETA | E67: 10 | G67: =+G66+E67+F67 -> 3321.26 | H67: a
A68: 45907 | B68: 17835 | C68: BANCA MOVIL TRANSFERENCIA DE CARLOS ERNESTO LAMBERT -JULIO A SEPTIEMBRE | D68: 223 | E68: 45 | G68: =+G67+E68+F68 -> 3366.26 | H68: a
A69: 45907 | B69: 17836 | C69: BANCA MOVIL TRANSFERENCIA DE ROSEMENE SERVILIUS MEDIEU (CARIBBEAN FOOD GOURMET) julio y agosto | D69: 182 | E69: 30 | G69: =+G68+E69+F69 -> 3396.26 | H69: a
A70: 45907 | B70: TARJETA | C70: YAPPY BG DE LUCAS ANTONIO CORTES SURGEON POR Tarjeta nueva casa 134 | D70: TARJETA | E70: 10 | G70: =+G69+E70+F70 -> 3406.26 | H70: a
A71: 45907 | B71: TARJETA | C71: ACH XPRESS - YOHANA MOLINAR | D71: TARJETA | E71: 10 | G71: =+G70+E71+F71 -> 3416.26 | H71: a
A72: 45907 | B72: 17837 | C72: BANCA MOVIL TRANSFERENCIA DE GLADYS JASMINA MC KENZIE DE ANDERSON casa 231 familia Anders- mes de abril | D72: 231 | E72: 15.55 | G72: =+G71+E72+F72 -> 3431.81 | H72: a
A73: 45907 | B73: TARJETA | C73: YAPPY BG DE ARIEL CORPAS BETEGON CASA 319 | D73: TARJETA | E73: 10 | G73: =+G72+E73+F73 -> 3441.81 | H73: a
A74: 45907 | B74: TARJETA | C74: YAPPY BG DE YASHIRA MICHELLY RAMOS PAJARO CASA 241 | D74: TARJETA | E74: 10 | G74: =+G73+E74+F74 -> 3451.81 | H74: a
A75: 45907 | B75: TARJETA | C75: BANCA MOVIL TRANSFERENCIA DE JANINA ANGELINNA BORELLY CASA 279 | D75: TARJETA | E75: 10 | G75: =+G74+E75+F75 -> 3461.81 | H75: a
A76: 45907 | B76: TARJETA | C76: YAPPY BG DE EDGARDO CHIARI FRANCO | D76: TARJETA | E76: 10 | G76: =+G75+E76+F76 -> 3471.81 | H76: a
A77: 45907 | B77: TARJETA | C77: YAPPY BG DE SARALIZ LORENA HUSBAND DE VELASQUEZ POR casa 117 tarjeta de acceso | D77: TARJETA | E77: 10 | G77: =+G76+E77+F77 -> 3481.81 | H77: a
A78: 45907 | B78: TARJETA | C78: BANCA MOVIL TRANSFERENCIA DE ADA ARGELIA CHONG CORREA C-133 | D78: TARJETA | E78: 10 | G78: =+G77+E78+F78 -> 3491.81 | H78: a
A79: 45907 | B79: TARJETA | C79: YAPPY BG DE MARIA DE LOS ANGELES MONTENEGRO DE LEON POR pago de targeta casa 14 | D79: TARJETA | E79: 10 | G79: =+G78+E79+F79 -> 3501.81 | H79: a
A80: 45907 | B80: 17838 | C80: YAPPY BG DE JOSE DAVID BONILLA ALVARADO POR Pago de Garita Flia Bonilla D14- MES DE AGOSTO | D80: D-14 | E80: 15 | G80: =+G79+E80+F80 -> 3516.81 | H80: a
A81: 45908 | B81: 17839 | C81: BANCA MOVIL TRANSFERENCIA DE LILIAN JAZMIN TUÑON DE TOULIER Agosto Septiembre casa 332 | D81: 332 | E81: 30 | G81: =+G80+E81+F81 -> 3546.81 | H81: a
A82: 45908 | B82: 17840 | C82: BANCA MOVIL TRANSFERENCIA DE ROLANDO BERNAL PACHECO BENNETT seguridad c160 agosto septiemb | D82: 160 | E82: 30 | G82: =+G81+E82+F82 -> 3576.81 | H82: a
A83: 45908 | B83: TARJETA | C83: BANCA MOVIL TRANSFERENCIA DE ROLANDO BERNAL PACHECO BENNETT seguridad c160 2-TARJETAS | D83: TARJETA | E83: 20 | G83: =+G82+E83+F83 -> 3596.81 | H83: a
A84: 45908 | B84: 17841 | C84: YAPPY BG DE ZAIS ANTONIO COSTARELOS HERRERA POR Familia Costarelos Casa 230 Julio Agosto Y septiembre | D84: 230 | E84: 45 | G84: =+G83+E84+F84 -> 3641.81 | H84: a
A85: 45908 | B85: RIFA | C85: YAPPY BG DE ZAIS ANTONIO COSTARELOS HERRERA POR Familia Costarelos casa 230 Pago de libre | D85: RIFA | E85: 10 | G85: =+G84+E85+F85 -> 3651.81 | H85: a
A86: 45908 | B86: TARJETA | C86: EFECTIVO - TARJETAS DE ENTRADA | D86: TARJETAS | E86: =515-30-15-75-90-15-120-60-30 -> 80 | G86: =+G85+E86+F86 -> 3731.81 | H86: a
A87: 45908 | B87: 17842 | C87: BANCA MOVIL TRANSFERENCIA DE ISABEL RIQUELME MARTINEZ casa 277 fliq Riquelme Luque mensual - SEPTIEMBRE | D87: 277 | E87: 15 | G87: =+G86+E87+F87 -> 3746.81 | H87: a
A88: 45908 | B88: 17843 | C88: YAPPY BG DE IDA CEMA JACKSON de VALENCIA - MES DE AGOSTO | D88: 270 | E88: 15 | G88: =+G87+E88+F88 -> 3761.81 | H88: a
A89: 45909 | B89: 17844 | C89: BANCA MOVIL TRANSFERENCIA DE KHALILA MITZOIE ASHBY DE BERMUDEZ Septiembre casa 212 Familia- MES DE SEPTIEMBRE | D89: 212 | E89: 15 | G89: =+G88+E89+F89 -> 3776.81 | H89: a
A90: 45909 | B90: TARJETA | C90: YAPPY BG DE ARTURO ROGELIO ROBINSON WILLIAMS POR Compra de 2 tarjetas casa 173 | D90: TARJETAS | E90: 20 | G90: =+G89+E90+F90 -> 3796.81 | H90: a
A91: 45909 | B91: PAGOS | C91: MANTEL PARA MESA GARITA | D91: PAGOS | E91: 0 | F91: -15 | G91: =+G90+E91+F91 -> 3781.81 | H91: a
A92: 45909 | B92: PAGOS | C92: TUBOS P/ORGANIZAR LA GARITA Y BAÑO | D92: PAGOS | E92: 0 | F92: =-6.93-6.37 -> -13.3 | G92: =+G91+E92+F92 -> 3768.51 | H92: a
A93: 45916 | B93: 17845 | C93: EFECTIVO - FABIOLA DE ALVEY- SEPTIEMBRE | D93: 188 | E93: 15 | G93: =+G92+E93+F93 -> 3783.51 | H93: a
A94: 45909 | B94: 17846 | C94: YAPPY BG DE MANUEL DE JESUS MEDINA ORTEGA POR septiembre y octubre Casa 25 | D94: 25 | E94: 30 | G94: =+G93+E94+F94 -> 3813.51 | H94: a
A95: 45909 | B95: 17847 | C95: YAPPY BG DE BOLIVAR RODRIGUEZ TORIBIO POR Casa 295 julio agost y sept | D95: 295 | E95: 45 | G95: =+G94+E95+F95 -> 3858.51 | H95: a
A96: 45901 | B96: 17848 | C96: YAPPY BG DE YUMITZIE ANNELIS HARWOOD de CEDEÑO POR mes de agosto casa 192 Flia Cedeno | D96: 192 | E96: 15 | G96: =+G95+E96+F96 -> 3873.51 | H96: a
A97: 45901 | B97: 17849 | C97: YAPPY BG DE JAIME ALBERTO PEREZ MERO- mes de septiembre | D97: 205 | E97: 15 | G97: =+G96+E97+F97 -> 3888.51 | H97: a
A98: 45910 | B98: 17850 | C98: BANCA MOVIL TRANSFERENCIA DE ALIZA EMERITA JIMENEZ - SEPTIEMBRE | D98: 30 | E98: 15 | F98: 0 | G98: =+G97+E98+F98 -> 3903.51 | H98: a
A99: 45913 | B99: 17851 | C99: EFECTIVO - CASA 260 FLIA MITCHELL - SEPTIEMBRE Y OCTUBRE | D99: 260 | E99: 30 | G99: =+G98+E99+F99 -> 3933.51 | H99: a
A100: 45910 | B100: 17852 | C100: YAPPY BG DE AMILKAR MORENO RIOS POR Mantenimiento Casa 36 agosto | D100: 36 | E100: 15 | F100: 0 | G100: =+G99+E100+F100 -> 3948.51 | H100: a
A101: 45910 | B101: 17853 | C101: YAPPY BG DE JACQUELINE YOVANIA VILLAMIL TORRES - mes de agosto | D101: 298 | E101: 15 | F101: 0 | G101: =+G100+E101+F101 -> 3963.51 | H101: a
A102: 45910 | B102: TARJETAS | C102: YAPPY BG DE JACQUELINE YOVANIA VILLAMIL TORRES - casa 298 | D102: TARJETAS | E102: 10 | G102: =+G101+E102+F102 -> 3973.51 | H102: a
A103: 45910 | B103: PAGOS | C103: BANCA MOVIL BAC INTERNATIONAL BANK 104349105 DISTRIBUIDORA GSQ PANAMA | D103: PAGOS | E103: 0 | F103: -210.59 | G103: =+G102+E103+F103 -> 3762.92 | H103: a
A104: 45911 | B104: TARJETA | C104: BANCA MOVIL TRANSFERENCIA DE ODALIS DEL CARMEN JAEN DE MENESES Pago de Tarjeta casa 50 | D104: TARJETAS | E104: 10 | F104: 0 | G104: =+G103+E104+F104 -> 3772.92 | H104: a
A105: 45911 | B105: 17854 | C105: YAPPY BG DE GIRLY ALEXIA ROBINSON MATOS POR Mantenimiento septiembre casa 257 | D105: 257 | E105: 15 | F105: 0 | G105: =+G104+E105+F105 -> 3787.92 | H105: a
...

Sheet pagos octubre 25
A1: DETALLE DE PAGOS EN BANCO
A2: MES DE OCTUBRE DE 2025
A4: Cuenta:Alborada 04-11-00-000468-4
A6: Fecha | B6: Recibo | C6: Descripción | D6: No.Casa | E6: Cobros | F6: Pagos | G6: Saldo total
A7: 45930 | C7: viene saldo anterior | G7: 5174.92
A8: 45931 | B8: 17944 | C8: YAPPY BG DE MARIET BROOKS SALAMANCA POR FliaBrooks casa 78 pago de seguridad sept y oct | D8: 78 | E8: 30 | G8: =+G7+E8+F8 -> 5204.92 | H8: a
A9: 45931 | B9: 17945 | C9: YAPPY BG DE SARALIZ LORENA HUSBAND DE VELASQUEZ POR casa 117 flia Velasquez mes de octubre | D9: 117 | E9: 15 | G9: =+G8+E9+F9 -> 5219.92 | H9: a
A10: 45931 | B10: 17946 | C10: ACH XPRESS - YOHANA MOLINAR- mes de octubre | D10: 113 | E10: 15 | G10: =+G9+E10+F10 -> 5234.92 | H10: a
A11: 45931 | B11: 17947 | C11: YAPPY BG DE JOSE DAVID BONILLA ALVARADO POR Septiembre 2025 Garita Casa D 14 Bonilla Gonz | D11: D-14 | E11: 15 | G11: =+G10+E11+F11 -> 5249.92 | H11: a
A12: 45931 | B12: 17948 | C12: BANCA MOVIL TRANSFERENCIA DE ROSEMENE SERVILIUS -mes de septiembre | D12: 182 | E12: 15 | G12: =+G11+E12+F12 -> 5264.92 | H12: a
A13: 45931 | B13: 17949 | C13: YAPPY BG DE ISAIAS FRANCISCO TATE BENJAMIN POR Seguridad y Mante Tate casa 239 mes Ago y septiembre | D13: 239 | E13: 30 | G13: =+G12+E13+F13 -> 5294.92 | H13: a
A14: 45931 | B14: 17950 | C14: BANCA MOVIL TRANSFERENCIA DE NATIVIDAD VALENCIA de JIMENEZ Pago mes de Septiembre Casa 26 | D14: 26 | E14: 15 | G14: =+G13+E14+F14 -> 5309.92 | H14: a
A15: 45931 | B15: 17951 | C15: YAPPY BG DE YUMITZIE ANNELIS HARWOOD de CEDEÑO POR mes de septiembre Flia Cedeno 192 | D15: 192 | E15: 15 | G15: =+G14+E15+F15 -> 5324.92 | H15: a
A16: 45931 | B16: 17952 | C16: YAPPY BG DE KASHMAH SHAMMETH CADOGAN de LEWIS POR mensualidad casa150 mes de julio | D16: 150 | E16: 15 | G16: =+G15+E16+F16 -> 5339.92 | H16: a
A17: 45931 | B17: 17953 | C17: YAPPY BG DE ANSELMO EMILIANO FORDE CHRISTOPHER- mes de octubre | D17: 5 | E17: 15 | G17: =+G16+E17+F17 -> 5354.92 | H17: a
A18: 45931 | B18: 17954 | C18: YAPPY BG DE HECTOR GABRIEL IBARGUEN MURILLO POR flia Ibarguen Ceballos mes septiembre | D18: 21 | E18: 15 | G18: =+G17+E18+F18 -> 5369.92 | H18: a
A19: 45931 | B19: PAGOS | C19: BANCA MOVIL TRANSFERENCIA A 0338011480674 TIGER SECURITY COMPANY AND TRAINING CENTER, S.A. | D19: PAGOS | E19: 0 | F19: -1819 | G19: =+G18+E19+F19 -> 3550.92 | H19: a
A20: 45931 | B20: 17955 | C20: BANCA MOVIL TRANSFERENCIA DE NILKA LORENA DEL CASTILLO ZELAYA casa 135- MES DE MAYO | D20: 135 | E20: 15 | G20: =+G19+E20+F20 -> 3565.92 | H20: a
A21: 45932 | B21: 17956 | C21: BANCA MOVIL TRANSFERENCIA DE JANINA ANGELINNA BORELLY de MELO Pago de oct nov dic casa 279 | D21: 279 | E21: 45 | G21: =+G20+E21+F21 -> 3610.92 | H21: a
A22: 45932 | B22: PAGOS | C22: BANCA MOVIL TRANSFERENCIA A 0454000010658 JOSE ALBERTO MARCIAGA BRAVO Materiales | D22: PAGOS | E22: 0 | F22: -15 | G22: =+G21+E22+F22 -> 3595.92 | H22: a
A23: 45932 | B23: 17957 | C23: YAPPY BG DE YURIBETH YAILYN LEE Casa 64 Familia Lee, Sep -Oct - Nov - Dic | D23: 64 | E23: 60 | G23: =+G22+E23+F23 -> 3655.92 | H23: a
A24: 45933 | B24: 17958 | C24: YAPPY BG DE ELOISA MALENY JAEN GUTIERREZ- MES DE AGOSTO | D24: 185 | E24: 15 | G24: =+G23+E24+F24 -> 3670.92 | H24: a
A25: 45933 | B25: 17959 | C25: YAPPY BG DE YELITZA YOLANY NORSE DE LA ESPADA POR pago Casa 318 - Agosto y Septiembre 202 | D25: 318 | E25: 30 | G25: =+G24+E25+F25 -> 3700.92 | H25: a
A26: 45933 | B26: 17960 | C26: YAPPY BG DE SHANI NG de CHIU POR Pago de Octubre familia Chiu casa 292 | D26: 292 | E26: 15 | G26: =+G25+E26+F26 -> 3715.92 | H26: a
A27: 45933 | B27: 17961 | C27: DEPOSITO -FLIA MURDOCK - MES DE SEPTIEMBRE | D27: 95 | E27: 15 | G27: =+G26+E27+F27 -> 3730.92 | H27: a
A28: 45933 | B28: 17962 | C28: BANCA MOVIL TRANSFERENCIA DE YOLANDA MAGALI CAMPOS GONZALEZ seguridad octubre 2025 | D28: 304 | E28: 15 | G28: =+G27+E28+F28 -> 3745.92 | H28: a
A29: 45933 | B29: 17963 | C29: YAPPY BG DE JAIME DAVID ANDERSON SINCLAIR- MES DE SEPTIEMBRE | D29: 172 | E29: 15 | G29: =+G28+E29+F29 -> 3760.92 | H29: a
A30: 45933 | B30: 17964 | C30: YAPPY BG DE EMELINA IVETT CATUY ALARCON- MES DE JULIO | D30: 68 | E30: 15 | G30: =+G29+E30+F30 -> 3775.92 | H30: a
A31: 45933 | B31: PAGOS | C31: BANCA MOVIL BAC INTERNATIONAL BANK 104349105 DISTRIBUIDORA GSQ PANAMA | D31: PAGOS | E31: 0 | F31: -213.52 | G31: =+G30+E31+F31 -> 3562.4 | H31: a
A32: 45933 | B32: 17965 | C32: YAPPY BG DE YANETH YAMILKA BADILLA PINEDA POR casa 157 octubre | D32: 157 | E32: 15 | G32: =+G31+E32+F32 -> 3577.4 | H32: a
A33: 45934 | B33: 17966 | C33: BANCA MOVIL TRANSFERENCIA DE ALIZA EMERITA JIMENEZ- MES DE OCTUBRE | D33: 30 | E33: 15 | G33: =+G32+E33+F33 -> 3592.4 | H33: a
A34: 45934 | B34: 17967 | C34: YAPPY BG DE AURA MERCEDES PINEDA de SANTAMARIA POR Casa 31 Familia Santamaria - MAYO, JUNIO, JULIO, AGOSTO, SEPTIEMBRE Y OCTUBRE | D34: 31 | E34: 90 | G34: =+G33+E34+F34 -> 3682.4 | H34: a
A35: 45934 | B35: TARJETAS | C35: YAPPY BG DE NELSON AZARIAS MORENO MAGDALENO POR - 3 TARJETAS CASA 310 | D35: TARJETAS | E35: 30 | G35: =+G34+E35+F35 -> 3712.4 | H35: a
A36: 45934 | B36: 17968 | C36: YAPPY BG DE NELSON AZARIAS MORENO MAGDALENO POR buen dia15 mes de oct 30 3 tarjeta de CASA 310 | D36: 310 | E36: 15 | G36: =+G35+E36+F36 -> 3727.4 | H36: a
A37: 45934 | B37: 17969 | C37: YAPPY BG DE YARITZA YAMILKA COOPER CHIFUNDO POR Casa 202 SChifundoYCooper mes de Sept 202 | D37: 202 | E37: 15 | G37: =+G36+E37+F37 -> 3742.4 | H37: a
A38: 45934 | B38: 17970 | C38: BANCA MOVIL TRANSFERENCIA DE EDWIN JAVIER ESCOBAR ROBINSON (YOUR PLUG) Flia Parris ENERO DE JUNIO | D38: 286 | E38: 90 | G38: =+G37+E38+F38 -> 3832.4 | H38: a
A39: 45934 | B39: 17971 | C39: YAPPY BG DE GUILLERMO CHALHOUB RODRIGUEZ POR Sept y Oct 2025 Casa 250 Alborada | D39: 250 | E39: 30 | G39: =+G38+E39+F39 -> 3862.4 | H39: a
A40: 45934 | B40: PAGOS | C40: YAPPY BG A MELVIN CARLTON FOSTER GALASTICA POR CORTE DE PARQUES | D40: PAGOS | E40: 0 | F40: -60 | G40: =+G39+E40+F40 -> 3802.4 | H40: a
A41: 45934 | B41: 17972 | C41: YAPPY BG DE VIELKA LUZMILA CUSATTI ANAYA - MES DE NOVIEMBRE | D41: 20 | E41: 15 | G41: =+G40+E41+F41 -> 3817.4 | H41: a
A42: 45934 | B42: 17973 | C42: YAPPY BG DE ARTURO ROGELIO ROBINSON WILLIAMS POR Pago de Sept a Dic 2025 casa 173 Flia Ro | D42: 173 | E42: 60 | G42: =+G41+E42+F42 -> 3877.4 | H42: a
A43: 45934 | B43: 17974 | C43: YAPPY BG DE LUZ MARIA BETEGON GARIBALDI POR casa 274 LuzM Betegon- MES DE JUNIO Y JULIO | D43: 274 | E43: 30 | G43: =+G42+E43+F43 -> 3907.4 | H43: a
A44: 45935 | B44: 17975 | C44: YAPPY BG DE YOLANDA ENEIDA LOPER ALABARCA POR mantenimiento octubre25 casa 271 | D44: 271 | E44: 20 | G44: =+G43+E44+F44 -> 3927.4 | H44: a
A45: 45935 | B45: 17976 | C45: YAPPY BG DE LUZMILA ELENA PORTER DE QUINTERO POR Septiembre25 | D45: 47 | E45: 15 | G45: =+G44+E45+F45 -> 3942.4 | H45: a
A46: 45935 | B46: 17977 | C46: YAPPY BG DE NIDIA ROSA BOHORQUEZ de MARTINEZ POR pago de casa 63 flia lia martinez septiemBRE A NOVIEMBRE | D46: 63 | E46: 45 | G46: =+G45+E46+F46 -> 3987.4 | H46: a
A47: 45936 | B47: 17978 | C47: BANCA MOVIL TRANSFERENCIA DE CARLOS ANTONIO MORAN MC COY Mant- OCTUBRE | D47: 251 | E47: 15 | G47: =+G46+E47+F47 -> 4002.4 | H47: a
A48: 45937 | B48: 17979 | C48: YAPPY BG DE PORFIRIO JUSTAVINO CEDEÑO POR octubre casa 289 | D48: 289 | E48: 15 | G48: =+G47+E48+F48 -> 4017.4 | H48: a
A49: 45937 | B49: TEATRO | C49: YAPPY BG DE PORFIRIO JUSTAVINO CEDEÑO POR pago 2 boletos de obra de teatro casa 289 | D49: TEATRO | E49: 24 | G49: =+G48+E49+F49 -> 4041.4 | H49: a
A50: 45937 | B50: 17980 | C50: BANCA MOVIL TRANSFERENCIA DE TWIRA TASHAWNNA ALLEYNE CLARK Casa 316 Ignacio Dreckett OCT aDICIEMBRE | D50: 316 | E50: 45 | G50: =+G49+E50+F50 -> 4086.4 | H50: a
A51: 45937 | B51: 17981 | C51: YAPPY BG DE CARLOS ENRIQUE GARAY DOMINGUEZ- MES DE OCTUBRE | D51: 4 | E51: 15 | G51: =+G50+E51+F51 -> 4101.4 | H51: a
A52: 45938 | B52: PAGOS | C52: YAPPY BG A HERNAN DARIO ROJAS LOPEZ POR 2 parques calle 6ta | D52: PAGOS | E52: 0 | F52: -70 | G52: =+G51+E52+F52 -> 4031.4 | H52: a
A53: 45938 | B53: 17982 | C53: BANCA MOVIL TRANSFERENCIA DE AIXA IVETTE HERNANDEZ SANTAMARIA (O) LOURDES LIZBETH LEZCANO - MARZO A JULIO | D53: 297 | E53: 75 | G53: =+G52+E53+F53 -> 4106.4 | H53: a
A54: 45939 | B54: 17983 | C54: BANCA MOVIL TRANSFERENCIA DE FERNANDO JOSE PENAS BLANCO-MES DE AGOSTO | D54: 169 | E54: 15 | G54: =+G53+E54+F54 -> 4121.4 | H54: a
A55: 45939 | B55: 17984 | C55: ACH - SYAHMAR MILENN ORTIZ CASTILLO- mes de octubre | D55: 46 | E55: 15 | G55: =+G54+E55+F55 -> 4136.4 | H55: a
A56: 45939 | B56: PAGOS | C56: YAPPY BG A HERNAN DARIO ROJAS LOPEZ POR Corte hierba parque grande | D56: PAGOS | E56: 0 | F56: -70 | G56: =+G55+E56+F56 -> 4066.4 | H56: a
A57: 45940 | B57: TARJETAS | C57: YAPPY BG DE MARIA DE LOS ANGELES MONTENEGRO DE LEON POR pago a targeta casa 16 | D57: TARJETAS | E57: 10 | G57: =+G56+E57+F57 -> 4076.4 | H57: a
A58: 45940 | B58: 17985 | C58: YAPPY BG DE MARIBEL ARISPE de VEGA- MES DE OCTUBRE | D58: 296 | E58: 15 | G58: =+G57+E58+F58 -> 4091.4 | H58: a
A59: 45940 | B59: PAGOS | C59: YAPPY BG A HERNAN DARIO ROJAS LOPEZ POR Canc Corte hierba parque grande | D59: PAGOS | E59: 0 | F59: -70 | G59: =+G58+E59+F59 -> 4021.4 | H59: a
A60: 45946 | B60: 17986 | C60: EFECTIVO- FABIOLA ALVEY - OCTUBRE | D60: 188 | E60: 15 | G60: =+G59+E60+F60 -> 4036.4 | H60: a
A61: 45940 | B61: 17987 | C61: YAPPY BG DE AMILKAR MORENO RIOS POR Mantenimiento Casa 36 Septiembre | D61: 36 | E61: 15 | F61: 0 | G61: =+G60+E61+F61 -> 4051.4 | H61: a
A62: 45940 | B62: 17988 | C62: YAPPY BG DE NIDIA EDITH RODRIGUEZ ORTIZ POR Familia Rodriguez casa267- mes DE JULIO | D62: 267 | E62: 15 | F62: 0 | G62: =+G61+E62+F62 -> 4066.4 | H62: a
A63: 45940 | B63: 17989 | C63: YAPPY BG DE PASTOR CAMARENA SMITH- OCTUBRE- NOBVIEMBRE Y DICIEMBRE | D63: D-10 | E63: 45 | F63: 0 | G63: =+G62+E63+F63 -> 4111.4 | H63: a
A64: 45940 | B64: 17990 | C64: YAPPY BG DE YANIZA INDIRA ATENCIO DE DRECKETT- SEPTIEMBRE Y OCTUBRE | D64: 18 | E64: 30 | F64: 0 | G64: =+G63+E64+F64 -> 4141.4 | H64: a
A65: 45941 | B65: 17991 | C65: BANCA MOVIL TRANSFERENCIA DE LUIS ENRIQUE AMADOR MARTINEZ pago mensual OCTUBRE | D65: 195 | E65: 15 | F65: 0 | G65: =+G64+E65+F65 -> 4156.4 | H65: a
A66: 45941 | B66: 17992 | C66: YAPPY BG DE JAIRO ABDIEL BUITRAGO VASQUEZ POR Septiembre Casa 100 | D66: 100 | E66: 15 | F66: 0 | G66: =+G65+E66+F66 -> 4171.4 | H66: a
A67: 45941 | B67: 17993 | C67: YAPPY BG DE ZAIDA NOEMI JIMENEZ SALAZAR- octubre y noviembre | D67: 91 | E67: 30 | F67: 0 | G67: =+G66+E67+F67 -> 4201.4 | H67: a
A68: 45942 | B68: TEATRO | C68: YAPPY BG DE NURIA ELENA JIMENEZ de ABREGO POR Boleto de obra 2178 Nuria | D68: TEATRO | E68: 12 | F68: 0 | G68: =+G67+E68+F68 -> 4213.4 | H68: a
A69: 45943 | B69: 17994 | C69: YAPPY BG DE SHARYN TAVANE DELGADO ROWE POR Octubre casa 199 Sharyn Delgado | D69: 199 | E69: 15 | F69: 0 | G69: =+G68+E69+F69 -> 4228.4 | H69: a
A70: 45944 | B70: 17995 | C70: YAPPY BG DE MARTIN LUIS MENESES TESIS POR Octubre FLIA Meneses 58 | D70: 58 | E70: 15 | F70: 0 | G70: =+G69+E70+F70 -> 4243.4 | H70: a
A71: 45944 | B71: 17996 | C71: BANCA MOVIL TRANSFERENCIA DE ERIC ARIEL VILLANUEVA - MES DE OCTUBRE | D71: 236 | E71: 15 | F71: 0 | G71: =+G70+E71+F71 -> 4258.4 | H71: a
A72: 45944 | B72: 17997 | C72: YAPPY BG DE NAYRA DEL CARMEN RAMOS RAMOS pago de garita - MES DE NOVIEMBRE | D72: 54 | E72: 15 | F72: 0 | G72: =+G71+E72+F72 -> 4273.4 | H72: a
A73: 45944 | B73: 17998 | C73: YAPPY BG DE ANIUTKA YOHANI ISAAC SILVERA POR casa 273 - MES DE AGOSTO | D73: 273 | E73: 15 | F73: 0 | G73: =+G72+E73+F73 -> 4288.4 | H73: a
A74: 45944 | B74: 17999 | C74: YAPPY BG DE MARTHA BIBIANA ACOSTA MARULANDA POR familia Estrada casa 105 mes octubre | D74: 105 | E74: 15 | F74: 0 | G74: =+G73+E74+F74 -> 4303.4 | H74: a
A75: 45944 | B75: TARJETAS | C75: YAPPY BG DE CIARA LUZ JIMENEZ CONCEPCION casa 16 | D75: TARJETAS | E75: 30 | F75: 0 | G75: =+G74+E75+F75 -> 4333.4 | H75: a
A76: 45945 | B76: 18000 | C76: YAPPY BG DE DAIZA BRU TORRES- MES DE SEPTIEMBREY OCTUBRE | D76: 143 | E76: 30 | F76: 0 | G76: =+G75+E76+F76 -> 4363.4 | H76: a
A77: 45945 | B77: 18001 | C77: YAPPY BG DE MELANY DEL CARMEN TAYLOR DELGADO POR Mes de noviembre 3era oeste casa 107 fam | D77: 107 | E77: 15 | F77: 0 | G77: =+G76+E77+F77 -> 4378.4 | H77: a
A78: 45945 | B78: 18002 | C78: BANCA MOVIL TRANSFERENCIA DE GREGORIA HEIDI BRYAN RAMOS casa 196 octubre | D78: 196 | E78: 15 | F78: 0 | G78: =+G77+E78+F78 -> 4393.4 | H78: a
A79: 45945 | B79: 18003 | C79: ACH - SERGIO JOSE DE CASTRO BUENDIA mes de octubre | D79: 246 | E79: 15 | F79: 0 | G79: =+G78+E79+F79 -> 4408.4 | H79: a
A80: 45945 | B80: 18004 | C80: BANCA MOVIL TRANSFERENCIA DE YARABY ORQUIDIA JIMENEZ pago seguridad Casa 303- MES DE SEPTIEMBRE | D80: 303 | E80: 15 | F80: 0 | G80: =+G79+E80+F80 -> 4423.4 | H80: a
A81: 45945 | B81: RIFA | C81: YAPPY BG DE JERONIMO VALENTIN HERNANDEZ CHIN | D81: RIFA | E81: 30 | F81: 0 | G81: =+G80+E81+F81 -> 4453.4 | H81: a
A82: 45945 | B82: 18005 | C82: YAPPY BG DE YESICA MARLENE CHIFUNDO DE PRESTAN POR mantenimiento de Noviembre Flia Prestan | D82: 210 | E82: 15 | F82: 0 | G82: =+G81+E82+F82 -> 4468.4 | H82: a
A83: 45945 | B83: 18006 | C83: BANCA MOVIL TRANSFERENCIA DE TOYA DELMINA BINGHAM de BETEGON Pago de OCTUBRE | D83: D-5 | E83: 15 | F83: 0 | G83: =+G82+E83+F83 -> 4483.4 | H83: a
A84: 45945 | B84: 18007 | C84: BANCA MOVIL TRANSFERENCIA DE YAVIRITZEL DEL CARMEN PANAY mes de octubre casa 187 | D84: 187 | E84: 15 | F84: 0 | G84: =+G83+E84+F84 -> 4498.4 | H84: a
A85: 45945 | B85: 18008 | C85: BANCA MOVIL TRANSFERENCIA DE VICENTE ROOK FRUTO casa 309 fla Rook mes de mayo | D85: 309 | E85: 15 | F85: 0 | G85: =+G84+E85+F85 -> 4513.4 | H85: a
A86: 45946 | B86: TEATRO | C86: BANCA MOVIL TRANSFERENCIA DE VICENTE ROOK FRUTO casa 309 fla Rook - boletoOBRA TEATRO | D86: TEATRO | E86: 12 | G86: =+G85+E86+F86 -> 4525.4 | H86: a
A87: 45945 | B87: 18009 | C87: YAPPY BG DE AYLLENE YEISURI SMALL CUERVO POR Octubre Flia Small Casa39 | D87: 39 | E87: 15 | F87: 0 | G87: =+G86+E87+F87 -> 4540.4 | H87: a
A88: 45945 | B88: 18010 | C88: BANCA MOVIL TRANSFERENCIA DE FERNANDO DE CASTRO BUENDIA- ME S DE OCTUBRE | D88: 311 | E88: 15 | F88: 0 | G88: =+G87+E88+F88 -> 4555.4 | H88: a
A89: 45945 | B89: TEATRO | C89: YAPPY BG DE YOLANDA ENEIDA LOPER ALABARCA POR pago de 6 boletos DagobertoParis | D89: TEATRO | E89: 72 | F89: 0 | G89: =+G88+E89+F89 -> 4627.4 | H89: a
A90: 45945 | B90: 18011 | C90: YAPPY BG DE ERNESTO GALVAN LEON - MES DE OCTUBRE | D90: 139 | E90: 15 | F90: 0 | G90: =+G89+E90+F90 -> 4642.4 | H90: a
A91: 45945 | B91: 18012 | C91: BANCA MOVIL TRANSFERENCIA DE YISEL BONET ALTAMIRANDA DE YARD pago mes de oct casa 156 flia | D91: 156 | E91: 15 | F91: 0 | G91: =+G90+E91+F91 -> 4657.4 | H91: a
A92: 45945 | B92: 18013 | C92: BANCA MOVIL TRANSFERENCIA DE JOSE MANUEL TUÑON RAMOS Pago de Octubre Casa 137 Familia Tuno | D92: 137 | E92: 15 | F92: 0 | G92: =+G91+E92+F92 -> 4672.4 | H92: a
A93: 45946 | B93: 18014 | C93: YAPPY BG DE GLADYS OSIRIS VILLANUEVA DE AGUILAR POR Pago de Agosto y Septiembre Casa 37 F | D93: 37 | E93: 30 | F93: 0 | G93: =+G92+E93+F93 -> 4702.4 | H93: a
A94: 45946 | B94: 18015 | C94: ACH XPRESS - JOSE LUIS GONZALEZ FLETCHER - OCTUBRE | D94: 247 | E94: 15 | F94: 0 | G94: =+G93+E94+F94 -> 4717.4 | H94: a
A95: 45946 | B95: 18016 | C95: YAPPY BG DE SUGEIRIS YANIRETH BARRETT JIMENEZ- mes de septiembre | D95: 326 | E95: 15 | F95: 0 | G95: =+G94+E95+F95 -> 4732.4 | H95: a
A96: 45946 | B96: 18017 | C96: BANCA MOVIL TRANSFERENCIA DE ROMELIA ORISSA HALL JOHNSON- mes de octubre | D96: 201 | E96: 15 | F96: 0 | G96: =+G95+E96+F96 -> 4747.4 | H96: a
A97: 45946 | B97: PAGOS | C97: BANCA MOVIL TRANSFERENCIA A 0454000010658 JOSE ALBERTO MARCIAGA BRAVO Abono trabajos en pa | D97: PAGOS | E97: 0 | F97: -150 | G97: =+G96+E97+F97 -> 4597.4 | H97: a
A98: 45947 | B98: 18018 | C98: BANCA MOVIL TRANSFERENCIA DE DAIRA ESTHER TAMAYO MARTINEZ octubre casa D 19 | D98: D-19 | E98: 15 | F98: 0 | G98: =+G97+E98+F98 -> 4612.4 | H98: a
A99: 45947 | B99: 18019 | C99: BANCA MOVIL TRANSFERENCIA DE NUDIA ESTHER MORALES de GUERRA casa315- MES DE SEPTIEMBRE | D99: 315 | E99: 15 | F99: 0 | G99: =+G98+E99+F99 -> 4627.4 | H99: a
A100: 45947 | B100: 18020 | C100: BANCA MOVIL TRANSFERENCIA DE ADA ARGELIA CHONG CORREA pago de mantenimiento casa 133 mes - OCTUBRE | D100: 133 | E100: 15 | F100: 0 | G100: =+G99+E100+F100 -> 4642.4 | H100: a
A101: 45947 | B101: 18021 | C101: YAPPY BG DE VIELKA GISELA MORAN MC COY de LOPEZ POR Pago de los meses de oct Nov Dic - FLIA LOPEZ | D101: 65 | E101: 45 | F101: 0 | G101: =+G100+E101+F101 -> 4687.4 | H101: a
A102: 45948 | B102: TEATRO | C102: YAPPY BG DE NAYRA DEL CARMEN RAMOS RAMOS (O) JERONIMO VALENTIN HERNANDEZ POR pago de bole | D102: TEATRO | E102: 36 | F102: 0 | G102: =+G101+E102+F102 -> 4723.4 | H102: a
...

Sheet pagos noviembre
A1: DETALLE DE PAGOS EN BANCO
A2: MES DE NOVIEMBRE DE 2025
A4: Cuenta:Alborada 04-11-00-000468-4
A6: Fecha | B6: Recibo | C6: Descripción | D6: No.Casa | E6: Cobros | F6: Pagos | G6: Saldo total
A7: 45961 | C7: viene saldo anterior | G7: =+'pagos octubre 25'!G200 -> 4252.56 | H7: a
A8: 45962 | B8: 18034 | C8: EFECTIVO- FLIA MENDOZA - NOVIEMBRE Y DICIEMBRE | D8: 244 | E8: 30 | G8: =+G7+E8+F8 -> 4282.56 | H8: a
A9: 45969 | B9: 18051 | C9: EFECTIVO - FLIA ALEXANDER - AGOSTO A NOVIEMBRE | D9: 89 | E9: 60 | G9: =+G8+E9+F9 -> 4342.56 | H9: a
A10: 45963 | B10: 18052 | C10: ACH -FLIA GONDOLA - MANT. NOVIEMBRE | D10: 113 | E10: 15 | G10: =+G9+E10+F10 -> 4357.56 | H10: a
A11: 45976 | B11: 18053 | C11: EFECTIVO - FLIA OGLIVE - MANT- junio a septiembre | D11: 186 | E11: 60 | G11: =+G10+E11+F11 -> 4417.56 | H11: a
A12: 45978 | B12: 18054 | C12: EFECTIVO - FLIA ALVEY - MANT. NOVIEMBRE | D12: 188 | E12: 15 | G12: =+G11+E12+F12 -> 4432.56 | H12: a
A13: 45962 | B13: TEATRO | C13: BANCA MOVIL TRANSFERENCIA DE YOLANDA MAGALI CAMPOS GONZALEZ pago de obra teatro | D13: TEATRO | E13: 12 | G13: =+G12+E13+F13 -> 4444.56 | H13: a
A14: 45962 | B14: PAGOS | C14: BANCA MOVIL TRANSFERENCIA A 0338011480674 TIGER SECURITY COMPANY AND TRAINING CENTER, S.A. | D14: PAGOS | E14: 0 | F14: -1819 | G14: =+G13+E14+F14 -> 2625.56 | H14: a
A15: 45962 | B15: PAGOS | C15: BANCA MOVIL TRANSFERENCIA A 0338011480674 TIGER SECURITY COMPANY AND TRAINING CENTER, S.A. | D15: PAGOS | E15: 0 | F15: -628.16 | G15: =+G14+E15+F15 -> 1997.4 | H15: a
A16: 45962 | B16: TEATRO | C16: YAPPY BG DE MIGUEL ROGELIO SANCHEZ PALACIO POR Pago de Boletos vendidos por Miguel Sanche | D16: TEATRO | E16: 180 | G16: =+G15+E16+F16 -> 2177.4 | H16: a
A17: 45962 | B17: PAGOS | C17: YAPPY BG A HERNAN DARIO ROJAS LOPEZ POR Corte Parque 6ta y vereda este | D17: PAGOS | E17: 0 | F17: -130 | G17: =+G16+E17+F17 -> 2047.4 | H17: a
A18: 45962 | B18: TEATRO | C18: YAPPY BG DE KATIRIA YATHZEEL ORTEGA CASTILLO POR casa 283 obra | D18: TEATRO | E18: 12 | G18: =+G17+E18+F18 -> 2059.4 | H18: a
A19: 45962 | B19: PAGOS | C19: BANCA MOVIL TRANSFERENCIA A 0472996299559 PEDRO ANTONIO GLASGOW BARRETT Corte de hierba | D19: PAGOS | E19: 0 | F19: -100 | G19: =+G18+E19+F19 -> 1959.4 | H19: a
A20: 45963 | B20: TARJETA | C20: BANCA MOVIL TRANSFERENCIA DE LILIAN JAZMIN TUÑON DE TOULIER tarjeta | D20: TARJETA | E20: 10 | G20: =+G19+E20+F20 -> 1969.4 | H20: a
A21: 45963 | B21: 18075 | C21: YAPPY BG DE GIRLY ALEXIA ROBINSON MATOS POR Pago mantenimiento Octubre casa 257 | D21: 257 | E21: 15 | G21: =+G20+E21+F21 -> 1984.4 | H21: a
A22: 45963 | B22: 18076 | C22: YAPPY BG DE MIOZOTIS DEL CARMEN OLMOS LARA- OCTUBRE | D22: 10 | E22: 15 | G22: =+G21+E22+F22 -> 1999.4 | H22: a
A23: 45963 | B23: 18077 | C23: BANCA MOVIL TRANSFERENCIA DE YAMILETH ALEIDA SANCHEZ DE ESPINOSA Mant y Seg ALBORADA JUL A SEPT | D23: 122 | E23: 45 | G23: =+G22+E23+F23 -> 2044.4 | H23: a
A24: 45963 | B24: 18078 | C24: YAPPY BG DE ALAIN AMINT ARAUZ POWELL POR Casa1 Mes de octubre y septiembre | D24: 1 | E24: 30 | G24: =+G23+E24+F24 -> 2074.4 | H24: a
A25: 45964 | B25: 18079 | C25: ACH XPRESS - DENNIS BARNES GRAHAM O SHARON TANISHA B ARNES - NOVIEMBRE Y DICIEMBRE | D25: 148 | E25: 30 | G25: =+G24+E25+F25 -> 2104.4 | H25: a
A26: 45965 | B26: 18080 | C26: BANCA MOVIL TRANSFERENCIA DE ALIZA EMERITA JIMENEZ - NOVIEMBRE | D26: 30 | E26: 15 | G26: =+G25+E26+F26 -> 2119.4 | H26: a
A27: 45965 | B27: 18081 | C27: BANCA MOVIL TRANSFERENCIA DE CARLOS ANTONIO MORAN MC COY MES - NOVIEMBRE | D27: 251 | E27: 15 | G27: =+G26+E27+F27 -> 2134.4 | H27: a
A28: 45965 | B28: 18082 | C28: BANCA MOVIL TRANSFERENCIA DE BARBARA ANN BENDIGO DE SANTAMARIA pago Dic 2025 Flia Santamar | D28: 44 | E28: 15 | G28: =+G27+E28+F28 -> 2149.4 | H28: a
A29: 45965 | B29: TEATRO | C29: BANCA MOVIL TRANSFERENCIA DE BARBARA ANN BENDIGO DE SANTAMARIA Colaboracion Obra teatral c | D29: TEATRO | E29: 12 | G29: =+G28+E29+F29 -> 2161.4 | H29: a
A30: 45966 | B30: 18083 | C30: YAPPY BG DE LUZMILA ELENA PORTER DE QUINTERO POR Oct25 | D30: 47 | E30: 15 | G30: =+G29+E30+F30 -> 2176.4 | H30: a
A31: 45966 | B31: 18084 | C31: BANCA MOVIL TRANSFERENCIA DE PIEDAD DEL CID Casa 57 pago del mes de Nov | D31: 57 | E31: 15 | G31: =+G30+E31+F31 -> 2191.4 | H31: a
A32: 45967 | B32: PAGOS | C32: BANCA MOVIL TRANSFERENCIA A 0454000010658 JOSE ALBERTO MARCIAGA BRAVO Abono trabajos muro | D32: PAGOS | E32: 0 | F32: -300 | G32: =+G31+E32+F32 -> 1891.4 | H32: a
A33: 45967 | B33: 18085 | C33: YAPPY BG DE ROBERTO ANTONIO JENKINS RENTERIA POR Casa 306 Roberto Jenkins paga septiembre Y OCTUBRE | D33: 306 | E33: 30 | G33: =+G32+E33+F33 -> 1921.4 | H33: a
A34: 45967 | B34: 18086 | C34: DEPOSITO -FLIA MURDOCK - OCTUBRE | D34: 95 | E34: 15 | G34: =+G33+E34+F34 -> 1936.4 | H34: a
A35: 45967 | B35: 18087 | C35: YAPPY BG DE SHANI NG de CHIU POR Pago de noviembre Flia Chiu casa 292 | D35: 292 | E35: 15 | G35: =+G34+E35+F35 -> 1951.4 | H35: a
A36: 45967 | B36: 18088 | C36: YAPPY BG DE LUCAS ANTONIO CORTES SURGEON POR Casa 134 oct- nov | D36: 134 | E36: 30 | G36: =+G35+E36+F36 -> 1981.4 | H36: a
A37: 45967 | B37: TEATRO | C37: BANCA MOVIL TRANSFERENCIA DE 0427120001653 DAYRA LUCILA CANALES - OBRA DE TEATRO | D37: TEATRO | E37: =245-30-151-10-30 -> 24 | G37: =+G36+E37+F37 -> 2005.4 | H37: a
A38: 45967 | B38: TEATRO | C38: OBRA DE TEATRO - ODALYS | D38: TEATRO | E38: 151 | G38: =+G37+E38+F38 -> 2156.4 | H38: a
A39: 45967 | B39: TARJETA | C39: CASA 313 COMPRA DE TARJETA | D39: TARJETA | E39: 10 | G39: =+G38+E39+F39 -> 2166.4 | H39: a
A40: 45967 | B40: 18089 | C40: FLIA PARRIS - CASA 286 - SEPTIEMBRE Y OCTUBRE | D40: 286 | E40: 30 | G40: =+G39+E40+F40 -> 2196.4 | H40: a
A41: 45967 | B41: 18090 | C41: YAPPY BG DE YOLANDA ENEIDA LOPER ALABARCA POR mantenimientocasa 271 noviembre2025 | D41: 271 | E41: 20 | G41: =+G40+E41+F41 -> 2216.4 | H41: a
A42: 45967 | B42: TEATRO | C42: BANCA MOVIL TRANSFERENCIA A 0427120001653 DAYRA LUCILA CANALES Devolucion de boletos Irasema duplicados | D42: TEATRO | E42: 0 | F42: -24 | G42: =+G41+E42+F42 -> 2192.4 | H42: a
A43: 45968 | B43: PAGOS | C43: BANCA MOVIL BAC INTERNATIONAL BANK 104349105 DISTRIBUIDORA GSQ PANAMA | D43: PAGOS | E43: 0 | F43: -74.9 | G43: =+G42+E43+F43 -> 2117.5 | H43: a
A44: 45968 | B44: 18091 | C44: YAPPY BG DE AURA MERCEDES PINEDA de SANTAMARIA POR Mes de noviembre casa 31 | D44: 31 | E44: 15 | G44: =+G43+E44+F44 -> 2132.5 | H44: a
A45: 45968 | B45: 18092 | C45: YAPPY BG DE PORFIRIO JUSTAVINO CEDEÑO- MES DE NOVIEMBRE | D45: 289 | E45: 15 | G45: =+G44+E45+F45 -> 2147.5 | H45: a
A46: 45968 | B46: 18093 | C46: YAPPY BG DE MARIBEL ARISPE de VEGA POR Pago de seguridad de noviembre 2025 casa 296 flia | D46: 296 | E46: 15 | G46: =+G45+E46+F46 -> 2162.5 | H46: a
A47: 45968 | B47: 18094 | C47: YAPPY BG DE BETZAIDA ITZEL CABEZA DE FORBES POR Pago seguridad familia Forbes casa 204 SEPTIEMBRE A DICIEMBRE | D47: 204 | E47: 60 | G47: =+G46+E47+F47 -> 2222.5 | H47: a
A48: 45968 | B48: 18095 | C48: BANCA MOVIL TRANSFERENCIA DE CARLOS ERNESTO LAMBERT PEREA - OCTUBRE A DICIEMBRE | D48: 223 | E48: 45 | G48: =+G47+E48+F48 -> 2267.5 | H48: a
A49: 45968 | B49: 18096 | C49: BANCA MOVIL TRANSFERENCIA DE FELICIA OLIVIA GITTENS MERCHANT Casa 40 Mant Sep y Oct Fam Gi | D49: 40 | E49: 30 | G49: =+G48+E49+F49 -> 2297.5 | H49: a
A50: 45968 | B50: 18097 | C50: YAPPY BG DE MARIA DE LOS ANGELES MONTENEGRO DE LEON POR mant casa 14 flia montenegro oct A DICIEMBRE | D50: 14 | E50: 45 | G50: =+G49+E50+F50 -> 2342.5 | H50: a
A51: 45968 | B51: 18098 | C51: YAPPY BG DE YEMIL DENISE RODRIGUEZ GONDOLA POR Casa 330 Vergara Rodriguez Agosto Septiemb Y OCTUBRE | D51: 330 | E51: 45 | G51: =+G50+E51+F51 -> 2387.5 | H51: a
A52: 45969 | B52: 18099 | C52: YAPPY BG DE SUNILA GITA PATEL SALDAÑA POR Casa 29 josefina de patel octubre y noviembre y | D52: 29 | E52: 30 | G52: =+G51+E52+F52 -> 2417.5 | H52: a
A53: 45971 | B53: 18100 | C53: YAPPY BG DE JAIME ALBERTO PEREZ MERO- NOVIEMBRE | D53: 205 | E53: 15 | G53: =+G52+E53+F53 -> 2432.5 | H53: a
A54: 45971 | B54: 18101 | C54: BANCA MOVIL TRANSFERENCIA DE LUIS ENRIQUE AMADOR MARTINEZ pago mensual NOVIEMBRE | D54: 195 | E54: 15 | G54: =+G53+E54+F54 -> 2447.5 | H54: a
A55: 45971 | B55: PAGOS | C55: BANCA MOVIL TRANSFERENCIA A 0495996629370 SANTOS DIOMEDES ARAUZ MEDINA Cancela factura 484 | D55: PAGOS | E55: 0 | F55: -85 | G55: =+G54+E55+F55 -> 2362.5 | H55: a
A56: 45972 | B56: 18102 | C56: ACH - SYAHMAR MILENN ORTIZ CASTILLO - NOVIEMBRE Y DICIEMBNRE | D56: 46 | E56: 30 | G56: =+G55+E56+F56 -> 2392.5 | H56: a
A57: 45972 | B57: 18103 | C57: BANCA MOVIL TRANSFERENCIA DE VICENTE ROOK FRUTO Fla Rook casa 309 agosto | D57: 309 | E57: 15 | G57: =+G56+E57+F57 -> 2407.5 | H57: a
A58: 45972 | B58: 18104 | C58: YAPPY BG DE MANUEL DE JESUS MEDINA ORTEGA POR Noviembre y Diciembre Casa 25 | D58: 25 | E58: 30 | G58: =+G57+E58+F58 -> 2437.5 | H58: a
A59: 45973 | B59: 18105 | C59: YAPPY BG DE ADAHIR ALEXIS LEONARD RIOS POR Pago de la garita OCTUBRE Y Noviembre- SIXTA CARDALES | D59: 213 | E59: 30 | G59: =+G58+E59+F59 -> 2467.5 | H59: a
A60: 45973 | B60: 18106 | C60: BANCA MOVIL TRANSFERENCIA DE AIXA IVETTE HERNANDEZ SANTAMARIA AGOSTO - SEPT Y OCTUBRE casa 297 | D60: 297 | E60: 45 | G60: =+G59+E60+F60 -> 2512.5 | H60: a
A61: 45974 | B61: 18107 | C61: BANCA MOVIL TRANSFERENCIA DE LINDA YAJAIRA LAJON ANDERSON seguridad casa 219 nov y dic | D61: 219 | E61: 30 | G61: =+G60+E61+F61 -> 2542.5 | H61: a
A62: 45974 | B62: 18108 | C62: BANCA MOVIL TRANSFERENCIA DE ROLANDO BERNAL PACHECO BENNETT cl 4ta casa 160 oct nov dic fa | D62: 160 | E62: 45 | G62: =+G61+E62+F62 -> 2587.5 | H62: a
A63: 45974 | B63: 18109 | C63: YAPPY BG DE YANIZA INDIRA ATENCIO DE DRECKETT - NOVIEMBRE Y DICIEMBRE | D63: 18 | E63: 30 | G63: =+G62+E63+F63 -> 2617.5 | H63: a
A64: 45974 | B64: TEATRO | C64: BANCA MOVIL TRANSFERENCIA DE ODALIS DEL CARMEN JAEN DE MENESES Pago varios | D64: TEATRO | E64: 24 | G64: =+G63+E64+F64 -> 2641.5 | H64: a
A65: 45975 | B65: RIFA | C65: BANCA MOVIL TRANSFERENCIA DE ODALIS DEL CARMEN JAEN DE MENESES Pago varios | D65: RIFA | E65: 10 | G65: =+G64+E65+F65 -> 2651.5 | H65: a
A66: 45974 | B66: 18110 | C66: DEPOSITO FLIA AVILA - ABRIL A JULIO | D66: 238 | E66: 60 | G66: =+G65+E66+F66 -> 2711.5 | H66: a
A67: 45974 | B67: PAGOS | C67: BANCA MOVIL TRANSFERENCIA A 0454000010658 JOSE ALBERTO MARCIAGA BRAVO Abono muro 6ta calle | D67: PAGOS | E67: 0 | F67: -350 | G67: =+G66+E67+F67 -> 2361.5 | H67: a
A68: 45975 | B68: 18111 | C68: BANCA MOVIL TRANSFERENCIA DE YISEL BONET ALTAMIRANDA DE YARD - NOVIEMBRE | D68: 156 | E68: 15 | G68: =+G67+E68+F68 -> 2376.5 | H68: a
A69: 45975 | B69: 18112 | C69: BANCA MOVIL TRANSFERENCIA DE DAIRA ESTHER TAMAYO MARTINEZ D19 mes de Noviembre | D69: D-19 | E69: 15 | G69: =+G68+E69+F69 -> 2391.5 | H69: a
A70: 45975 | B70: 18113 | C70: YAPPY BG DE VANESSA VICTORIA PARNTHER LUZCANDO POR Mant casa 75 calle 2da este flia Parnt - OCTUBRE Y NOVIEMBRE | D70: 75 | E70: 30 | G70: =+G69+E70+F70 -> 2421.5 | H70: a
A71: 45975 | B71: 18114 | C71: ACH - SERGIO JOSE DE CASTRO BUENDIA- NOVIEMBRE | D71: 246 | E71: 15 | G71: =+G70+E71+F71 -> 2436.5 | H71: a
A72: 45975 | B72: 18115 | C72: BANCA MOVIL TRANSFERENCIA DE YAVIRITZEL DEL CARMEN PANAY noviembre y diciembre casa 187 | D72: 187 | E72: 30 | G72: =+G71+E72+F72 -> 2466.5 | H72: a
A73: 45975 | B73: 18116 | C73: BANCA MOVIL TRANSFERENCIA DE JOSE ALEJANDRO BARROWS ROBINSON Casa 154 - OCTUBRE | D73: 154 | E73: 15 | G73: =+G72+E73+F73 -> 2481.5 | H73: a
A74: 45975 | B74: 18117 | C74: YAPPY BG DE MARTHA BIBIANA ACOSTA MARULANDA POR casa 105 familia Estrada noviembre | D74: 105 | E74: 15 | G74: =+G73+E74+F74 -> 2496.5 | H74: a
A75: 45975 | B75: 18118 | C75: YAPPY BG DE VIELKA LUZMILA CUSATTI ANAYA - diciembre | D75: 20 | E75: 15 | G75: =+G74+E75+F75 -> 2511.5 | H75: a
A76: 45975 | B76: 18119 | C76: BANCA MOVIL TRANSFERENCIA DE ERIC ARIEL VILLANUEVA -NOVIEMBRE | D76: 236 | E76: 15 | G76: =+G75+E76+F76 -> 2526.5 | H76: a
A77: 45975 | B77: 18120 | C77: YAPPY BG DE MARTIN LUIS MENESES TESIS POR noviembre casa58 Meneses | D77: 58 | E77: 15 | G77: =+G76+E77+F77 -> 2541.5 | H77: a
A78: 45975 | B78: 18121 | C78: YAPPY BG DE SHARYN TAVANE DELGADO ROWE POR Nov casa 199 Sharyn Delgado | D78: 199 | E78: 15 | G78: =+G77+E78+F78 -> 2556.5 | H78: a
A79: 45975 | B79: TARJETA | C79: BANCA MOVIL TRANSFERENCIA DE BETZAIDA ITZEL CABEZA DE FORBES pago tarjeta de acceso | D79: TARJETA | E79: 10 | G79: =+G78+E79+F79 -> 2566.5 | H79: a
A80: 45975 | B80: 18122 | C80: BANCA MOVIL TRANSFERENCIA DE YOLANDA FORBES FERNANDEZ casa 155 mes de noviembre | D80: 155 | E80: 15 | G80: =+G79+E80+F80 -> 2581.5 | H80: a
A81: 45975 | B81: 18123 | C81: YAPPY BG DE NAYRA DEL CARMEN RAMOS RAMOS pago segurid- DICIEMBRE | D81: 54 | E81: 15 | G81: =+G80+E81+F81 -> 2596.5 | H81: a
A82: 45975 | B82: 18124 | C82: YAPPY BG DE MELANY DEL CARMEN TAYLOR DELGADO POR Mes de diciembre familia Taylor 3era oes | D82: 107 | E82: 15 | G82: =+G81+E82+F82 -> 2611.5 | H82: a
A83: 45975 | B83: 18125 | C83: BANCA MOVIL TRANSFERENCIA DE ROMELIA ORISSA HALL JOHNSON Nov 25 | D83: 201 | E83: 15 | G83: =+G82+E83+F83 -> 2626.5 | H83: a
A84: 45976 | B84: 18126 | C84: YAPPY BG DE OSVALDO HERRERA CARRIAZO POR casa 53 Flia Herrera Bamby - OCTUBRE | D84: 53 | E84: 15 | G84: =+G83+E84+F84 -> 2641.5 | H84: a
A85: 45976 | B85: 18127 | C85: BANCA MOVIL TRANSFERENCIA DE FERNANDO DE CASTRO BUENDIA - NOVIEMBRE | D85: 311 | E85: 15 | G85: =+G84+E85+F85 -> 2656.5 | H85: a
A86: 45977 | B86: 18128 | C86: YAPPY BG DE STEPHANIE MICHELLE ESPINOSA GONZALEZ POR Casa 123 flia Espinosa mes de noviembre y diciembre | D86: 123 | E86: 30 | G86: =+G85+E86+F86 -> 2686.5 | H86: a
A87: 45977 | B87: 18129 | C87: BANCA MOVIL TRANSFERENCIA DE TOYA DELMINA BINGHAM de BETEGON Pago de mantenimiento Familia- NOVIEMBRE | D87: D-5 | E87: 15 | G87: =+G86+E87+F87 -> 2701.5 | H87: a
A88: 45977 | B88: 18130 | C88: ACH XPRESS - JOSE LUIS GONZALEZ FLETCHER O MAIQUEL ITZELA POLLACK- NOVIEMBRE | D88: 247 | E88: 15 | G88: =+G87+E88+F88 -> 2716.5 | H88: a
A89: 45977 | B89: 18131 | C89: YAPPY BG DE SUMAYKIRA YANILET GRENALD FERREIRA POR Pago de seguridad casa 136 - NOVIEMBRE | D89: 136 | E89: 15 | G89: =+G88+E89+F89 -> 2731.5 | H89: a
A90: 45977 | B90: 18132 | C90: BANCA MOVIL TRANSFERENCIA DE NEILA ELIDA JESSE DE SCOTT A TERCEROS - JULIO A OCTUBRE | D90: 206 | E90: 60 | G90: =+G89+E90+F90 -> 2791.5 | H90: a
A91: 45978 | B91: 18133 | C91: BANCA MOVIL TRANSFERENCIA DE FERNANDO JOSE PENAS BLANCO- SEPTIEMBRE | D91: 169 | E91: 15 | G91: =+G90+E91+F91 -> 2806.5 | H91: a
A92: 45978 | B92: 18134 | C92: YAPPY BG DE VANESSA VICTORIA PARNTHER LUZCANDO POR Mant Nv y Dic casa 80 calle IIdaEste S | D92: 80 | E92: 30 | G92: =+G91+E92+F92 -> 2836.5 | H92: a
A93: 45979 | B93: PAGOS | C93: COMPRA DE ARBOLITOS Y GLOBO SANTA | D93: PAGOS | E93: 0 | F93: -74 | G93: =+G92+E93+F93 -> 2762.5 | H93: a
A94: 45979 | B94: TEATRO | C94: BOLETOS OBRA DE TEATRO - DAYRA | D94: TEATRO | E94: 24 | G94: =+G93+E94+F94 -> 2786.5 | H94: a
A95: 45978 | B95: 18135 | C95: BANCA MOVIL TRANSFERENCIA DE YENITZA NAYROBIS ASHAW SMALL pago de octubre y noviembre casa | D95: 261 | E95: 30 | G95: =+G94+E95+F95 -> 2816.5 | H95: a
A96: 45978 | B96: 18136 | C96: YAPPY BG DE LUZ GRACIELA MARTINEZ RODRIGUEZ POR Pago de familia Sarmiento casa 245 mes SEPTIEMBRE Y OCTUBRE | D96: 245 | E96: 30 | G96: =+G95+E96+F96 -> 2846.5 | H96: a
A97: 45978 | B97: 18137 | C97: YAPPY BG DE ERNESTO GALVAN LEON - NOVIEMBRE | D97: 139 | E97: 15 | G97: =+G96+E97+F97 -> 2861.5 | H97: a
A98: 45979 | B98: 18138 | C98: BANCA MOVIL TRANSFERENCIA DE JOSE MANUEL TUÑON RAMOS Pago de Noviembre y Diciembre Casa 13 | D98: 137 | E98: 30 | G98: =+G97+E98+F98 -> 2891.5 | H98: a
A99: 45979 | B99: 18139 | C99: YAPPY BG DE JACQUELINE YOVANIA VILLAMIL TORRES | D99: 298 | E99: 15 | G99: =+G98+E99+F99 -> 2906.5 | H99: a
A100: 45980 | B100: 18140 | C100: EFECTIVO- FLIA VANEGAS - NOVI Y DICI | D100: 200 | E100: 30 | G100: =+G99+E100+F100 -> 2936.5 | H100: a
A101: 45962 | B101: 18141 | C101: YAPPY BG DE CELINDA DE LOURDES VALDES AGUILAR POR familia valdes casa 69 - JULIO | D101: 69 | E101: 15 | G101: =+G100+E101+F101 -> 2951.5 | H101: a
A102: 45962 | B102: 18142 | C102: YAPPY BG DE IDA CEMA JACKSON de VALENCIA - SEPTIEMBRE | D102: 270 | E102: 15 | G102: =+G101+E102+F102 -> 2966.5 | H102: a
...

Sheet pagos diciembre
A1: DETALLE DE PAGOS EN BANCO
A2: MES DE DICIEMBRE DE 2025
A4: Cuenta:Alborada 04-11-00-000468-4
A6: Fecha | B6: Recibo | C6: Descripción | D6: No.Casa | E6: Cobros | F6: Pagos | G6: Saldo total
A7: 45991 | C7: viene saldo anterior | G7: =+'pagos noviembre'!G193 -> 4185.97 | H7: a
A8: 45992 | B8: 18196 | C8: EFECTIVO - FAMILIA MACIA- MES DE NOVIEMBRE Y DICIEMBRE | D8: 11 | E8: 30 | G8: =+G7+E8+F8 -> 4215.97 | H8: a
A9: 45994 | B9: 18197 | C9: EFECTIVO - FAMILIA GONZALEZ --MES DE OCTUBRE-NOVIEMBRE Y DICIEMBRE | D9: 97 | E9: 45 | G9: =+G8+E9+F9 -> 4260.97 | H9: a
A10: 45994 | B10: 18198 | C10: EFECTIVO- REYNALDO ANGARITA- MES DE OCTUBRE- NOVIEMBRE Y DICIEMBRE | D10: 82 | E10: 45 | G10: =+G9+E10+F10 -> 4305.97 | H10: a
A11: 45994 | B11: 18200 | C11: EFECTIVO - PIEDAD DEL CID- DICIEMBRE | D11: 57 | E11: 15 | G11: =+G10+E11+F11 -> 4320.97 | H11: a
A12: 46004 | B12: 18201 | C12: FAMILIA CUENCO- MANT NOVIEMBRE Y DICIEMBRE | D12: 253 | E12: 30 | G12: =+G11+E12+F12 -> 4350.97 | H12: a | I12: EFECTIVO X DEPOSITAR
A13: 45994 | B13: 18223 | C13: EFECTIVO- IRACEMA DE SMALL- NOVIEMBRE Y DICIEMBRE | D13: 119 | E13: 30 | G13: =+G12+E13+F13 -> 4380.97 | H13: a
A14: 45994 | B14: 18224 | C14: EFECTIVO - DELANO SAUNDERS- NOVIEMBRE Y DICIEMBRE | D14: 285 | E14: 30 | G14: =+G13+E14+F14 -> 4410.97 | H14: a
A15: 45994 | B15: RIFA 2 | C15: FLIA VANEGAS RIFA JAMON #80 | D15: RIFA 2 | E15: 5 | F15: 0 | G15: =+G14+E15+F15 -> 4415.97 | H15: a
B16: 18225 | C16: NUMERO DE NOVIEMBRE | F16: 0 | G16: =+G15+E16+F16 -> 4415.97 | H16: a
A17: 45992 | B17: 18226 | C17: YAPPY BG DE ZAIS ANTONIO COSTARELOS HERRERA POR Casa 230 Familia Costarelos- noviembre y diciembre | D17: 230 | E17: 30 | F17: 0 | G17: =+G16+E17+F17 -> 4445.97 | H17: a
A18: 45992 | B18: 18227 | C18: YAPPY BG DE JAIME DAVID ANDERSON SINCLAIR- NOVIEMBRE | D18: 172 | E18: 15 | F18: 0 | G18: =+G17+E18+F18 -> 4460.97 | H18: a
A19: 45992 | B19: 18228 | C19: BANCA MOVIL TRANSFERENCIA DE GYSELLE DEYANIRA GRANT WELCH NOV y DIC casa 265 | D19: 265 | E19: 30 | F19: 0 | G19: =+G18+E19+F19 -> 4490.97 | H19: a
A20: 45992 | B20: 18229 | C20: ACH - EMILIO STERLING LOVET WILSON- AGOSTO | D20: 67 | E20: 15 | F20: 0 | G20: =+G19+E20+F20 -> 4505.97 | H20: a
A21: 45992 | B21: 18230 | C21: ACH - JENISEL ELENA HOYTE ARISPE - MARZO - ABRIL | D21: 275 | E21: 30 | F21: 0 | G21: =+G20+E21+F21 -> 4535.97 | H21: a
A22: 45992 | B22: 18231 | C22: YAPPY BG DE ARIE CORPAS BETEGON- NOV-DIC | D22: 319 | E22: 30 | F22: 0 | G22: =+G21+E22+F22 -> 4565.97 | H22: a
A23: 45992 | B23: 18232 | C23: YAPPY BG DE JOSE DAVID BONILLA ALVARADO POR Flia Bonilla Casa D14 Pago de garita Noviembr | D23: D-14 | E23: 15 | F23: 0 | G23: =+G22+E23+F23 -> 4580.97 | H23: a
A24: 45992 | B24: 18233 | C24: YAPPY BG DE CARLOS ANTONIO SIERRA ACOSTA- OCTUBRE | D24: 110 | E24: 15 | F24: 0 | G24: =+G23+E24+F24 -> 4595.97 | H24: a
A25: 45992 | B25: RIFA 2 | C25: YAPPY BG DE SHARYN TAVANE DELGADO ROWE POR Casa 199 boleto 86 | D25: RIFA 2 | E25: 5 | F25: 0 | G25: =+G24+E25+F25 -> 4600.97 | H25: a
A26: 45993 | B26: 18234 | C26: BANCA MOVIL TRANSFERENCIA DE ROSEMENE SERVILIUS MEDIEU (CARIBBEAN FOOD GOURMET) mes de nov | D26: 182 | E26: 15 | G26: =+G25+E26+F26 -> 4615.97 | H26: a
A27: 45993 | B27: 18235 | C27: BANCA MOVIL TRANSFERENCIA DE CARLENI ANYURE CLOP FLORES Junio julio agosto casa 149 Ricard | D27: 149 | E27: 45 | F27: 0 | G27: =+G26+E27+F27 -> 4660.97 | H27: a
A28: 45993 | B28: PAGOS | C28: BANCA MOVIL TRANSFERENCIA A 0338011480674 TIGER SECURITY COMPANY AND TRAINING CENTER, S.A. | D28: PAGOS | E28: 0 | F28: -1819 | G28: =+G27+E28+F28 -> 2841.97 | H28: a
A29: 45993 | B29: 18236 | C29: YAPPY BG DE CELINDA DE LOURDES VALDES AGUILAR POR FAMILIA VALDES CASA 69- AGOSTO | D29: 69 | E29: 15 | F29: 0 | G29: =+G28+E29+F29 -> 2856.97 | H29: a
A30: 45993 | B30: 18237 | C30: BANCA MOVIL TRANSFERENCIA DE GREGORIA HEIDI BRYAN RAMOS noviembre diciembre 196 | D30: 196 | E30: 30 | F30: 0 | G30: =+G29+E30+F30 -> 2886.97 | H30: a
A31: 45993 | B31: 18238 | C31: DEPOSITO CUENTA DE AHORROS SIN LIBRETA | E31: 15 | F31: 0 | G31: =+G30+E31+F31 -> 2901.97 | H31: a
A32: 45993 | B32: RIFA 2 | C32: YAPPY BG DE NURIA ELENA JIMENEZ de ABREGO POR pagonumerosde rifa Nuria | D32: RIFA 2 | E32: 15 | F32: 0 | G32: =+G31+E32+F32 -> 2916.97 | H32: a
A33: 45993 | B33: 18239 | C33: YAPPY BG DE OSVALDO HERRERA CARRIAZO POR casa 53 Bamby Herrera - NOVIEMBRE | D33: 53 | E33: 15 | F33: 0 | G33: =+G32+E33+F33 -> 2931.97 | H33: a
A34: 45993 | B34: 18240 | C34: BANCA MOVIL TRANSFERENCIA DE NUDIA ESTHER MORALES de GUERRA- OCT-NOVY DIC | D34: 315 | E34: 45 | F34: 0 | G34: =+G33+E34+F34 -> 2976.97 | H34: a
A35: 45993 | B35: 18241 | C35: YAPPY BG DE LUZ GRACIELA MARTINEZ RODRIGUEZ POR Casa 245 pago de nov y diciembre 2025 fam | D35: 245 | E35: 30 | F35: 0 | G35: =+G34+E35+F35 -> 3006.97 | H35: a
A36: 45993 | B36: 18242 | C36: YAPPY BG DE YOLANDA ENEIDA LOPER ALABARCA POR mantenimiento casa 271 diciembre 2025 | D36: 271 | E36: 20 | F36: 0 | G36: =+G35+E36+F36 -> 3026.97 | H36: a
A37: 45993 | B37: 18243 | C37: YAPPY BG DE MAUREL MARIAM MIER de ESCOBAR- NOVIEMBRE | D37: 221 | E37: 15 | F37: 0 | G37: =+G36+E37+F37 -> 3041.97 | H37: a
A38: 45993 | B38: 18244 | C38: YAPPY BG DE YARIBEL RUIZ DE GRACIA- JUNIO, JULIO Y AGOSTO | D38: 41 | E38: 45 | G38: =+G37+E38+F38 -> 3086.97 | H38: a
A39: 45994 | B39: 18245 | C39: BANCA MOVIL TRANSFERENCIA DE DAIZA BRU TORRES- NOVIEMBRE Y DICIEMBRE | D39: 143 | E39: 30 | F39: 0 | G39: =+G38+E39+F39 -> 3116.97 | H39: a
A40: 45994 | B40: PAGOS | C40: BANCA MOVIL TRANSFERENCIA A 0454000010658 JOSE ALBERTO MARCIAGA BRAVO Trabajos parque 6ta | D40: PAGOS | E40: 0 | F40: -300 | G40: =+G39+E40+F40 -> 2816.97 | H40: a
A41: 45994 | B41: 18246 | C41: YAPPY BG DE JAIME DAVID ANDERSON DEL VALLE POR Pago de garita casa 231 | D41: 231 | E41: 45 | F41: 0 | G41: =+G40+E41+F41 -> 2861.97 | H41: a
A42: 45994 | B42: RIFA 2 | C42: YAPPY BG DE ILKA MELISA MARK HOY | D42: RIFA 2 | E42: 10 | F42: 0 | G42: =+G41+E42+F42 -> 2871.97 | H42: a
A43: 45995 | B43: 18247 | C43: DEPOSITO- PEDRO AVILA - OCTUBRE Y NOVIEMBRE | D43: 238 | E43: 30 | F43: 0 | G43: =+G42+E43+F43 -> 2901.97 | H43: a
A44: 45995 | B44: 18248 | C44: YAPPY BG DE EDGARDO CHIARI FRANCO -DICIEMBRE | D44: 329 | E44: 15 | F44: 0 | G44: =+G43+E44+F44 -> 2916.97 | H44: a
A45: 45995 | B45: 18249 | C45: YAPPY BG DE ANA MICHELLE PILE OSSA (O) ARELIS VANESSA OSSA DIAZ POR Casa 106 noviembre y diciembre | D45: 106 | E45: 30 | F45: 0 | G45: =+G44+E45+F45 -> 2946.97 | H45: a
A46: 45995 | B46: 18250 | C46: BANCA MOVIL TRANSFERENCIA DE NIDIA SILGADO LEON Casa 164 mes DICIEMBRE | D46: 164 | E46: 15 | F46: 0 | G46: =+G45+E46+F46 -> 2961.97 | H46: a
A47: 45995 | B47: 18251 | C47: YAPPY BG DE MARIBEL ARISPE de VEGA | D47: 296 | E47: 15 | F47: 0 | G47: =+G46+E47+F47 -> 2976.97 | H47: a
A48: 45995 | B48: DONACION | C48: BANCA MOVIL TRANSFERENCIA DE VICTOR DE JESUS CASTILLO CORTEZ A TERCEROS | D48: DONACION | E48: 700 | F48: 0 | G48: =+G47+E48+F48 -> 3676.97 | H48: a
A49: 46007 | B49: 18252 | C49: BANCA MOVIL TRANSFERENCIA DE NATIVIDAD VALENCIA de JIMENEZ -NOVIEMNRE | D49: 26 | E49: 15 | G49: =+G48+E49+F49 -> 3691.97 | H49: a
A50: 45995 | B50: 18253 | C50: YAPPY BG DE NATIVIDAD SANCHEZ DE FORBES POR casa 175 familia Forbes mes de Noviembre | D50: 175 | E50: 15 | F50: 0 | G50: =+G49+E50+F50 -> 3706.97 | H50: a
A51: 45995 | B51: 18254 | C51: BANCA MOVIL TRANSFERENCIA DE YOLANDA MAGALI CAMPOS GONZALEZ Mes de diciembre 2025 casa 304 | D51: 304 | E51: 15 | F51: 0 | G51: =+G50+E51+F51 -> 3721.97 | H51: a
A52: 45996 | B52: 18255 | C52: YAPPY BG DE ROBERTO ANTONIO JENKINS RENTERIA POR Casa 306 Roberto Jenkins paga noviembre | D52: 306 | E52: 30 | F52: 0 | G52: =+G51+E52+F52 -> 3751.97 | H52: a
A53: 45996 | B53: 18256 | C53: YAPPY BG DE YANETH YAMILKA BADILLA PINEDA POR casa 157 diciembre | D53: 157 | E53: 15 | F53: 0 | G53: =+G52+E53+F53 -> 3766.97 | H53: a
A54: 45996 | B54: 18257 | C54: BANCA MOVIL TRANSFERENCIA DE CARLOS ANTONIO MORAN MC COY Pago de mantenimiento diciembre | D54: 251 | E54: 15 | F54: 0 | G54: =+G53+E54+F54 -> 3781.97 | H54: a
A55: 45996 | B55: 18258 | C55: YAPPY BG DE LUZMILA ELENA PORTER DE QUINTERO POR 301125 Lp Primera C47- noviembre | D55: 47 | E55: 15 | F55: 0 | G55: =+G54+E55+F55 -> 3796.97 | H55: a
A56: 45996 | B56: 18259 | C56: BANCA MOVIL TRANSFERENCIA DE JOSSUA EMMIR WILLIAMS RIOS Seguridad y Mantenimiento -DICIEMBRE | D56: 327 | E56: 15 | F56: 0 | G56: =+G55+E56+F56 -> 3811.97 | H56: a
A57: 45996 | B57: 18260 | C57: BANCA MOVIL TRANSFERENCIA DE DIANA MARIA SANCHEZ FLORES- NOVIEMBRE Y DICIEMBRE | D57: D-24 | E57: 30 | F57: 0 | G57: =+G56+E57+F57 -> 3841.97 | H57: a
A58: 45996 | B58: 18261 | C58: YAPPY BG DE ZAIDA NOEMI JIMENEZ SALAZAR- DICIEMBRE | D58: 91 | E58: 15 | F58: 0 | G58: =+G57+E58+F58 -> 3856.97 | H58: a
A59: 45996 | B59: 18262 | C59: YAPPY BG DE DAYANARA ITZEL BENJAMIN DE DE LEON POR casa D 12 oct nov dic 2025 | D59: D-12 | E59: 45 | F59: 0 | G59: =+G58+E59+F59 -> 3901.97 | H59: a
A60: 45996 | B60: 18263 | C60: YAPPY BG DE ROBERTO RODRIGUEZ PEREIRA POR Casa 43 familia Rodriguez- MAYO A NOVIEMBRE | D60: 43 | E60: 105 | F60: 0 | G60: =+G59+E60+F60 -> 4006.97 | H60: a
A61: 45997 | B61: 18264 | C61: YAPPY BG DEERIC LASONDER casa 49- MAYO, JUNIO Y JULIO | D61: 49 | E61: 45 | F61: 0 | G61: =+G60+E61+F61 -> 4051.97 | H61: a
A62: 45997 | B62: 18265 | C62: BANCA MOVIL TRANSFERENCIA DE LUIS ENRIQUE AMADOR MARTINEZ pago mensual- DICIEMBRE | D62: 195 | E62: 15 | G62: =+G61+E62+F62 -> 4066.97 | H62: a
A63: 45997 | B63: 18266 | C63: BANCA MOVIL TRANSFERENCIA DE VICENTE ROOK FRUTO Fla Rook casa 309 | D63: 309 | E63: 30 | G63: =+G62+E63+F63 -> 4096.97 | H63: a
A64: 45997 | B64: PAGOS | C64: BANCA MOVIL TRANSFERENCIA A 0454000010658 JOSE ALBERTO MARCIAGA BRAVO Abono a trabajos par | D64: PAGOS | E64: 0 | F64: -100 | G64: =+G63+E64+F64 -> 3996.97 | H64: a
A65: 45997 | B65: PAGOS | C65: BANCA MOVIL TRANSFERENCIA A 0472996299559 PEDRO ANTONIO GLASGOW BARRETT Corte de hierba pa | D65: PAGOS | E65: 0 | F65: -100 | G65: =+G64+E65+F65 -> 3896.97 | H65: a
A66: 45997 | B66: 18267 | C66: YAPPY BG DE SHANI NG de CHIU POR mes de DicCasa 292 Flia chiu | D66: 292 | E66: 15 | F66: 0 | G66: =+G65+E66+F66 -> 3911.97 | H66: a
A67: 45997 | B67: 18268 | C67: BANCA MOVIL TRANSFERENCIA DE ALIZA EMERITA JIMENEZ- MES DE DICIEMBRE | D67: 30 | E67: 15 | F67: 0 | G67: =+G66+E67+F67 -> 3926.97 | H67: a
A68: 45998 | B68: PAGOS | C68: YAPPY BG A HERNAN DARIO ROJAS LOPEZ POR CORTE 3 PARQUES SEXTA Y CIRCUNVALACION | D68: PAGOS | E68: 0 | F68: -210 | G68: =+G67+E68+F68 -> 3716.97 | H68: a
A69: 45998 | B69: RIFA 2 | C69: YAPPY BG DE QUERUBI LIZET NEREIDA de HILTON POR Pago de rifa casa 19 primera calle | D69: RIFA 2 | E69: 30 | F69: 0 | G69: =+G68+E69+F69 -> 3746.97 | H69: a
A70: 45998 | B70: 18269 | C70: YAPPY BG DE QUERUBI LIZET NEREIDA de HILTON POR Mes de diciembre casa 19 familia Nereida | D70: 19 | E70: 15 | F70: 0 | G70: =+G69+E70+F70 -> 3761.97 | H70: a
A71: 45998 | B71: PAGOS | C71: YAPPY BG A MELVIN CARLTON FOSTER GALASTICA POR Corte hierba | D71: PAGOS | E71: 0 | F71: -60 | G71: =+G70+E71+F71 -> 3701.97 | H71: a
A72: 46000 | B72: RIFA 2 | C72: YAPPY BG DE JAIME CEBALLOS ANDRADE POR Rifa Navidad 38 casa 147 | D72: RIFA 2 | E72: 5 | F72: 0 | G72: =+G71+E72+F72 -> 3706.97 | H72: a
A73: 46000 | B73: 18270 | C73: BANCA EN LINEA TRANSFERENCIA DE 0427120001653 DAYRA LUCILA CANALES de SWANSTON casa 240 NOVIEMBRE Y DICIEMBRE | D73: 240 | E73: 30 | F73: 0 | G73: =+G72+E73+F73 -> 3736.97 | H73: a
A74: 46000 | B74: RIFA 2 | C74: YAPPY BG DE NITZIA ITZEL AGUILAR GALVAN POR boleto rifa num45 | D74: RIFA 2 | E74: 5 | F74: 0 | G74: =+G73+E74+F74 -> 3741.97 | H74: a
A75: 46000 | B75: 18271 | C75: YAPPY BG DE NITZIA ITZEL AGUILAR GALVAN POR abono mensualidadesseguridadCasa56- MAYO Y JUNIO | D75: 56 | E75: 30 | F75: 0 | G75: =+G74+E75+F75 -> 3771.97 | H75: a
A76: 46001 | B76: RIFA 2 | C76: ACH XPRESS - PAMELA PATRICIA PETERS BAILEY OR ALBERTO BELFORD MEL | D76: RIFA 2 | E76: 20 | F76: 0 | G76: =+G75+E76+F76 -> 3791.97 | H76: a
A77: 46001 | B77: NAVIDAD | C77: BANCA MOVIL TRANSFERENCIA DE 0427120001653 DAYRA CANALES-COMPRA DE LUCES NAVIDAD | D77: NAVIDAD | E77: 0 | F77: -31.25 | G77: =+G76+E77+F77 -> 3760.72 | H77: a
A78: 45997 | B78: 18272 | C78: YAPPY- GILBERTO GARCIA - DICIEMBRE | D78: 301 | E78: 15 | F78: 0 | G78: =+G77+E78+F78 -> 3775.72 | H78: a
A79: 45997 | B79: TARJETA | C79: TARJETA DE ENTRADA - CASA #11 | D79: TARJETA | E79: 10 | F79: 0 | G79: =+G78+E79+F79 -> 3785.72 | H79: a
A80: 46003 | B80: 18273 | C80: YAPPY BG DE JAIME ALBERTO PEREZ MERO- DICIEMBRE | D80: 205 | E80: 15 | F80: 0 | G80: =+G79+E80+F80 -> 3800.72 | H80: a
A81: 46003 | B81: 18274 | C81: YAPPY BG DE YELITZA YOLANY NORSE DE LA ESPADA POR Pago Nov y Dic - Casa 318 | D81: 318 | E81: 30 | F81: 0 | G81: =+G80+E81+F81 -> 3830.72 | H81: a
A82: 46003 | B82: 18275 | C82: YAPPY BG DE ANIUTKA YOHANI ISAAC SILVERA POR casa 273-SEPTIEMBRE | D82: 273 | E82: 15 | G82: =+G81+E82+F82 -> 3845.72 | H82: a
A83: 46003 | B83: 18276 | C83: YAPPY BG DE CARLOS ANTONIO SIERRA ACOSTA- NOVIEMBRE | D83: 110 | E83: 15 | F83: 0 | G83: =+G82+E83+F83 -> 3860.72 | H83: a
A84: 46003 | B84: 18277 | C84: ACH - EDWIN IDEL CEDEÃ?O CARDENAS- OCTUBRE- NOVIEMBRE Y DICIEMBRE | D84: 258 | E84: 45 | F84: 0 | G84: =+G83+E84+F84 -> 3905.72 | H84: a
A85: 46003 | B85: RIFA 2 | C85: YAPPY BG DE YOLANDA ENEIDA LOPER ALABARCA POR pago rifa alborada casa 271 | D85: RIFA 2 | E85: 30 | F85: 0 | G85: =+G84+E85+F85 -> 3935.72 | H85: a
A86: 46003 | B86: 18278 | C86: YAPPY BG DE SHARYN TAVANE DELGADO ROWE- DICIEMBRE | D86: 199 | E86: 15 | F86: 0 | G86: =+G85+E86+F86 -> 3950.72 | H86: a
A87: 46003 | B87: RIFA 2 | C87: YAPPY BG DE JAIME ALBERTO PEREZ MERO | D87: RIFA 2 | E87: 25 | F87: 0 | G87: =+G86+E87+F87 -> 3975.72 | H87: a
A88: 46003 | B88: RIFA 2 | C88: YAPPY BG DE JENIFER ODALILIA MORENO DE WELLER POR pago de Rifa navidena casa 146 | D88: RIFA 2 | E88: 5 | F88: 0 | G88: =+G87+E88+F88 -> 3980.72 | H88: a
A89: 46003 | B89: 18279 | C89: BANCA MOVIL TRANSFERENCIA DE ERIC ARIEL VILLANUEVA - DICIEMBRE | D89: 236 | E89: 15 | G89: =+G88+E89+F89 -> 3995.72 | H89: a
A90: 46003 | B90: RIFA 2 | C90: YAPPY BG DE EDIANI YENISEL MARTINEZ ARAUZ POR Pago rifa navidena calle cuarta este casa 1 | D90: RIFA 2 | E90: 5 | F90: 0 | G90: =+G89+E90+F90 -> 4000.72 | H90: a
A91: 46003 | B91: 18280 | C91: BANCA MOVIL TRANSFERENCIA DE DAIRA ESTHER TAMAYO MARTINEZ Diciembre casa D19 | D91: D-19 | E91: 15 | F91: 0 | G91: =+G90+E91+F91 -> 4015.72 | H91: a
A92: 46003 | B92: 18281 | C92: YAPPY BG DE VANESSA VICTORIA PARNTHER LUZCANDO POR Casa 75 mes de diciembre familia Parnt | D92: 75 | E92: 15 | F92: 0 | G92: =+G91+E92+F92 -> 4030.72 | H92: a
A93: 46003 | B93: NAVIDAD | C93: BANCA MOVIL TRANSFERENCIA A 0454000010658 JOSE ALBERTO MARCIAGA BRAVO Pintura arbolito | D93: NAVIDAD | E93: 0 | F93: -17.1 | G93: =+G92+E93+F93 -> 4013.62 | H93: a
A94: 46004 | B94: 18282 | C94: YAPPY BG DE LEAN LOY LOPEZ DE HOYOS POR Casa 8 octubre noviembre y diciembre | D94: 8 | E94: 45 | F94: 0 | G94: =+G93+E94+F94 -> 4058.62 | H94: a
A95: 46004 | B95: RIFA 2 | C95: YAPPY BG DE LEAN LOY LOPEZ DE HOYOS POR Rifa | D95: RIFA 2 | E95: 15 | G95: =+G94+E95+F95 -> 4073.62 | H95: a
A96: 46004 | B96: RIFA 2 | C96: YAPPY BG DE MARIA DE LOS ANGELES MONTENEGRO DE LEON | D96: RIFA 2 | E96: 5 | G96: =+G95+E96+F96 -> 4078.62 | H96: a
A97: 46004 | B97: NAVIDAD | C97: BANCA MOVIL TRANSFERENCIA A 0427976265450 JESUS DE LEON RODRIGUEZ Abono musica navidad | D97: NAVIDAD | E97: 0 | F97: -50 | G97: =+G96+E97+F97 -> 4028.62 | H97: a
A98: 46004 | B98: RIFA 2 | C98: YAPPY BG DE JULIO ENRIQUE MEJIA POR Pago de los 4 numeros de la rifa casa 291 flia Mejia | D98: RIFA 2 | E98: 20 | G98: =+G97+E98+F98 -> 4048.62 | H98: a
A99: 46004 | B99: 18283 | C99: YAPPY BG DE MARTHA BIBIANA ACOSTA MARULANDA POR diciembre casa 105 familia Estrada | D99: 105 | E99: 15 | G99: =+G98+E99+F99 -> 4063.62 | H99: a
A100: 46004 | B100: 18284 | C100: BANCA MOVIL TRANSFERENCIA DE BARBARA ANN BENDIGO DE SANTAMARIA Ene 2026 seguridad Flia San | D100: 44 | E100: 15 | G100: =+G99+E100+F100 -> 4078.62 | H100: a
A101: 46004 | B101: RIFA 2 | C101: BANCA MOVIL TRANSFERENCIA DE BARBARA ANN BENDIGO DE SANTAMARIA colaboracion Rifa Flia San | D101: RIFA 2 | E101: 5 | G101: =+G100+E101+F101 -> 4083.62 | H101: a
A102: 46004 | B102: 18285 | C102: YAPPY BG DE VIELKA LUZMILA CUSATTI ANAYA- ENERO 2026 | D102: 20 | E102: 15 | G102: =+G101+E102+F102 -> 4098.62 | H102: a
...

Sheet mensual 2025
B1: Detalle de Pagos Mensuales
B2: Urbanizacion Alborada Año 2025
A4: Calle | B4: No. Casa | C4: Nombre | D4: Enero | E4: Febrero | F4: Marzo | G4: Abril | H4: Mayo | I4: Junio | J4: Julio | K4: Agosto | L4: Septiembre | M4: Octubre | N4: Noviembre | O4: Diciembre | P4: ene-26 | Q4: Total
A5: 1RA OESTE | B5: 1 | C5: Rubén Araúz \ Elisa Indira Powel Rodriguez | D5: 15 | E5: 15 | F5: 15 | G5: 15 | H5: 15 | I5: 15 | J5: 15 | K5: 15 | L5: 15 | M5: 15 | N5: 15 | Q5: =SUM(Tabla38[[#This Row],[Enero]:[ene-26]]) -> 165
A6: 1RA OESTE | B6: 2 | C6: Omar Cueto | D6: 15 | E6: 15 | F6: 15 | G6: 15 | H6: 15 | I6: 15 | J6: 15 | K6: 15 | L6: 15 | M6: 15 | N6: 15 | O6: 15 | P6: 15 | Q6: =SUM(Tabla38[[#This Row],[Enero]:[ene-26]]) -> 195
A7: 1RA OESTE | B7: 3 | C7: Leonardo Small / Gilda Gavidia | D7: 0 | E7: 15 | F7: 15 | G7: 15 | H7: 15 | Q7: =SUM(Tabla38[[#This Row],[Enero]:[ene-26]]) -> 60
A8: 1RA OESTE | B8: 4 | C8: Carlos Garay | D8: 15 | E8: 15 | F8: 15 | G8: 15 | H8: 15 | I8: 15 | J8: 15 | K8: 15 | L8: 15 | M8: 15 | N8: 15 | O8: 15 | Q8: =SUM(Tabla38[[#This Row],[Enero]:[ene-26]]) -> 180
A9: 1RA OESTE | B9: 5 | C9: Anselmo Forde | D9: 15 | E9: 15 | F9: 15 | G9: 15 | H9: 15 | I9: 15 | J9: 15 | K9: 15 | L9: 15 | M9: 15 | N9: 15 | O9: 15 | P9: 15 | Q9: =SUM(Tabla38[[#This Row],[Enero]:[ene-26]]) -> 195
A10: 1RA OESTE | B10: 6 | C10: Miguel Sanchez | D10: 15 | E10: 15 | F10: 15 | G10: 15 | H10: 15 | I10: 15 | J10: 20 | K10: 20 | L10: 15 | M10: 15 | N10: 15 | O10: 15 | Q10: =SUM(Tabla38[[#This Row],[Enero]:[ene-26]]) -> 190
A11: 1RA CENTRO | B11: 7 | C11: Alex Paz | D11: 15 | E11: 15 | F11: 15 | G11: 15 | H11: 15 | I11: 15 | Q11: =SUM(Tabla38[[#This Row],[Enero]:[ene-26]]) -> 90
A12: 1RA CENTRO | B12: 8 | C12: Darinka de Hoyos | D12: 0 | E12: 15 | F12: 15 | G12: 15 | H12: 15 | I12: 15 | J12: 15 | K12: 15 | L12: 15 | M12: 15 | N12: 15 | O12: 15 | Q12: =SUM(Tabla38[[#This Row],[Enero]:[ene-26]]) -> 165
A13: 1RA CENTRO | B13: 9 | C13: Aura del Carmen Hurtado/ Tahimy Guadalupe | D13: 15 | E13: 15 | F13: 15 | G13: 15 | H13: 15 | I13: 15 | J13: 15 | K13: 15 | L13: 15 | M13: 15 | N13: 15 | O13: 15 | Q13: =SUM(Tabla38[[#This Row],[Enero]:[ene-26]]) -> 180
A14: 1RA CENTRO | B14: 10 | C14: Miozotis del Carmen Olmos | D14: 15 | E14: 15 | F14: 15 | G14: 15 | H14: 15 | I14: 15 | J14: 15 | K14: 15 | L14: 15 | M14: 15 | N14: 15 | O14: 15 | Q14: =SUM(Tabla38[[#This Row],[Enero]:[ene-26]]) -> 180
A15: 1RA CENTRO | B15: 11 | C15: Mario Macías / NAIDA ELEYDA NG | D15: 15 | E15: 15 | F15: 15 | G15: 15 | H15: 15 | I15: 15 | J15: 15 | K15: 15 | L15: 15 | M15: 15 | N15: 15 | O15: 15 | P15: 45 | Q15: =SUM(Tabla38[[#This Row],[Enero]:[ene-26]]) -> 225
A16: 1RA CENTRO | B16: 12 | C16: Sheriska Escobar | D16: 15 | E16: 15 | F16: 15 | G16: 15 | H16: 15 | I16: 15 | J16: 15 | K16: 15 | Q16: =SUM(Tabla38[[#This Row],[Enero]:[ene-26]]) -> 120
A17: 1RA CENTRO | B17: 13 | C17: Flia. Ceballos | D17: 15 | E17: 15 | F17: 15 | G17: 15 | H17: 15 | I17: 15 | J17: 15 | K17: 15 | L17: 15 | M17: 15 | N17: 15 | O17: 15 | P17: 15 | Q17: =SUM(Tabla38[[#This Row],[Enero]:[ene-26]]) -> 195
A18: 1RA CENTRO | B18: 14 | C18: María Montenegro | D18: 15 | E18: 15 | F18: 15 | G18: 15 | H18: 15 | I18: 15 | J18: 15 | K18: 15 | L18: 15 | M18: 15 | N18: 15 | O18: 15 | Q18: =SUM(Tabla38[[#This Row],[Enero]:[ene-26]]) -> 180
A19: 1RA CENTRO | B19: 15 | C19: Susana Thachar | D19: 15 | E19: 15 | F19: 15 | G19: 15 | H19: 15 | I19: 15 | J19: 15 | K19: 15 | L19: 15 | M19: 15 | N19: 15 | O19: 15 | Q19: =SUM(Tabla38[[#This Row],[Enero]:[ene-26]]) -> 180
A20: 1RA CENTRO | B20: 16 | C20: Victor de Jesus Castillo / Ciara Jimenez | D20: 15 | E20: 15 | F20: 15 | G20: 15 | H20: 15 | I20: 15 | J20: 15 | K20: 15 | L20: 15 | M20: 15 | N20: 15 | O20: 15 | Q20: =SUM(Tabla38[[#This Row],[Enero]:[ene-26]]) -> 180
A21: 1RA ESTE | B21: 17 | C21: Daibelis Victoria | D21: 0 | E21: 0 | F21: 0 | Q21: =SUM(Tabla38[[#This Row],[Enero]:[ene-26]]) -> 0
A22: 1RA ESTE | B22: 18 | C22: Yaniza de Dreckett | D22: 15 | E22: 15 | F22: 15 | G22: 15 | H22: 15 | I22: 15 | J22: 15 | K22: 15 | L22: 15 | M22: 15 | N22: 15 | O22: 15 | Q22: =SUM(Tabla38[[#This Row],[Enero]:[ene-26]]) -> 180
A23: 1RA ESTE | B23: 19 | C23: Querubi Nereida | D23: 15 | E23: 15 | F23: 15 | G23: 15 | H23: 15 | I23: 15 | J23: 15 | K23: 15 | L23: 15 | M23: 15 | N23: 15 | O23: 15 | Q23: =SUM(Tabla38[[#This Row],[Enero]:[ene-26]]) -> 180
A24: 1RA ESTE | B24: 20 | C24: Vielka Cusati | D24: 15 | E24: =5+10 -> 15 | F24: 15 | G24: 15 | H24: 15 | I24: 15 | J24: 15 | K24: 15 | L24: 15 | M24: 15 | N24: 15 | O24: =15 -> 15 | P24: =15 -> 15 | Q24: =SUM(Tabla38[[#This Row],[Enero]:[ene-26]]) -> 195
A25: 1RA ESTE | B25: 21 | C25: Hector Ibarguen | D25: 15 | E25: 15 | F25: 15 | G25: 15 | H25: 15 | I25: 15 | J25: 15 | K25: 15 | L25: 15 | M25: 15 | N25: 15 | Q25: =SUM(Tabla38[[#This Row],[Enero]:[ene-26]]) -> 165
A26: 1RA ESTE | B26: 22 | C26: Juan Cedeño | D26: 0 | E26: 0 | F26: 0 | Q26: =SUM(Tabla38[[#This Row],[Enero]:[ene-26]]) -> 0
A27: 1RA ESTE | B27: 23 | C27: Humberto Guevara | D27: 15 | E27: 15 | F27: 15 | G27: 15 | H27: 15 | I27: 15 | J27: 15 | K27: 15 | L27: 15 | M27: 15 | N27: 15 | O27: 15 | Q27: =SUM(Tabla38[[#This Row],[Enero]:[ene-26]]) -> 180
A28: 2DA ESTE | B28: 24 | C28: Aikza Abrego | D28: 0 | E28: 0 | F28: 0 | Q28: =SUM(Tabla38[[#This Row],[Enero]:[ene-26]]) -> 0
A29: 2DA ESTE | B29: 25 | C29: Manuel de Jesus Medina | D29: 15 | E29: 15 | F29: 15 | G29: 15 | H29: 15 | I29: 15 | J29: 15 | K29: 15 | L29: 15 | M29: 15 | N29: 15 | O29: 15 | Q29: =SUM(Tabla38[[#This Row],[Enero]:[ene-26]]) -> 180
A30: 2DA ESTE | B30: 26 | C30: Dionisio Jimenez | D30: 15 | E30: 15 | F30: 15 | G30: 15 | H30: 15 | I30: 15 | J30: 15 | K30: 15 | L30: 15 | M30: 15 | N30: 15 | Q30: =SUM(Tabla38[[#This Row],[Enero]:[ene-26]]) -> 165
A31: 2DA ESTE | B31: 27 | C31: James Mick | D31: 15 | E31: 15 | F31: 15 | G31: 15 | H31: 15 | I31: 15 | J31: 15 | K31: 15 | Q31: =SUM(Tabla38[[#This Row],[Enero]:[ene-26]]) -> 120
A32: 2DA ESTE | B32: 28 | C32: Luis Sanchez | D32: 15 | E32: 15 | F32: 15 | G32: 15 | H32: 15 | I32: 15 | Q32: =SUM(Tabla38[[#This Row],[Enero]:[ene-26]]) -> 90
A33: 2DA ESTE | B33: 29 | C33: Indira Patel | D33: 0 | E33: 15 | F33: 15 | G33: 15 | H33: 15 | I33: 15 | J33: 15 | K33: 15 | L33: 15 | M33: 15 | N33: 15 | Q33: =SUM(Tabla38[[#This Row],[Enero]:[ene-26]]) -> 150
A34: 2DA ESTE | B34: 30 | C34: Aliza Jimenez | D34: 0 | E34: 15 | F34: 15 | G34: 15 | H34: 15 | I34: 15 | J34: 15 | K34: 15 | L34: 15 | M34: 15 | N34: 15 | O34: 15 | Q34: =SUM(Tabla38[[#This Row],[Enero]:[ene-26]]) -> 165
A35: 2DA CENTRO | B35: 31 | C35: Israel Santamaría | D35: 15 | E35: 15 | F35: 15 | G35: 15 | H35: 15 | I35: 15 | J35: 15 | K35: 15 | L35: 15 | M35: 15 | N35: 15 | O35: 15 | Q35: =SUM(Tabla38[[#This Row],[Enero]:[ene-26]]) -> 180
A36: 2DA CENTRO | B36: 32 | C36: Roberto Rudy | D36: 15 | E36: 15 | F36: 15 | G36: 15 | Q36: =SUM(Tabla38[[#This Row],[Enero]:[ene-26]]) -> 60
A37: 2DA CENTRO | B37: 33 | C37: Xenia Rosales de Betegon | D37: 15 | E37: 15 | F37: 15 | G37: 15 | H37: 15 | I37: 15 | J37: 15 | K37: 15 | L37: 15 | M37: 15 | Q37: =SUM(Tabla38[[#This Row],[Enero]:[ene-26]]) -> 150
A38: 2DA CENTRO | B38: 34 | C38: Sonia Rodríguez de Murillo | D38: 15 | E38: 15 | F38: 15 | G38: 15 | H38: 15 | I38: 15 | J38: 15 | K38: 15 | L38: 15 | M38: 15 | Q38: =SUM(Tabla38[[#This Row],[Enero]:[ene-26]]) -> 150
A39: 2DA CENTRO | B39: 35 | C39: Malibetza Ceballos | D39: 0 | E39: 15 | F39: 15 | G39: 15 | H39: 15 | I39: 15 | J39: 15 | K39: 15 | Q39: =SUM(Tabla38[[#This Row],[Enero]:[ene-26]]) -> 105
A40: 2DA CENTRO | B40: 36 | C40: Yirabel Girado | D40: 15 | E40: 15 | F40: 15 | G40: 15 | H40: 15 | I40: 15 | J40: 15 | K40: 15 | L40: 15 | M40: 15 | N40: 15 | O40: 15 | Q40: =SUM(Tabla38[[#This Row],[Enero]:[ene-26]]) -> 180
A41: 2DA CENTRO | B41: 37 | C41: Gladys Villanueva | D41: 15 | E41: 15 | F41: 15 | G41: 15 | H41: 15 | I41: 15 | J41: 15 | K41: 15 | L41: 15 | M41: 15 | N41: 15 | Q41: =SUM(Tabla38[[#This Row],[Enero]:[ene-26]]) -> 165
A42: 2DA CENTRO | B42: 38 | C42: Argelia Morris | D42: 0 | E42: 0 | F42: 0 | Q42: =SUM(Tabla38[[#This Row],[Enero]:[ene-26]]) -> 0
A43: 2DA CENTRO | B43: 39 | C43: Ernesto Small | D43: 0 | E43: 0 | F43: 15 | G43: 15 | H43: 15 | I43: 15 | J43: 15 | K43: 15 | L43: 15 | M43: 15 | N43: 15 | O43: 15 | Q43: =SUM(Tabla38[[#This Row],[Enero]:[ene-26]]) -> 150
A44: 2DA CENTRO | B44: 40 | C44: Felicia Gittens | D44: 15 | E44: 15 | F44: 15 | G44: 15 | H44: 15 | I44: 15 | J44: 15 | K44: 15 | L44: 15 | M44: 15 | N44: 15 | Q44: =SUM(Tabla38[[#This Row],[Enero]:[ene-26]]) -> 165
A45: 1RA OESTE | B45: 41 | C45: Alberto Chambers / YARIBEL RUIZ | D45: 15 | E45: 15 | F45: 15 | G45: 15 | H45: =5+15 -> 20 | I45: 15 | J45: 15 | K45: 15 | Q45: =SUM(Tabla38[[#This Row],[Enero]:[ene-26]]) -> 125
A46: 1RA OESTE | B46: 42 | C46: Jasmin Johnson | D46: 15 | E46: 15 | F46: 15 | G46: 15 | H46: 15 | I46: 15 | J46: 15 | Q46: =SUM(Tabla38[[#This Row],[Enero]:[ene-26]]) -> 105
A47: 1RA OESTE | B47: 43 | C47: Roberto Rodríguez | D47: 15 | E47: 15 | F47: 15 | G47: 15 | H47: 15 | I47: 15 | J47: 15 | K47: 15 | L47: 15 | M47: 15 | N47: 15 | Q47: =SUM(Tabla38[[#This Row],[Enero]:[ene-26]]) -> 165
A48: 1RA OESTE | B48: 44 | C48: Otman Santamaría /BARBARA BENDIGO DE SANTAMARIA | D48: 15 | E48: 15 | F48: 15 | G48: 15 | H48: 15 | I48: 15 | J48: 15 | K48: 15 | L48: 15 | M48: 15 | N48: 15 | O48: =15 -> 15 | P48: =15 -> 15 | Q48: =SUM(Tabla38[[#This Row],[Enero]:[ene-26]]) -> 195
A49: 1RA OESTE | B49: 45 | C49: Fernando Cummings | D49: 0 | E49: 0 | F49: 0 | Q49: =SUM(Tabla38[[#This Row],[Enero]:[ene-26]]) -> 0
A50: 1RA OESTE | B50: 46 | C50: Rafael Arnemann / SYAHMAR ORTIZ | D50: 15 | E50: 15 | F50: 15 | G50: 15 | H50: 15 | I50: 15 | J50: 15 | K50: 15 | L50: 15 | M50: 15 | N50: 15 | O50: 15 | Q50: =SUM(Tabla38[[#This Row],[Enero]:[ene-26]]) -> 180
A51: 1RA OESTE | B51: 47 | C51: Luzmila de Quintero | D51: 15 | E51: 15 | F51: 15 | G51: 15 | H51: 15 | I51: 15 | J51: 15 | K51: 15 | L51: 15 | M51: 15 | N51: 15 | Q51: =SUM(Tabla38[[#This Row],[Enero]:[ene-26]]) -> 165
A52: 2DA OESTE | B52: 48 | C52: Analida Jordan | D52: 0 | E52: 15 | F52: 15 | Q52: =SUM(Tabla38[[#This Row],[Enero]:[ene-26]]) -> 30
A53: 2DA OESTE | B53: 49 | C53: Eric Lasonder | D53: 0 | E53: 15 | F53: 15 | G53: 15 | H53: 15 | I53: 15 | J53: 15 | Q53: =SUM(Tabla38[[#This Row],[Enero]:[ene-26]]) -> 90
A54: 2DA OESTE | B54: 50 | C54: Pablo y Noris de Mejía | D54: 0 | E54: 15 | F54: 15 | G54: 15 | H54: 15 | I54: 15 | J54: 15 | K54: 15 | L54: 15 | M54: 15 | N54: 15 | O54: 15 | Q54: =SUM(Tabla38[[#This Row],[Enero]:[ene-26]]) -> 165
A55: 2DA OESTE | B55: 51 | C55: José Zurita/ Hernestina de Zurita- Panama Fast | D55: 15 | E55: 15 | F55: 15 | G55: 15 | H55: 15 | I55: 15 | J55: 15 | K55: 15 | L55: 15 | M55: 15 | N55: 15 | O55: 15 | Q55: =SUM(Tabla38[[#This Row],[Enero]:[ene-26]]) -> 180
A56: 2DA OESTE | B56: 52 | C56: Crisalida Solís | D56: 0 | E56: 15 | F56: 15 | G56: 15 | Q56: =SUM(Tabla38[[#This Row],[Enero]:[ene-26]]) -> 45
A57: 2DA OESTE | B57: 53 | C57: Osvaldo Herrera | E57: 15 | F57: 15 | G57: 15 | H57: 15 | I57: 15 | J57: 15 | K57: 15 | L57: 15 | M57: 15 | N57: 15 | Q57: =SUM(Tabla38[[#This Row],[Enero]:[ene-26]]) -> 150
A58: 2DA OESTE | B58: 54 | C58: Jerónimo Hernandez | D58: 15 | E58: 15 | F58: 15 | G58: 15 | H58: 15 | I58: 15 | J58: 15 | K58: 15 | L58: 15 | M58: 15 | N58: 15 | O58: 15 | P58: 15 | Q58: =SUM(Tabla38[[#This Row],[Enero]:[ene-26]]) -> 195
A59: 2DA OESTE | B59: 55 | C59: Alberto Benett | D59: 15 | E59: 15 | F59: 15 | G59: 15 | H59: 15 | I59: 15 | J59: 15 | K59: 15 | L59: 15 | M59: 15 | Q59: =SUM(Tabla38[[#This Row],[Enero]:[ene-26]]) -> 150
A60: 2DA OESTE | B60: 56 | C60: Nitzia Aguilar | D60: 15 | E60: 15 | F60: 15 | G60: 15 | H60: 15 | I60: 15 | Q60: =SUM(Tabla38[[#This Row],[Enero]:[ene-26]]) -> 90
A61: 2DA OESTE | B61: 57 | C61: Piedad de Cid | D61: 0 | E61: 15 | F61: 15 | G61: 15 | H61: 15 | I61: 15 | J61: 15 | K61: 15 | L61: 15 | M61: 15 | N61: 15 | O61: 15 | Q61: =SUM(Tabla38[[#This Row],[Enero]:[ene-26]]) -> 165
A62: 2DA OESTE | B62: 58 | C62: Martín Meneses | D62: 15 | E62: 15 | F62: 15 | G62: 15 | H62: 15 | I62: 15 | J62: 15 | K62: 15 | L62: 15 | M62: 15 | N62: 15 | O62: 15 | Q62: =SUM(Tabla38[[#This Row],[Enero]:[ene-26]]) -> 180
A63: 2DA OESTE | B63: 59 | C63: Ilka Mark | D63: 15 | E63: 15 | F63: 15 | G63: 15 | H63: 15 | I63: 15 | J63: 15 | K63: 15 | L63: 15 | M63: 15 | N63: 15 | O63: 15 | Q63: =SUM(Tabla38[[#This Row],[Enero]:[ene-26]]) -> 180
A64: 2DA OESTE | B64: 60 | C64: Mario Mitchel | D64: 0 | E64: 0 | F64: 0 | Q64: =SUM(Tabla38[[#This Row],[Enero]:[ene-26]]) -> 0
A65: 2DA CENTRO | B65: 61 | C65: Armando Gittens | D65: 15 | E65: 15 | F65: 15 | G65: 15 | H65: 15 | I65: 15 | J65: 15 | K65: 15 | Q65: =SUM(Tabla38[[#This Row],[Enero]:[ene-26]]) -> 120
A66: 2DA CENTRO | B66: 62 | C66: Armando Lee/ Mirna Reed de Lee | E66: 15 | F66: 15 | G66: 15 | H66: 15 | I66: 15 | J66: 15 | Q66: =SUM(Tabla38[[#This Row],[Enero]:[ene-26]]) -> 90
A67: 2DA CENTRO | B67: 63 | C67: Nidia de Martinez | D67: 15 | E67: 15 | F67: 15 | G67: 15 | H67: 15 | I67: 15 | J67: 15 | K67: 15 | L67: 15 | M67: 15 | N67: 15 | Q67: =SUM(Tabla38[[#This Row],[Enero]:[ene-26]]) -> 165
A68: 2DA CENTRO | B68: 64 | C68: Iliana Lee | D68: 15 | E68: 15 | F68: 15 | G68: 15 | H68: 15 | I68: 15 | J68: 15 | K68: 15 | L68: 15 | M68: 15 | N68: 15 | O68: 15 | Q68: =SUM(Tabla38[[#This Row],[Enero]:[ene-26]]) -> 180
A69: 2DA CENTRO | B69: 65 | C69: César López | D69: 0 | E69: 15 | F69: 15 | G69: 15 | H69: 15 | I69: 15 | J69: 15 | K69: 15 | L69: 15 | M69: 15 | N69: 15 | O69: 15 | Q69: =SUM(Tabla38[[#This Row],[Enero]:[ene-26]]) -> 165
A70: 2DA CENTRO | B70: 66 | C70: Dhayanara Mendoza | D70: 0 | E70: 0 | F70: 0 | Q70: =SUM(Tabla38[[#This Row],[Enero]:[ene-26]]) -> 0
A71: 2DA CENTRO | B71: 67 | C71: Emilio Lovet | D71: 15 | E71: 15 | F71: 15 | G71: 15 | H71: 15 | I71: 15 | J71: 15 | K71: 15 | L71: 15 | M71: 15 | Q71: =SUM(Tabla38[[#This Row],[Enero]:[ene-26]]) -> 150
A72: 2DA CENTRO | B72: 68 | C72: Wilfredo Pacheco/ EMELINA CATUY | D72: 0 | E72: 15 | F72: 15 | G72: 15 | H72: 15 | I72: 15 | J72: 15 | Q72: =SUM(Tabla38[[#This Row],[Enero]:[ene-26]]) -> 90
A73: 2DA CENTRO | B73: 69 | C73: Celina de Laurdes | D73: 15 | E73: 15 | F73: 15 | G73: 15 | H73: 15 | I73: 10 | J73: 15 | K73: 15 | Q73: =SUM(Tabla38[[#This Row],[Enero]:[ene-26]]) -> 115
A74: 2DA CENTRO | B74: 70 | C74: Damaris Jackson | D74: 0 | E74: 0 | F74: 0 | Q74: =SUM(Tabla38[[#This Row],[Enero]:[ene-26]]) -> 0
A75: 2DA CENTRO | B75: 71 | C75: Carlos Valdez | D75: 15 | E75: 15 | F75: 15 | G75: 15 | H75: 15 | I75: 15 | J75: 15 | K75: 15 | L75: 15 | M75: 15 | N75: 15 | O75: 15 | Q75: =SUM(Tabla38[[#This Row],[Enero]:[ene-26]]) -> 180
A76: 2DA CENTRO | B76: 72 | C76: Damian Montenegro | D76: 0 | E76: 0 | F76: 0 | Q76: =SUM(Tabla38[[#This Row],[Enero]:[ene-26]]) -> 0
A77: 2DA CENTRO | B77: 73 | C77: Yira de Morales | D77: 15 | E77: 15 | F77: 15 | G77: 15 | Q77: =SUM(Tabla38[[#This Row],[Enero]:[ene-26]]) -> 60
A78: 2DA CENTRO | B78: 74 | C78: Victor Rozette | D78: 0 | E78: 0 | F78: 0 | Q78: =SUM(Tabla38[[#This Row],[Enero]:[ene-26]]) -> 0
A79: 2DA ESTE | B79: 75 | C79: Vanessa Luzcando | D79: 15 | E79: 15 | F79: 15 | G79: 15 | H79: 15 | I79: 15 | J79: 15 | K79: 15 | L79: 15 | M79: 15 | N79: 15 | O79: 15 | P79: 15 | Q79: =SUM(Tabla38[[#This Row],[Enero]:[ene-26]]) -> 195
A80: 2DA ESTE | B80: 76 | C80: Oscar Gomez | D80: 0 | E80: 0 | F80: 0 | Q80: =SUM(Tabla38[[#This Row],[Enero]:[ene-26]]) -> 0
A81: 2DA ESTE | B81: 77 | C81: Enrique Herrera | D81: 15 | E81: 15 | F81: 15 | G81: 15 | H81: 15 | I81: 15 | J81: 15 | K81: 15 | L81: 15 | M81: 15 | N81: 15 | O81: 15 | P81: 20 | Q81: =SUM(Tabla38[[#This Row],[Enero]:[ene-26]]) -> 200
A82: 2DA ESTE | B82: 78 | C82: Antonio Brooks | D82: 15 | E82: 15 | F82: 15 | G82: 15 | H82: 15 | I82: 15 | J82: 15 | K82: 15 | L82: 15 | M82: 15 | Q82: =SUM(Tabla38[[#This Row],[Enero]:[ene-26]]) -> 150
A83: 2DA ESTE | B83: 79 | C83: Moises Gonzalez / Kaisha Rivas | D83: 15 | E83: 15 | F83: 15 | G83: 15 | H83: 15 | I83: 15 | J83: 15 | K83: 15 | L83: 15 | Q83: =SUM(Tabla38[[#This Row],[Enero]:[ene-26]]) -> 135
A84: 2DA ESTE | B84: 80 | C84: Juan Alvarado / Florencia Sinclair | D84: 15 | E84: 15 | F84: 15 | G84: 15 | H84: 15 | I84: 15 | J84: 15 | K84: 15 | L84: 15 | M84: 15 | N84: 15 | O84: 15 | Q84: =SUM(Tabla38[[#This Row],[Enero]:[ene-26]]) -> 180
A85: 2DA ESTE | B85: 81 | C85: Yomaira Avila | D85: 0 | E85: 0 | F85: 0 | Q85: =SUM(Tabla38[[#This Row],[Enero]:[ene-26]]) -> 0
A86: 3RA ESTE | B86: 82 | C86: Reynaldo Angarita | D86: 15 | E86: 15 | F86: 15 | M86: 15 | N86: 15 | O86: 15 | Q86: =SUM(Tabla38[[#This Row],[Enero]:[ene-26]]) -> 90
A87: 3RA ESTE | B87: 83 | C87: Amarilis Mata S. | D87: 0 | E87: 0 | F87: 0 | Q87: =SUM(Tabla38[[#This Row],[Enero]:[ene-26]]) -> 0
A88: 3RA ESTE | B88: 84 | C88: Javier Campo | D88: 0 | E88: 0 | F88: 0 | Q88: =SUM(Tabla38[[#This Row],[Enero]:[ene-26]]) -> 0
